Workbook
Name base_year: 'Cover Page'!$F$15
Name bs_check: '3-Statement'!$F$104
Name circularity: 'Cover Page'!$F$19
Name company_name: 'Cover Page'!$C$5
Name money: Inputs!$E$13

Sheet Cover Page
C5: BT GROUP PLC
C6: BT.L
C8: Author: | F8: Opeoluwa Kuku
C9: School ID: | F9: H00529768
C10: Course: | F10: Corporate Finance
C11: Course Code: | F11: C31CF
C12: Scalling: | F12: Millions GBP
C13: Historical Period: | F13: 31/Mar/2022 - 31/Mar/2026
C14: Forecast Period: | F14: 31/Mar/2027 - 31/Mar/2031
C15: Base Year: | F15: 2026
C16: Valuation Date: | F16: 46319
C17: Current Share Price: | F17: 211.8 | U17: Do Not delete
C18: Balance Sheet: | F18: =IF(bs_check=0,"Balanced","Error!!!") -> Balanced | U18: 1
C19: Circularity: | F19: 1 | U19: 0

Sheet Investment recommendation
B2: =company_name -> BT GROUP PLC
C3: Investment Recommendation
B8: Dashboard
D10: ="Current Share Price: "&'Cover Page'!F17 -> Current Share Price: 211.8
D11: Recommendation: Buy
D12: Date | E12: ='Cover Page'!F16 -> 46319
D13: Valuation Summary | V13: Valuation Ranges
V41: Data
Z43: High | AA43: Mid | AB43: Low
V44: =D56 -> Dividend Discount Model | Z44: =G71 -> 157.46247 | AA44: =I72 -> 128.29569 | AB44: =K74 -> 103.70133
V45: =D57 -> FCFF/FCFE Model | Z45: =W71 -> 434.17676 | AA45: =X73 -> 319.75487 | AB45: =Z74 -> 227.66208
V46: =D58 -> Residual Income | Z46: =O71 -> 314.26293 | AA46: =Q72 -> 254.41506 | AB46: =S74 -> 210.59713
V47: =D59 -> Comparables | Z47: =W56 -> 376.62783 | AA47: =W57 -> 225.95691 | AB47: =W58 -> 136.80467
C50: Inputs & Outputs
D53: Main Outputs | N53: Main Inputs | T53: Comparables (P/E)
W55: Share price/share
D56: Dividend Discount Model | E56: Pence/Sh | F56: =DDM!F43 -> 128.29569 | N56: WACC | P56: % | Q56: ='Cost of Capital'!I17 -> 0.068424935 | T56: =COMPS!C16 -> Maximum | U56: x | V56: =COMPS!F16 -> 23.850831 | W56: =V56*$V$59*100 -> 376.62783
D57: FCFF/FCFE Model | E57: Pence/Sh | F57: =FCFF!F48 -> 319.75487 | N57: Cost of Equity | P57: % | Q57: ='Cost of Equity'!E15 -> 0.092604508 | T57: =COMPS!C17 -> Average | U57: x | V57: =COMPS!F17 -> 14.309245 | W57: =V57*$V$59*100 -> 225.95691
D58: Residual Income | E58: Pence/Sh | F58: ='RES.INC'!F62 -> 254.41506 | N58: Perpetual Growth Rate | P58: % | Q58: =DDM!F17 -> 0.020296084 | T58: =COMPS!C19 -> Minimum | U58: x | V58: =COMPS!F19 -> 8.6634731 | W58: =V58*$V$59*100 -> 136.80467
D59: Comparables | E59: Pence/Sh | F59: =COMPS!I35 -> 225.95691 | N59: UK GDP Growth Rate | P59: % | Q59: =Inputs!F32 -> 0.014 | T59: =COMPS!G34 -> Forward EPS | U59: =COMPS!H34 -> [£'M] | V59: =COMPS!I34 -> 0.15790973
N60: Current Share Price | P60: Pence/Sh | Q60: ='Cover Page'!F17 -> 211.8
C64: Sensitivity
G67: Dividend Discount Model | N67: Residual Income | V67: FCFF/FCFE Model
G69: Cost of Equity | N69: Cost of Equity | W69: WACC
F70: =DDM!F43 -> 128.29569 | G70: 0.083 | H70: 0.088 | I70: 0.092604508 | J70: 0.098 | K70: 0.103 | M70: Growth Rate | N70: ='RES.INC'!F62 -> 254.41506 | O70: 0.082604508 | P70: 0.087604508 | Q70: 0.092604508 | R70: 0.097604508 | S70: 0.10260451 | U70: Growth Rate | V70: =FCFF!F48 -> 319.75487 | W70: 0.063424935 | X70: 0.068424935 | Y70: 0.073424935 | Z70: 0.078424935
E71: Growth Rate | F71: 0.025296084 | G71: 157.46247 | H71: 145.23713 | I71: 135.58494 | J71: 125.82992 | K71: 117.99898 | N71: 0.025296084 | O71: 314.26293 | P71: 286.26707 | Q71: 262.42698 | R71: 241.87968 | S71: 223.98549 | V71: 0.02 | W71: 434.17676 | X71: 371.20253 | Y71: 320.03836 | Z71: 277.65164
F72: 0.020296084 | G72: 147.35287 | H72: 136.75723 | I72: 128.29569 | J72: 119.65653 | K72: 112.65684 | N72: 0.020296084 | O72: 301.2184 | P72: 276.07842 | Q72: 254.41506 | R72: 235.55285 | S72: 218.9805 | V72: 0.017 | W72: 399.99658 | X72: 343.97803 | Y72: 297.90954 | Z72: 259.36079
F73: 0.015296084 | G73: 138.73647 | H73: 129.44369 | I73: 121.94932 | J73: 114.22958 | K73: 107.92381 | N73: 0.015296084 | O73: 290.11188 | P73: 267.29883 | Q73: 247.4395 | R73: 229.9947 | S73: 214.54876 | V73: 0.014 | W73: 369.96575 | X73: 319.75487 | Y73: 278.01501 | Z73: 242.7734
F74: 0.010296084 | G74: 131.30521 | H74: 123.07135 | I74: 116.374 | J74: 109.42141 | K74: 103.70133 | N74: 0.010296084 | O74: 280.54136 | P74: 259.65489 | Q74: 241.31143 | R74: 225.07315 | S74: 210.59713 | V74: 0.011 | W74: 343.37192 | X74: 298.06264 | Y74: 260.03266 | Z74: 227.66208

Sheet Inputs
B2: =company_name -> BT GROUP PLC
C3: Inputs and Assumptions
C5: ="Balance Sheet Check: "&IF(bs_check=0,"Balanced as all things should be","Error!!!") -> Balance Sheet Check: Balanced as all things should be
D6: Description | E6: Units | F6: Inputs | I6: Hist | J6: Hist | K6: Hist | L6: Hist | M6: Hist | N6: Forecast | O6: Forecast | P6: Forecast | Q6: Forecast | R6: Forecast | S6: Term
I7: 2022 | J7: 2023 | K7: 2024 | L7: 2025 | M7: =base_year -> 2026 | N7: =M7+1 -> 2027 | O7: =N7+1 -> 2028 | P7: =O7+1 -> 2029 | Q7: =P7+1 -> 2030 | R7: =Q7+1 -> 2031
C9: Style Guide & Timing assumption
D10: Historicals | E10: 1234
D11: Inputs | E11: 1234
D12: Linked Cells | E12: 1234 | M12: Valuation | N12: Discrete Period | S12: Term
D13: Units | E13: [£'M] | M13: (YYYY-MM-DD) | N13: (YYYY-MM-DD) | O13: (YYYY-MM-DD) | P13: (YYYY-MM-DD) | Q13: (YYYY-MM-DD) | R13: (YYYY-MM-DD)
D14: Notes | E14: Statement | M14: ='Cover Page'!F16 -> 46319 | N14: 46477 | O14: =EDATE(N14,12) -> 46843 | P14: =EDATE(O14,12) -> 47208 | Q14: =EDATE(P14,12) -> 47573 | R14: =EDATE(Q14,12) -> 47938
D15: Numbers | E15: 1234
D16: Percent | E16: 0.121
D17: Sub total | E17: 1234
D18: Total | E18: 12.35
D19: Multiples | E19: 12
D20: Heading 1 | E20: BT
D21: Heading 2 | E21: BT
D22: Heading 3 | E22: BT
B24: Income Statement Inputs and Assumptions
C25: Revenue
D26: ='3-Statement'!D11 -> Revenue | I26: ='3-Statement'!I11 -> 20845 | J26: ='3-Statement'!J11 -> 20669 | K26: ='3-Statement'!K11 -> 20835 | L26: ='3-Statement'!L11 -> 20370 | M26: ='3-Statement'!M11 -> 19646 | N26: =M26*(1+N27) -> 19319.684 | O26: =N26*(1+O27) -> 19416.283 | P26: =O26*(1+P27) -> 19688.111 | Q26: =P26*(1+Q27) -> 19963.744 | R26: =Q26*(1+R27) -> 20243.237
D27: Growth Rate | J27: =(J26-I26)/I26 -> -0.0084432718 | K27: =(K26-J26)/J26 -> 0.0080313513 | L27: =(L26-K26)/K26 -> -0.022318215 | M27: =(M26-L26)/L26 -> -0.035542464 | N27: -0.016609776 | O27: 0.005 | P27: 0.014 | Q27: 0.014 | R27: 0.014
D28: Revenue contracting " mainly driven by lower International revenue including the impact of divesting entities in the year" - Q2 earnings report
D29: Due to the structural changes, I assume that the contraction will continue and eventually BT.L will grow again in line with the economy based on the expected benefits from their transformation and the growth in the sale of FTTP service. This is also in line with their guidance
D30: Growth is expected from FY2028 as per BT.L's earnings report guidance
D32: UK GDP Growth rate Q2 Y-o-Y | F32: 0.014 | L32: 0.01 | M32: 0.014 | N32: =$F$32 -> 0.014 | O32: =$F$32 -> 0.014 | P32: =$F$32 -> 0.014 | Q32: =$F$32 -> 0.014 | R32: =$F$32 -> 0.014
D33: United Kingdom GDP Annual Growth Rate
D34: My economic growth rate is based on "Trading Economics" data. I assume the UK's economy will grow based on the average of the last two y-o-y growth rates
C37: Cost of Sales
D38: ='3-Statement'!D12 -> Cost of Sales | E38: =money -> [£'M] | I38: =-'3-Statement'!I12 -> 7951 | J38: =-'3-Statement'!J12 -> 7820 | K38: =-'3-Statement'!K12 -> 7658 | L38: =-'3-Statement'!L12 -> 6777 | M38: =-'3-Statement'!M12 -> 6474 | N38: =N26*(1-N41) -> 6305.082 | O38: =O26*(1-O41) -> 6274.6218 | P38: =P26*(1-P41) -> 6299.3152 | Q38: =Q26*(1-Q41) -> 6323.1667 | R38: =R26*(1-R41) -> 6346.1423
D39: Growth rate | E39: % | J39: =(J38-I38)/I38 -> -0.016475915 | K39: =(K38-J38)/J38 -> -0.020716113 | L39: =(L38-K38)/K38 -> -0.11504309 | M39: =(M38-L38)/L38 -> -0.044710049
D40: ='3-Statement'!D13 -> Gross Profit | E40: =money -> [£'M] | I40: ='3-Statement'!I13 -> 12894 | J40: ='3-Statement'!J13 -> 12849 | K40: ='3-Statement'!K13 -> 13177 | L40: ='3-Statement'!L13 -> 13593 | M40: ='3-Statement'!M13 -> 13172
D41: Gross Profit Margin | E41: =money -> [£'M] | I41: =I40/I26 -> 0.6185656 | J41: =J40/J26 -> 0.62165562 | K41: =K40/K26 -> 0.6324454 | L41: =L40/L26 -> 0.66730486 | M41: =M40/M26 -> 0.67046727 | N41: =M41*(1+N42) -> 0.67364467 | O41: =N41*(1+O42) -> 0.67683712 | P41: =O41*(1+P42) -> 0.68004471 | Q41: =P41*(1+Q42) -> 0.68326749 | R41: =Q41*(1+R42) -> 0.68650555
D42: Growth rate | E42: % | J42: =J41/I41-1 -> 0.0049954544 | K42: =K41/J41-1 -> 0.017356531 | L42: =L41/K41-1 -> 0.055118522 | M42: =M41/L41-1 -> 0.0047390792 | N42: =M42 -> 0.0047390792 | O42: =N42 -> 0.0047390792 | P42: =O42 -> 0.0047390792 | Q42: =P42 -> 0.0047390792 | R42: =Q42 -> 0.0047390792
D44: BT.L is currently undergoing a cost cutting and cost efficiency program.
D45: I can assume that the benefits of this initiative would be reflected in the forecast period before it normalizes, hence I can forecasst a modest continued growth in gross profit margin.
C46: SG&A
D47: ='3-Statement'!D16 -> SGA | I47: =-'3-Statement'!I16 -> 5777 | J47: =-'3-Statement'!J16 -> 5496 | K47: =-'3-Statement'!K16 -> 6353 | L47: =-'3-Statement'!L16 -> 6482 | M47: =-'3-Statement'!M16 -> 5808 | N47: =N48*N26 -> 5648.3478 | O47: =O48*O26 -> 5735.6987 | P47: =P48*P26 -> 5932.1629 | Q47: =Q48*Q26 -> 6000.7884 | R47: =R48*R26 -> 6013.4269
D48: SG&A to Revenue (%) | I48: =I47/I26 -> 0.2771408 | J48: =J47/J26 -> 0.26590546 | K48: =K47/K26 -> 0.30491961 | L48: =L47/L26 -> 0.31821306 | M48: =M47/M26 -> 0.2956327 | N48: =AVERAGE(I48:M48) -> 0.29236233 | O48: =AVERAGE(J48:N48) -> 0.29540663 | P48: =AVERAGE(K48:O48) -> 0.30130686 | Q48: =AVERAGE(L48:P48) -> 0.30058432 | R48: =AVERAGE(M48:Q48) -> 0.29705857
C50: Dividend
D51: Dividends based on policy | I51: ='Hist - CS'!F96 -> 755 | J51: ='Hist - CS'!E96 -> 760 | K51: ='Hist - CS'!D96 -> 783 | L51: ='Hist - CS'!C96 -> 801 | M51: ='Hist - CS'!B96 -> 822 | N51: =(N53/100)*$F$59/1000000 -> 854.18687 | O51: =(O53/100)*$F$59/1000000 -> 879.81247 | P51: =(P53/100)*$F$59/1000000 -> 906.20685 | Q51: =(Q53/100)*$F$59/1000000 -> 933.39305 | R51: =(R53/100)*$F$59/1000000 -> 961.39484
D52: Payout ratio | I52: =I51/'3-Statement'!I36 -> 0.59262166 | J52: =J51/'3-Statement'!J36 -> 0.39895013 | K52: =K51/'3-Statement'!K36 -> 0.91578947 | L52: =L51/'3-Statement'!L36 -> 0.75996205 | M52: =M51/'3-Statement'!M36 -> 0.7632312 | N52: =N51/'3-Statement'!N36 -> 0.5426898 | O52: =O51/'3-Statement'!O36 -> 0.489139 | P52: =P51/'3-Statement'!P36 -> 0.46018345 | ... R52: =R51/'3-Statement'!R36 -> 0.37067355
D53: Dividends Policy | E53: Pence/Sh | F53: 0.03 | L53: 8.16 | M53: 8.32 | N53: =M53*(1+$F$53) -> 8.5696 | O53: =N53*(1+$F$53) -> 8.826688 | P53: =O53*(1+$F$53) -> 9.0914886 | Q53: =P53*(1+$F$53) -> 9.3642333 | R53: =Q53*(1+$F$53) -> 9.6451603
D54: Dividends based on forecast
D56: Dividend Policy based on earnings report and forecast based on this guidance "The Board has adopted a new policy to grow the dividend by low to mid single digit percent per annum in FY27 and onwards" page 157 of financial statement report
C58: Valuation
D59: Shares Outstanding | E59: Unit | F59: =9967639866 -> 9967639866
D60: Current Share Price | E60: Pence/Sh | F60: 209.7
D61: 10 Year Uk Bond Yield | E61: % | F61: 0.0537
D62: ='3-Statement'!D34 -> Equity in Earnings/(Loss) of Affiliates (after Taxes) | N62: 0 | O62: 0 | P62: 0 | Q62: 0 | R62: 0
D64: Source for 10yr Uk Bond Yield: Bloomberg www.bloomberg.com/markets/rates-bonds/government-bonds/uk
C66: Tax
D67: Uk Corporate Tax Rate | E67: % | F67: 0.25
D68: Page 5 of the earnings report states that the effective tax rate was 25% for the last period, inline with the corporate Tax rate
D70: ='3-Statement'!D28 -> EBT | K70: ='3-Statement'!K28 -> 1207 | L70: ='3-Statement'!L28 -> 1342 | M70: ='3-Statement'!M28 -> 1646
D71: ='3-Statement'!D30 -> Current Taxes | K71: ='3-Statement'!K30 -> -97 | L71: ='3-Statement'!L30 -> -84 | M71: ='3-Statement'!M30 -> -82
D72: ='3-Statement'!D31 -> Deferred Taxes | K72: ='3-Statement'!K31 -> -234 | L72: ='3-Statement'!L31 -> -196 | M72: ='3-Statement'!M31 -> -277
D73: ='3-Statement'!D32 -> Total Taxes | K73: ='3-Statement'!K32 -> -331 | L73: ='3-Statement'!L32 -> -280 | M73: ='3-Statement'!M32 -> -359
D75: Effective Tax Rate | K75: =-K73/K70 -> 0.27423364 | L75: =-L73/L70 -> 0.20864382 | M75: =-M73/M70 -> 0.2181045
D76: Implied Taxable Income | K76: =-K71/K75 -> 353.71299 | L76: =-L71/L75 -> 402.6 | M76: =-M71/M75 -> 375.96657
D77: Implied Government Reduction in EBT/Timing difference | K77: =K70-K76 -> 853.28701 | L77: =L70-L76 -> 939.4 | M77: =M70-M76 -> 1270.0334 | N77: 1270.0334 | O77: 1270.0334 | P77: 1270.0334 | Q77: 1270.0334 | R77: 1270.0334
D79: I understand this assumption can be more accurate/detailed but the goal here is to maintain a similar current-deferred tax ratio for valuation purpose
B82: Balance Sheet Inputs & Assumptions
C84: Current Asset
D85: ='Hist - BS'!B240 -> Inventories | E85: % of COGS | L85: ='Hist - BS'!J240/L38 -> 0.04884167 | M85: ='Hist - BS'!K240/M38 -> 0.056533828 | N85: =AVERAGE(L85:M85) -> 0.052687749 | O85: =AVERAGE(M85:N85) -> 0.054610788 | P85: =AVERAGE(N85:O85) -> 0.053649269 | Q85: =AVERAGE(O85:P85) -> 0.054130028 | R85: =AVERAGE(P85:Q85) -> 0.053889649
D86: ='Hist - BS'!B314 -> Trade and other receivables | E86: % of revenues | L86: ='Hist - BS'!J314/L26 -> 0.170054 | M86: ='Hist - BS'!K314/M26 -> 0.18064746 | N86: =AVERAGE(L86:M86) -> 0.17535073 | O86: =AVERAGE(M86:N86) -> 0.1779991 | P86: =AVERAGE(N86:O86) -> 0.17667491 | Q86: =AVERAGE(O86:P86) -> 0.177337 | R86: =AVERAGE(P86:Q86) -> 0.17700596
D87: ='Hist - BS'!B242 -> Preference shares in joint | E87: Ending Balance | L87: ='Hist - BS'!J242 -> 161 | M87: ='Hist - BS'!K242 -> 282 | N87: =M87 -> 282 | O87: =N87 -> 282 | P87: =O87 -> 282 | Q87: =P87 -> 282 | R87: =Q87 -> 282
D88: ='Hist - BS'!B243 -> Contract assets | E88: % of COGS | L88: ='Hist - BS'!J243/L38 -> 0.17618415 | M88: ='Hist - BS'!K243/M38 -> 0.15585419 | N88: =M88 -> 0.15585419 | O88: =N88 -> 0.15585419 | P88: =O88 -> 0.15585419 | Q88: =P88 -> 0.15585419 | R88: =Q88 -> 0.15585419
D89: ='Hist - BS'!B244 -> Assets classified as held | E89: Ending Balance | L89: ='Hist - BS'!J244 -> 245 | M89: ='Hist - BS'!K244 -> 0 | N89: 0 | O89: 0 | P89: 0 | Q89: 0 | R89: 0
D90: ='Hist - BS'!B309 -> Short Term Investments | E90: Ending Balance per Page 6 stating the divestment period is over | L90: ='Hist - BS'!J309 -> 2761 | M90: ='Hist - BS'!K309 -> 1550 | N90: =M90 -> 1550 | O90: =N90 -> 1550 | P90: =O90 -> 1550 | Q90: =P90 -> 1550 | R90: =Q90 -> 1550
C92: Non-Current Assets
D93: ='Hist - BS'!B253 -> Goodwill | E93: Ending balance | L93: ='Hist - BS'!J253 -> 7310 | M93: ='Hist - BS'!K253 -> 7305 | N93: 7305 | O93: 7305 | P93: 7305 | Q93: 7305 | R93: 7305
D94: ='Hist - BS'!B254 -> Other intangible assets | E94: % of COGS | L94: ='Hist - BS'!J254/L38 -> 0.75593921 | M94: ='Hist - BS'!K254/M38 -> 0.72026568 | N94: =AVERAGE(L94:M94) -> 0.73810244 | O94: =AVERAGE(M94:N94) -> 0.72918406 | P94: =AVERAGE(N94:O94) -> 0.73364325 | Q94: =AVERAGE(O94:P94) -> 0.73141366 | R94: =AVERAGE(P94:Q94) -> 0.73252845
D95: ='Hist - BS'!B325 -> Long Term Investments | E95: Ending balance | L95: ='Hist - BS'!J325 -> 921 | M95: ='Hist - BS'!K325 -> 850 | N95: =M95 -> 850 | O95: =N95 -> 850 | P95: =O95 -> 850 | Q95: =P95 -> 850 | R95: =Q95 -> 850
D96: ='Hist - BS'!B259 -> Joint ventures and associates | E96: Ending balance | L96: ='Hist - BS'!J259 -> 252 | M96: ='Hist - BS'!K259 -> 4 | N96: 4 | O96: 4 | P96: 4 | Q96: 4 | R96: 4
D97: ='Hist - BS'!B260 -> Trade and other receivables | E97: % of revenue | L97: ='Hist - BS'!J260/L26 -> 0.03215513 | M97: ='Hist - BS'!K260/M26 -> 0.034663545 | N97: =AVERAGE(L97:M97) -> 0.033409337 | O97: =AVERAGE(M97:N97) -> 0.034036441 | P97: =AVERAGE(N97:O97) -> 0.033722889 | Q97: =AVERAGE(O97:P97) -> 0.033879665 | R97: =AVERAGE(P97:Q97) -> 0.033801277
D98: ='Hist - BS'!B261 -> Preference shares in joint | E98: Ending balance | L98: ='Hist - BS'!J261 -> 234 | M98: ='Hist - BS'!K261 -> 0 | N98: 0 | O98: 0 | P98: 0 | Q98: 0 | R98: 0
D99: ='Hist - BS'!B262 -> Contract assets | E99: % of COGS | L99: ='Hist - BS'!J262/L38 -> 0.045152722 | M99: ='Hist - BS'!K262/M38 -> 0.059005252 | N99: =AVERAGE(L99:M99) -> 0.052078987 | O99: =AVERAGE(M99:N99) -> 0.055542119 | P99: =AVERAGE(N99:O99) -> 0.053810553 | Q99: =AVERAGE(O99:P99) -> 0.054676336 | R99: =AVERAGE(P99:Q99) -> 0.054243445
D100: ='Hist - BS'!B263 -> Retirement benefit surplus | E100: % of SGA | L100: ='Hist - BS'!J263/L47 -> 0.021906819 | M100: ='Hist - BS'!K263/M47 -> 0.029269972 | N100: =AVERAGE(L100:M100) -> 0.025588396 | O100: =AVERAGE(M100:N100) -> 0.027429184 | P100: =AVERAGE(N100:O100) -> 0.02650879 | Q100: =AVERAGE(O100:P100) -> 0.026968987 | R100: =AVERAGE(P100:Q100) -> 0.026738888
D101: ='Hist - BS'!B264 -> Deferred tax assets | L101: ='Hist - BS'!J264 -> 959 | M101: ='Hist - BS'!K264 -> 1124
D103: PP&E Assumptions
D104: Capital Expenditures | I104: ='Hist - CS'!F46 -> 4607 | J104: ='Hist - CS'!E46 -> 5307 | K104: ='Hist - CS'!D46 -> 4969 | L104: ='Hist - CS'!C46 -> 4937 | M104: ='Hist - CS'!B46 -> 5169 | N104: =M104*(1+$N$105) -> 4958.7828 | O104: =N104*(1+$N$105) -> 4757.1148 | P104: =O104*(1+$N$105) -> 4563.6485 | Q104: =P104*(1+$N$105) -> 4378.0502 | R104: 4200
D105: "By the end of the decade capital expenditure excluding spectrum will reduce by more than £1bn from the FY26 level" - Earnings Report Mar 2026 | N105: =_xlfn.RRI(5,M104,R104) -> -0.040668839
D106: Depreciation | I106: =-'3-Statement'!I20 -> 4405 | J106: =-'3-Statement'!J20 -> 4742 | K106: =-'3-Statement'!K20 -> 4792 | L106: =-'3-Statement'!L20 -> 4883 | M106: =-'3-Statement'!M20 -> 4853 | N106: =N104*N107 -> 4780.0893 | O106: =O104*O107 -> 4525.9918 | P106: =P104*P107 -> 4370.5595 | Q106: =Q104*Q107 -> 4179.0789 | R106: =R104*R107 -> 4015.7088
E107: % of Capex | I107: =I106/I104 -> 0.95615368 | J107: =J106/J104 -> 0.89353684 | K107: =K106/K104 -> 0.96437915 | L107: =L106/L104 -> 0.98906218 | M107: =M106/M104 -> 0.93886632 | N107: =AVERAGE(L107:M107) -> 0.96396425 | O107: =AVERAGE(M107:N107) -> 0.95141528 | P107: =AVERAGE(N107:O107) -> 0.95768977 | Q107: =AVERAGE(O107:P107) -> 0.95455253 | R107: =AVERAGE(P107:Q107) -> 0.95612115
D108: On Page 10 of the earnings report, under the financials metrics, it can be seen that depreciation tracks investments
C111: Current Liabilities
D112: ='Hist - BS'!B269 -> Derivative financial instruments | E112: Ending Balance | L112: ='Hist - BS'!J269 -> 106 | M112: ='Hist - BS'!K269 -> 85 | N112: =M112 -> 85 | O112: =N112 -> 85 | P112: =O112 -> 85 | Q112: =P112 -> 85 | R112: =Q112 -> 85 | S112: =R112 -> 85
D113: ='Hist - BS'!B270 -> Trade and other payables | E113: % of COGS | L113: ='Hist - BS'!J270/L38 -> 0.87870739 | M113: ='Hist - BS'!K270/M38 -> 0.91056534 | N113: =AVERAGE(L113:M113) -> 0.89463637 | O113: =AVERAGE(M113:N113) -> 0.90260085 | P113: =AVERAGE(N113:O113) -> 0.89861861 | Q113: =AVERAGE(O113:P113) -> 0.90060973 | R113: =AVERAGE(P113:Q113) -> 0.89961417 | S113: =AVERAGE(Q113:R113) -> 0.90011195
D114: ='Hist - BS'!B271 -> Contract liabilities | E114: % of Revenue | L114: ='Hist - BS'!J271/L26 -> 0.04413353 | M114: ='Hist - BS'!K271/M26 -> 0.049017612 | N114: =AVERAGE(L114:M114) -> 0.046575571 | O114: =AVERAGE(M114:N114) -> 0.047796591 | P114: =AVERAGE(N114:O114) -> 0.047186081 | Q114: =AVERAGE(O114:P114) -> 0.047491336 | R114: =AVERAGE(P114:Q114) -> 0.047338709 | S114: =AVERAGE(Q114:R114) -> 0.047415022
D115: ='Hist - BS'!B272 -> Lease liabilities | E115: % of Revenue | L115: ='Hist - BS'!J272/L26 -> 0.03460972 | M115: ='Hist - BS'!K272/M26 -> 0.039651838 | N115: =AVERAGE(L115:M115) -> 0.037130779 | O115: =AVERAGE(M115:N115) -> 0.038391308 | P115: =AVERAGE(N115:O115) -> 0.037761044 | Q115: =AVERAGE(O115:P115) -> 0.038076176 | R115: =AVERAGE(P115:Q115) -> 0.03791861 | S115: =AVERAGE(Q115:R115) -> 0.037997393
D116: ='Hist - BS'!B273 -> Liabilities held for sale | E116: Ending Balance | L116: ='Hist - BS'!J273 -> 188 | M116: ='Hist - BS'!K273 -> 0 | N116: =M116 -> 0 | O116: =N116 -> 0 | P116: =O116 -> 0 | Q116: =P116 -> 0 | R116: =Q116 -> 0 | S116: =R116 -> 0
D117: ='Hist - BS'!B274 -> Current tax liabilities | E117: % of EBT | L117: ='Hist - BS'!J274/'3-Statement'!L28 -> 0.061102832 | M117: ='Hist - BS'!K274/'3-Statement'!M28 -> 0.040097205 | N117: =M117 -> 0.040097205 | O117: =N117 -> 0.040097205 | P117: =O117 -> 0.040097205 | Q117: =P117 -> 0.040097205 | R117: =Q117 -> 0.040097205 | S117: =R117 -> 0.040097205
D118: ='Hist - BS'!B275 -> Provisions | E118: % of EBT | L118: ='Hist - BS'!J275/'3-Statement'!L28 -> 0.19225037 | M118: ='Hist - BS'!K275/'3-Statement'!M28 -> 0.12211422 | N118: =M118 -> 0.12211422 | O118: =N118 -> 0.12211422 | P118: =O118 -> 0.12211422 | Q118: =P118 -> 0.12211422 | R118: =Q118 -> 0.12211422 | S118: =R118 -> 0.12211422
C120: Non-Current Liabilities
D121: ='Hist - BS'!B280 -> Loans and other borrowings | L121: ='Hist - BS'!J331 -> 18762 | M121: ='Hist - BS'!K331 -> 18536
D122: ='Hist - BS'!B281 -> Derivative financial instruments | E122: Ending Balance | L122: ='Hist - BS'!J281 -> 391 | M122: ='Hist - BS'!K281 -> 313 | N122: 313 | O122: 313 | P122: 313 | Q122: 313 | R122: 313 | S122: 313
D123: ='Hist - BS'!B282 -> Contract liabilities | E123: % of Revenue | L123: ='Hist - BS'!J282/L26 -> 0.012616593 | M123: ='Hist - BS'!K282/M26 -> 0.013946859 | N123: =M123 -> 0.013946859 | O123: =N123 -> 0.013946859 | P123: =O123 -> 0.013946859 | Q123: =P123 -> 0.013946859 | R123: =Q123 -> 0.013946859 | S123: =R123 -> 0.013946859
D124: ='Hist - BS'!B283 -> Lease liabilities | E124: Ending Balance | L124: ='Hist - BS'!J283 -> 3866 | M124: ='Hist - BS'!K283 -> 3405 | N124: =M124 -> 3405 | O124: =N124 -> 3405 | P124: =O124 -> 3405 | Q124: =P124 -> 3405 | R124: =Q124 -> 3405 | S124: =R124 -> 3405
...

Sheet DDM
B2: =company_name -> BT GROUP PLC
C3: Dividend Discount Model
C5: ="Balance Sheet Check: "&IF(bs_check=0,"Balanced as all things should be","Error!!!") -> Balance Sheet Check: Balanced as all things should be
D6: Description | E6: Units | F6: Inputs | I6: Hist | J6: Hist | K6: Hist | L6: Hist | M6: Hist | N6: Forecast | O6: Forecast | P6: Forecast | Q6: Forecast | R6: Forecast | S6: Term
I7: 2022 | J7: 2023 | K7: 2024 | L7: 2025 | M7: =base_year -> 2026 | N7: =M7+1 -> 2027 | O7: =N7+1 -> 2028 | P7: =O7+1 -> 2029 | Q7: =P7+1 -> 2030 | R7: =Q7+1 -> 2031
C10: Perpetual Growth Rate (G)
D11: Net Profit Margin | F11: ='3-Statement'!M36/'3-Statement'!M11 -> 0.05482032
D12: Asset Turnover | F12: ='3-Statement'!M11/'Hist - BS'!E250 -> 0.39310869
D13: Financial Leverage | F13: ='3-Statement'!M70/'3-Statement'!M101 -> 3.9777141
D14: Return on Equity 2026 | E14: % | F14: =F11*F12*F13 -> 0.085721108
D15: Payout Ratio | E15: % | F15: =Inputs!M52 -> 0.7632312
D16: Retention Rate | E16: % | F16: =1-F15 -> 0.2367688
D17: Growth Rate | E17: % | F17: =F14*F16 -> 0.020296084
D18: Notice: Growth Rate is greater than the growth rate of the economy
D19: I used Gordon Growth Model because the company is a mature company and grows slower and around the same rate as it's host country's (UK) economy
D21: Cost of Equity | E21: % | F21: ='Investment recommendation'!Q57 -> 0.092604508
D22: Growth Rate | E22: % | F22: ='Investment recommendation'!Q58 -> 0.020296084
D24: Dividends | E24: [£'M] | I24: =Inputs!I51 -> 755 | J24: =Inputs!J51 -> 760 | K24: =Inputs!K51 -> 783 | L24: =Inputs!L51 -> 801 | M24: =Inputs!M51 -> 822 | N24: =Inputs!N51 -> 854.18687 | O24: =Inputs!O51 -> 879.81247 | P24: =Inputs!P51 -> 906.20685 | ... R24: =Inputs!R51 -> 961.39484 | S24: =R24*(1+F22) -> 980.90739
D25: Payout Ratio | E25: % | I25: =Inputs!I52 -> 0.59262166 | J25: =Inputs!J52 -> 0.39895013 | K25: =Inputs!K52 -> 0.91578947 | L25: =Inputs!L52 -> 0.75996205 | M25: =Inputs!M52 -> 0.7632312 | N25: =Inputs!N52 -> 0.5426898 | O25: =Inputs!O52 -> 0.489139 | P25: =Inputs!P52 -> 0.46018345 | ... S25: =Inputs!S52 -> 0
N27: =N7 -> 2027 | O27: =O7 -> 2028 | P27: =P7 -> 2029 | Q27: =Q7 -> 2030 | R27: =R7 -> 2031
D28: Dividends | E28: [£'M] | N28: =N24 -> 854.18687 | O28: =O24 -> 879.81247 | P28: =P24 -> 906.20685 | Q28: =Q24 -> 933.39305 | R28: =R24 -> 961.39484
D29: Terminal Value | E29: [£'M] | R29: =S24/(F21-F22) -> 13565.603
D30: Total Dividend | E30: [£'M] | N30: =SUM(N28:N29) -> 854.18687 | O30: =SUM(O28:O29) -> 879.81247 | P30: =SUM(P28:P29) -> 906.20685 | Q30: =SUM(Q28:Q29) -> 933.39305 | R30: =SUM(R28:R29) -> 14526.998
M32: Valuation | N32: Discrete Period
M33: (YYYY-MM-DD) | N33: (YYYY-MM-DD) | O33: (YYYY-MM-DD) | P33: (YYYY-MM-DD) | Q33: (YYYY-MM-DD) | R33: (YYYY-MM-DD)
M34: 46308 | N34: 46477 | O34: =EDATE(N34,12) -> 46843 | P34: =EDATE(O34,12) -> 47208 | Q34: =EDATE(P34,12) -> 47573 | R34: =EDATE(Q34,12) -> 47938
D36: Discounting Period | M36: 0 | N36: =M36+YEARFRAC(M34,N34) -> 0.46666667 | O36: =N36+YEARFRAC(N34,O34) -> 1.4666667 | P36: =O36+YEARFRAC(O34,P34) -> 2.4666667 | Q36: =P36+YEARFRAC(P34,Q34) -> 3.4666667 | R36: =Q36+YEARFRAC(Q34,R34) -> 4.4666667
D37: Present Value of Dividends | E37: [£'M] | N37: =N30/(1+$F$21)^N36 -> 819.60292 | O37: =O30/(1+$F$21)^O36 -> 772.64097 | P37: =P30/(1+$F$21)^P36 -> 728.36986 | Q37: =Q30/(1+$F$21)^Q36 -> 686.63542 | R37: =R30/(1+$F$21)^R36 -> 9780.8036
C39: Dividend Discount Model
D40: Intrinsic Equity Value | E40: [£'M] | F40: =SUM(N37:R37) -> 12788.053
D41: Shares Outstanding | E41: Units in M | F41: =Inputs!F59/1000000 -> 9967.6399
D42: Valuation Date | E42: Date | F42: =M34 -> 46308
D43: Intrinsic Equity Value per share | E43: Pence/sh | F43: =F40/F41*100 -> 128.29569
D44: Current Share Price | E44: Pence/sh | F44: =Inputs!F60 -> 209.7
D45: Judgement | E45: Text | F45: =IF(F44<F43, "Undervalued", "Overvalued") -> Overvalued

Sheet FCFF
B2: =company_name -> BT GROUP PLC
C3: FCFF/FCFE Model
C5: ="Balance Sheet Check: "&IF(bs_check=0,"Balanced as all things should be","Error!!!") -> Balance Sheet Check: Balanced as all things should be
D6: Description | E6: Units | F6: Inputs | I6: Hist | J6: Hist | K6: Hist | L6: Hist | M6: Hist | N6: Forecast | O6: Forecast | P6: Forecast | Q6: Forecast | R6: Forecast | S6: Term
I7: 2022 | J7: 2023 | K7: 2024 | L7: 2025 | M7: =base_year -> 2026 | N7: =M7+1 -> 2027 | O7: =N7+1 -> 2028 | P7: =O7+1 -> 2029 | Q7: =P7+1 -> 2030 | R7: =Q7+1 -> 2031
D9: =Inputs!D67 -> Uk Corporate Tax Rate | E9: =Inputs!E67 -> % | F9: =Inputs!F67 -> 0.25
D10: WACC | E10: % | F10: ='Investment recommendation'!Q56 -> 0.068424935
D11: =Inputs!D32 -> UK GDP Growth rate Q2 Y-o-Y | E11: % | F11: ='Investment recommendation'!Q59 -> 0.014
D12: =Inputs!D59 -> Shares Outstanding | E12: =Inputs!E59 -> Unit | F12: =Inputs!F59 -> 9967639866
B14: Unlevered Free Cashflow to the Firm
D15: ='3-Statement'!D21 -> EBIT | N15: ='3-Statement'!N21 -> 2586.1652 | O15: ='3-Statement'!O21 -> 2879.9705 | P15: ='3-Statement'!P21 -> 3086.0731 | Q15: ='3-Statement'!Q21 -> 3460.7102 | R15: ='3-Statement'!R21 -> 3867.9587 | S15: =R15*(1+$F$11) -> 3922.1101
D16: Unlevered Taxes | N16: =-N15*$F$9 -> -646.5413 | O16: =-O15*$F$9 -> -719.99264 | P16: =-P15*$F$9 -> -771.51829 | Q16: =-Q15*$F$9 -> -865.17756 | R16: =-R15*$F$9 -> -966.98968 | S16: =R16*(1+$F$11) -> -980.52753
D18: Net Operating profit After Tax (NOPAT) | N18: =SUM(N15:N16) -> 1939.6239 | O18: =SUM(O15:O16) -> 2159.9779 | P18: =SUM(P15:P16) -> 2314.5549 | Q18: =SUM(Q15:Q16) -> 2595.5327 | R18: =SUM(R15:R16) -> 2900.969 | S18: =R18*(1+$F$11) -> 2941.5826
D19: ='3-Statement'!D111 -> Depreciation & Amortization | N19: ='3-Statement'!N111 -> 4780.0893 | O19: ='3-Statement'!O111 -> 4525.9918 | P19: ='3-Statement'!P111 -> 4370.5595 | Q19: ='3-Statement'!Q111 -> 4179.0789 | R19: ='3-Statement'!R111 -> 4015.7088 | S19: =R19*(1+$F$11) -> 4071.9287
D20: ='3-Statement'!D114 -> Change in UFCF OWC | N20: ='3-Statement'!N194 -> 194.05619 | O20: ='3-Statement'!O194 -> 57.35645 | P20: ='3-Statement'!P194 -> 58.02685 | Q20: ='3-Statement'!Q194 -> 101.67065 | R20: ='3-Statement'!R194 -> 116.79868 | S20: =R20*(1+$F$11) -> 118.43387
D21: ='3-Statement'!D122 -> Investing Cashflows | N21: ='3-Statement'!N122 -> -4958.7828 | O21: ='3-Statement'!O122 -> -4757.1148 | P21: ='3-Statement'!P122 -> -4563.6485 | Q21: ='3-Statement'!Q122 -> -4378.0502 | R21: ='3-Statement'!R122 -> -4200 | S21: =R21*(1+$F$11) -> -4258.8
D22: FCFF | N22: =SUM(N18:N21) -> 1954.9866 | O22: =SUM(O18:O21) -> 1986.2113 | P22: =SUM(P18:P21) -> 2179.4927 | Q22: =SUM(Q18:Q21) -> 2498.232 | R22: =SUM(R18:R21) -> 2833.4765 | S22: =SUM(S18:S21) -> 2873.1452
M26: Valuation | N26: Discrete Period
M27: (YYYY-MM-DD) | N27: (YYYY-MM-DD) | O27: (YYYY-MM-DD) | P27: (YYYY-MM-DD) | Q27: (YYYY-MM-DD) | R27: (YYYY-MM-DD)
M28: 46308 | N28: 46477 | O28: =EDATE(N28,12) -> 46843 | P28: =EDATE(O28,12) -> 47208 | Q28: =EDATE(P28,12) -> 47573 | R28: =EDATE(Q28,12) -> 47938
D29: FCFF | N29: =N22 -> 1954.9866 | O29: =O22 -> 1986.2113 | P29: =P22 -> 2179.4927 | Q29: =Q22 -> 2498.232 | R29: =R22 -> 2833.4765
D30: Terminal value | R30: =S22/(F10-F11) -> 52790.972
D31: Total Cashflow | N31: =SUM(N29:N30) -> 1954.9866 | O31: =SUM(O29:O30) -> 1986.2113 | P31: =SUM(P29:P30) -> 2179.4927 | Q31: =SUM(Q29:Q30) -> 2498.232 | R31: =SUM(R29:R30) -> 55624.449
C34: Discounted FCFF
D35: Years for Discounting | M35: 0 | N35: =M35+YEARFRAC(M28,N28) -> 0.46666667 | O35: =N35+YEARFRAC(N28,O28) -> 1.4666667 | P35: =O35+YEARFRAC(O28,P28) -> 2.4666667 | Q35: =P35+YEARFRAC(P28,Q28) -> 3.4666667 | R35: =Q35+YEARFRAC(Q28,R28) -> 4.4666667
D37: Discrete Forecaast | M37: 0 | N37: =N29/(1+$F$10)^N35 -> 1895.5268 | O37: =O29/(1+$F$10)^O35 -> 1802.468 | P37: =P29/(1+$F$10)^P35 -> 1851.2007 | Q37: =Q29/(1+$F$10)^Q35 -> 1986.0348 | R37: =R29/(1+$F$10)^R35 -> 2108.2868
D38: Terminal Value | M38: 0 | R38: =R30/(1+F10)^R35 -> 39279.841
D39: Total FCFF | N39: =SUM(N37:N38) -> 1895.5268 | O39: =SUM(O37:O38) -> 1802.468 | P39: =SUM(P37:P38) -> 1851.2007 | Q39: =SUM(Q37:Q38) -> 1986.0348 | R39: =SUM(R37:R38) -> 41388.128
D41: FCFF/FCFE Model
D42: Enterprise Value | E42: =money -> [£'M] | F42: =SUM(N39:R39) -> 48923.358
D43: Less: MV Debt | E43: =money -> [£'M] | F43: =-'Cost of Capital'!F16/1000000 -> -17410.345
D44: Add: Cash and Cash Equivalents | E44: =money -> [£'M] | F44: ='3-Statement'!M50 -> 359
D45: Intrinsic Equity Value | E45: =money -> [£'M] | F45: =SUM(F42:F44) -> 31872.013
D46: Shares Outstanding | E46: Unit | F46: =F12/1000000 -> 9967.6399
D47: Current Share Price | E47: Pence/Sh | F47: =DDM!F44 -> 209.7
D48: Intrinsic Equity Value per Share | E48: Pence/Sh | F48: =F45/F46*100 -> 319.75487
D49: Judgement | E49: Text | F49: =IF(F48>F47, "Undervalued", "Overvalued") -> Undervalued
D51: This model may not account for the changes in the capital structure, so the WACC may be understated as the debt level of the company reduces.

Sheet RES.INC
B2: =company_name -> BT GROUP PLC
C3: Residual Income Model
C5: ="Balance Sheet Check: "&IF(bs_check=0,"Balanced as all things should be","Error!!!") -> Balance Sheet Check: Balanced as all things should be
D6: Description | E6: Units | F6: Inputs | I6: Hist | J6: Hist | K6: Hist | L6: Hist | M6: Hist | N6: Forecast | O6: Forecast | P6: Forecast | Q6: Forecast | R6: Forecast | S6: Term
I7: 2022 | J7: 2023 | K7: 2024 | L7: 2025 | M7: =base_year -> 2026 | N7: =M7+1 -> 2027 | O7: =N7+1 -> 2028 | P7: =O7+1 -> 2029 | Q7: =P7+1 -> 2030 | R7: =Q7+1 -> 2031
B8: Residual Income
D10: ='3-Statement'!D36 -> Net Income | E10: =money -> [£'M] | M10: ='3-Statement'!M36 -> 1077 | N10: ='3-Statement'!N36 -> 1573.9873 | O10: ='3-Statement'!O36 -> 1798.6962 | P10: ='3-Statement'!P36 -> 1969.2295 | Q10: ='3-Statement'!Q36 -> 2264.4339 | R10: ='3-Statement'!R36 -> 2593.643
D11: ='3-Statement'!D101 -> Total Equity | E11: =money -> [£'M] | M11: ='3-Statement'!M101 -> 12564 | N11: ='3-Statement'!N101 -> 13283.8 | O11: ='3-Statement'!O101 -> 14202.684 | P11: ='3-Statement'!P101 -> 15265.707 | Q11: ='3-Statement'!Q101 -> 16596.748 | R11: ='3-Statement'!R101 -> 18228.996
D12: Return On Equity | E12: % | M12: =M10/M11 -> 0.085721108 | N12: =N10/N11 -> 0.11848923 | O12: =O10/O11 -> 0.12664481 | P12: =P10/P11 -> 0.12899694 | Q12: =Q10/Q11 -> 0.13643841 | R12: =R10/R11 -> 0.14228118
D13: ='Cost of Equity'!D15 -> Cost of Equity | E13: % | F13: ='Investment recommendation'!Q57 -> 0.092604508
D14: =DDM!D17 -> Growth Rate | E14: % | F14: ='Investment recommendation'!Q58 -> 0.020296084
D15: =FCFF!D12 -> Shares Outstanding | E15: =FCFF!E12 -> Unit | F15: =FCFF!F12/1000000 -> 9967.6399
D16: Total Equity Reconciles with the data from Refinitiv's financial summary and the condition of accounting clean surplus is shown in the retained earnings schedule
C18: Clean Surplus Accounting
C20: ='3-Statement'!C254 -> Retained Earnings
D21: ='3-Statement'!D255 -> Beginning Balance | M21: ='3-Statement'!M255 -> 0 | N21: ='3-Statement'!N255 -> 9554 | O21: ='3-Statement'!O255 -> 10273.8 | P21: ='3-Statement'!P255 -> 11192.684 | Q21: ='3-Statement'!Q255 -> 12255.707 | R21: ='3-Statement'!R255 -> 13586.748
D22: ='3-Statement'!D256 -> Net Income | M22: ='3-Statement'!M256 -> 0 | N22: ='3-Statement'!N256 -> 1573.9873 | O22: ='3-Statement'!O256 -> 1798.6962 | P22: ='3-Statement'!P256 -> 1969.2295 | Q22: ='3-Statement'!Q256 -> 2264.4339 | R22: ='3-Statement'!R256 -> 2593.643
D23: ='3-Statement'!D257 -> Dividends | M23: ='3-Statement'!M257 -> 0 | N23: ='3-Statement'!N257 -> -854.18687 | O23: ='3-Statement'!O257 -> -879.81247 | P23: ='3-Statement'!P257 -> -906.20685 | Q23: ='3-Statement'!Q257 -> -933.39305 | R23: ='3-Statement'!R257 -> -961.39484
D24: ='3-Statement'!D258 -> Ending Balance | M24: ='3-Statement'!M258 -> 9554 | N24: ='3-Statement'!N258 -> 10273.8 | O24: ='3-Statement'!O258 -> 11192.684 | P24: ='3-Statement'!P258 -> 12255.707 | Q24: ='3-Statement'!Q258 -> 13586.748 | R24: ='3-Statement'!R258 -> 15218.996
C26: ='3-Statement'!C94 -> Equity
D27: ='3-Statement'!D95 -> Share capital | M27: ='3-Statement'!M95 -> 499 | N27: ='3-Statement'!N95 -> 499 | O27: ='3-Statement'!O95 -> 499 | P27: ='3-Statement'!P95 -> 499 | Q27: ='3-Statement'!Q95 -> 499 | R27: ='3-Statement'!R95 -> 499
D28: ='3-Statement'!D96 -> Share premium | M28: ='3-Statement'!M96 -> 1051 | N28: ='3-Statement'!N96 -> 1051 | O28: ='3-Statement'!O96 -> 1051 | P28: ='3-Statement'!P96 -> 1051 | Q28: ='3-Statement'!Q96 -> 1051 | R28: ='3-Statement'!R96 -> 1051
D29: ='3-Statement'!D97 -> Own shares | M29: ='3-Statement'!M97 -> -188 | N29: ='3-Statement'!N97 -> -188 | O29: ='3-Statement'!O97 -> -188 | P29: ='3-Statement'!P97 -> -188 | Q29: ='3-Statement'!Q97 -> -188 | R29: ='3-Statement'!R97 -> -188
D30: ='3-Statement'!D98 -> Merger reserve | M30: ='3-Statement'!M98 -> 998 | N30: ='3-Statement'!N98 -> 998 | O30: ='3-Statement'!O98 -> 998 | P30: ='3-Statement'!P98 -> 998 | Q30: ='3-Statement'!Q98 -> 998 | R30: ='3-Statement'!R98 -> 998
D31: ='3-Statement'!D99 -> Other reserves | M31: ='3-Statement'!M99 -> 650 | N31: ='3-Statement'!N99 -> 650 | O31: ='3-Statement'!O99 -> 650 | P31: ='3-Statement'!P99 -> 650 | Q31: ='3-Statement'!Q99 -> 650 | R31: ='3-Statement'!R99 -> 650
D32: ='3-Statement'!D100 -> Retained earnings | M32: ='3-Statement'!M100 -> 9554 | N32: ='3-Statement'!N100 -> 10273.8 | O32: ='3-Statement'!O100 -> 11192.684 | P32: ='3-Statement'!P100 -> 12255.707 | Q32: ='3-Statement'!Q100 -> 13586.748 | R32: ='3-Statement'!R100 -> 15218.996
D33: ='3-Statement'!D101 -> Total Equity | M33: ='3-Statement'!M101 -> 12564 | N33: ='3-Statement'!N101 -> 13283.8 | O33: ='3-Statement'!O101 -> 14202.684 | P33: ='3-Statement'!P101 -> 15265.707 | Q33: ='3-Statement'!Q101 -> 16596.748 | R33: ='3-Statement'!R101 -> 18228.996
C36: Model
D37: =D12 -> Return On Equity | E37: =E12 -> % | M37: =M12 -> 0.085721108 | N37: =N12 -> 0.11848923 | O37: =O12 -> 0.12664481 | P37: =P12 -> 0.12899694 | Q37: =Q12 -> 0.13643841 | R37: =R12 -> 0.14228118
D38: Cost of Equity | E38: =E13 -> % | M38: =$F$13 -> 0.092604508 | N38: =$F$13 -> 0.092604508 | O38: =$F$13 -> 0.092604508 | P38: =$F$13 -> 0.092604508 | Q38: =$F$13 -> 0.092604508 | R38: =$F$13 -> 0.092604508
D39: Required Rate of Return (Equity Charge) | E39: =money -> [£'M] | N39: =N38*M11 -> 1163.483 | O39: =O38*N11 -> 1230.1398 | P39: =P38*O11 -> 1315.2326 | Q39: =Q38*P11 -> 1413.6733 | R39: =R38*Q11 -> 1536.9337
D40: Residual Income | E40: =money -> [£'M] | N40: =N10-N39 -> 410.5043 | O40: =O10-O39 -> 568.55641 | P40: =P10-P39 -> 653.99697 | Q40: =Q10-Q39 -> 850.76067 | R40: =R10-R39 -> 1056.7093 | S40: =R40*(1+$F$14) -> 1078.1564
M44: Valuation | N44: Discrete Period | S44: Term
M45: (YYYY-MM-DD) | N45: (YYYY-MM-DD) | O45: (YYYY-MM-DD) | P45: (YYYY-MM-DD) | Q45: (YYYY-MM-DD) | R45: (YYYY-MM-DD) | S45: (YYYY-MM-DD)
M46: 46308 | N46: 46477 | O46: =EDATE(N46,12) -> 46843 | P46: =EDATE(O46,12) -> 47208 | Q46: =EDATE(P46,12) -> 47573 | R46: =EDATE(Q46,12) -> 47938 | S46: =EDATE(R46,12) -> 48304
D48: Discounting Period | M48: 0 | N48: =M48+YEARFRAC(M46,N46) -> 0.46666667 | O48: =N48+YEARFRAC(N46,O46) -> 1.4666667 | P48: =O48+YEARFRAC(O46,P46) -> 2.4666667 | Q48: =P48+YEARFRAC(P46,Q46) -> 3.4666667 | R48: =Q48+YEARFRAC(Q46,R46) -> 4.4666667
D50: =D40 -> Residual Income | N50: =N40 -> 410.5043 | O50: =O40 -> 568.55641 | P50: =P40 -> 653.99697 | Q50: =Q40 -> 850.76067 | R50: =R40 -> 1056.7093
D51: Terminal Value | R51: =S40/(F13-F14) -> 14910.522
D52: Total Cashflow | N52: =SUM(N50:N51) -> 410.5043 | O52: =SUM(O50:O51) -> 568.55641 | P52: =SUM(P50:P51) -> 653.99697 | Q52: =SUM(Q50:Q51) -> 850.76067 | R52: =SUM(R50:R51) -> 15967.232
D54: Present Value of Cashflows | N54: =N52/(1+$F$13)^N48 -> 393.88398 | O54: =O52/(1+$F$13)^O48 -> 499.29955 | P54: =P52/(1+$F$13)^P48 -> 525.65448 | Q54: =Q52/(1+$F$13)^Q48 -> 625.84826 | R54: =R52/(1+$F$13)^R48 -> 10750.49
D57: Residual Income
D58: Sum of PV of Residual Income | E58: =money -> [£'M] | F58: =SUM(N54:R54) -> 12795.177
D59: 2026A Book Value of Equity | E59: =money -> [£'M] | F59: =M11 -> 12564
D60: Intrinsic Equity Value | E60: =money -> [£'M] | F60: =SUM(F58:F59) -> 25359.177
D61: Shares Outstanding | E61: Unit | F61: =F15 -> 9967.6399
D62: Intrinsic Equity Value/Share | E62: =DDM!E43 -> Pence/sh | F62: =F60/F61*100 -> 254.41506
D63: =DDM!D44 -> Current Share Price | E63: =DDM!E44 -> Pence/sh | F63: =DDM!F44 -> 209.7
D64: Judgement | E64: Text | F64: =IF(F63<F62, "Undervalued", "Overvalued") -> Undervalued

Sheet COMPS
B2: =company_name -> BT GROUP PLC
C5: Market Data as at | D5: ='Cover Page'!F16 -> 46319
C6: Company Name | D6: EV / Revenue (NTM) | E6: EV / EBITDA | F6: Price / EPS (NTM) | G6: Price / Cash Flow Per Share (NTM) | H6: Price / Book Value Per Share (NTM) | I6: Price / Revenue (NTM) | J6: Dividend Per Share Yield % (NTM) | K6: Price / Free Cash Flow Per Share (FY1) | L6: Price / CAPEX (FY1) | M6: Return On Equity | N6: Net Debt to Total Equity (FY0) | O6: Asset Turnover (FY0) | P6: Quick Ratio (FY0) | Q6: Gross Profit Margin - % (FY0) | R6: Net Income Margin - Actual (FY0) | S6: Company Market Capitalization (usd)
C7: Vodafone Group PLC | D7: 1.6054114 | E7: 5.3145 | F7: 11.321447 | G7: 2.722113 | H7: 0.71142604 | I7: 0.71669884 | J7: 0.034609165 | K7: 15.878295 | L7: 4.0371381 | M7: 0.0943 | N7: 0.67845 | O7: 0.31311838 | P7: 1.10531 | Q7: 0.3146981 | R7: 0.07129 | S7: 3.6617543e+10
C8: Deutsche Telekom AG | D8: 2.2173078 | E8: 5.3203787 | F8: 9.8976226 | G8: 3.0425025 | H8: 1.8871344 | I8: 0.95215508 | J8: 0.050041882 | K8: 7.983025 | L8: 6.7501665 | M8: 0.0534 | N8: 1.44198 | O8: 0.40047217 | P8: 1.0397 | Q8: 0.4121396 | R8: 0.08189 | S8: 1.3771914e+11
C9: Koninklijke KPN NV | D9: 3.7062689 | E9: 7.7989013 | F9: 15.877067 | G9: 6.4689476 | H9: 4.1556963 | I9: 2.5792855 | J9: 0.059492002 | K9: 15.465058 | L9: 12.218014 | M9: 0.0003 | N9: 1.79641 | O9: 0.45937488 | P9: 0.61716 | Q9: 0.5632977 | R9: 0.14669 | S9: 1.739173e+10
C10: Swisscom AG | D10: 3.4156368 | E10: 7.5994206 | F10: 23.850831 | G10: 6.455936 | H10: 2.9618512 | I10: 2.4351628 | J10: 0.03958593 | K10: 25.129323 | L10: 9.9830601 | M10: -0.0356 | N10: 1.23517 | O10: 0.40742947 | P10: 0.73192 | Q10: 0.4723551 | R10: 0.08439 | S10: 4.2985125e+10
C11: Telefonica SA | D11: 1.7168172 | E11: 4.8618477 | F11: 8.6634731 | G11: 2.3107303 | H11: 1.3059154 | I11: 0.56821591 | J11: 0.045608536 | K11: 12.600407 | L11: 4.0459247 | M11: 0.0608 | N11: 1.83738 | O11: 0.36484711 | P11: 0.85127 | Q11: 0.2889237 | R11: 0.0604 | S11: 2.1703755e+10
C12: Telia Company AB (publ) | D12: 3.1351973 | E12: 7.9493401 | F12: 18.271108 | G12: 6.6569727 | H12: 3.669829 | I12: 2.209192 | J12: 0.046492328 | K12: 6.5415947 | L12: 14.195216 | M12: 0 | N12: 1.30212 | O12: 0.41157442 | P12: 0.87113 | Q12: 0.3533378 | R12: 0.09509 | S12: 1.9111146e+10
C13: Orange SA | D13: 1.7940852 | E13: 5.4176049 | F13: 12.28317 | G13: 2.8195077 | H13: 1.1636725 | I13: 0.78726541 | J13: 0.057849837 | K13: 10.049204 | L13: 5.0521087 | M13: 0.035 | N13: 0.91256 | O13: 0.38237674 | P13: 1.08547 | Q13: 0.5906525 | R13: 0.0608 | S13: 4.2327886e+10
C14: BT Group PLC | D14: 2.4086191 | E14: 5.2143384 | F14: 11.216754 | G14: 3.1268146 | H14: 1.5799143 | I14: 1.2086569 | J14: 0.040961824 | K14: 15.047327 | L14: 4.6607584 | M14: =DDM!F14 -> 0.085721108 | N14: 1.6716 | O14: 0.38919154 | P14: 0.80259 | Q14: 0.423445 | R14: 0.0913 | S14: 2.8230295e+10
C16: Maximum | D16: =MAX(D7:D13) -> 3.7062689 | E16: =MAX(E7:E13) -> 7.9493401 | F16: =MAX(F7:F13) -> 23.850831 | G16: =MAX(G7:G13) -> 6.6569727 | H16: =MAX(H7:H13) -> 4.1556963 | I16: =MAX(I7:I13) -> 2.5792855 | J16: =MAX(J7:J13) -> 0.059492002 | K16: 23.268548 | L16: 13.16136 | M16: =MAX(M7:M13) -> 0.0943 | N16: =MAX(N7:N13) -> 1.83738 | O16: =MAX(O7:O13) -> 0.45937488 | P16: =MAX(P7:P13) -> 1.10531 | Q16: =MAX(Q7:Q13) -> 0.5906525 | R16: =MAX(R7:R13) -> 0.14669 | S16: =MAX(S7:S13) -> 1.3771914e+11
C17: Average | D17: =AVERAGE(D7:D13) -> 2.5129606 | E17: =AVERAGE(E7:E13) -> 6.3231419 | F17: =AVERAGE(F7:F13) -> 14.309245 | G17: =AVERAGE(G7:G13) -> 4.3538157 | H17: =AVERAGE(H7:H13) -> 2.265075 | I17: =AVERAGE(I7:I13) -> 1.4639965 | J17: =AVERAGE(J7:J13) -> 0.047668526 | K17: 13.258452 | L17: 7.6634987 | M17: =AVERAGE(M7:M13) -> 0.029742857 | N17: =AVERAGE(N7:N13) -> 1.3148671 | O17: =AVERAGE(O7:O13) -> 0.39131331 | P17: =AVERAGE(P7:P13) -> 0.90028 | Q17: =AVERAGE(Q7:Q13) -> 0.42791493 | R17: =AVERAGE(R7:R13) -> 0.085792857 | S17: =AVERAGE(S7:S13) -> 4.5408046e+10
C18: Median | D18: =MEDIAN(D7:D13) -> 2.2173078 | E18: =MEDIAN(E7:E13) -> 5.4176049 | F18: =MEDIAN(F7:F13) -> 12.28317 | G18: =MEDIAN(G7:G13) -> 3.0425025 | H18: =MEDIAN(H7:H13) -> 1.8871344 | I18: =MEDIAN(I7:I13) -> 0.95215508 | J18: =MEDIAN(J7:J13) -> 0.046492328 | K18: 11.884447 | L18: 6.7325942 | M18: =MEDIAN(M7:M13) -> 0.035 | N18: =MEDIAN(N7:N13) -> 1.30212 | O18: =MEDIAN(O7:O13) -> 0.40047217 | P18: =MEDIAN(P7:P13) -> 0.87113 | Q18: =MEDIAN(Q7:Q13) -> 0.4121396 | R18: =MEDIAN(R7:R13) -> 0.08189 | S18: =MEDIAN(S7:S13) -> 3.6617543e+10
C19: Minimum | D19: =MIN(D7:D13) -> 1.6054114 | E19: =MIN(E7:E13) -> 4.8618477 | F19: =MIN(F7:F13) -> 8.6634731 | G19: =MIN(G7:G13) -> 2.3107303 | H19: =MIN(H7:H13) -> 0.71142604 | I19: =MIN(I7:I13) -> 0.56821591 | J19: =MIN(J7:J13) -> 0.034609165 | K19: 7.9581285 | L19: 3.81193 | M19: =MIN(M7:M13) -> -0.0356 | N19: =MIN(N7:N13) -> 0.67845 | O19: =MIN(O7:O13) -> 0.31311838 | P19: =MIN(P7:P13) -> 0.61716 | Q19: =MIN(Q7:Q13) -> 0.2889237 | R19: =MIN(R7:R13) -> 0.0604 | S19: =MIN(S7:S13) -> 1.739173e+10
C23: BT Group PLC | D23: =D14 -> 2.4086191 | E23: =E14 -> 5.2143384 | F23: =F14 -> 11.216754 | G23: =G14 -> 3.1268146 | H23: =H14 -> 1.5799143 | I23: =I14 -> 1.2086569 | J23: =J14 -> 0.040961824 | K23: =K14 -> 15.047327 | ... S23: =S14 -> 2.8230295e+10
C25: Relative Multiples | M25: Ranks vs Industry Peers
C26: Conclusion (Average) | D26: =IF(D$23>D17,"Overvalued", "Undervalued") -> Undervalued | E26: =IF(E$23>E17,"Overvalued", "Undervalued") -> Undervalued | F26: =IF(F$23>F17,"Overvalued", "Undervalued") -> Undervalued | G26: =IF(G$23>G17,"Overvalued", "Undervalued") -> Undervalued | H26: =IF(H$23>H17,"Overvalued", "Undervalued") -> Undervalued | I26: =IF(I$23>I17,"Overvalued", "Undervalued") -> Undervalued | J26: =IF(J$23>J17,"Overvalued", "Undervalued") -> Undervalued | K26: =IF(K$23>K17,"Overvalued", "Undervalued") -> Overvalued | L26: =IF(L$23>L17,"Overvalued", "Undervalued") -> Undervalued | M26: =_xlfn.RANK.AVG(M14,M7:M14) -> 2 | N26: =_xlfn.RANK.AVG(N14,N7:N14) -> 3 | O26: =_xlfn.RANK.AVG(O14,O7:O14) -> 5 | P26: =_xlfn.RANK.AVG(P14,P7:P14) -> 6 | Q26: =_xlfn.RANK.AVG(Q14,Q7:Q14) -> 4 | R26: =_xlfn.RANK.AVG(R14,R7:R14) -> 3 | S26: =_xlfn.RANK.AVG(S14,S7:S14) -> 5
C27: Conclusion (Median) | D27: =IF(D$23>D18,"Overvalued", "Undervalued") -> Overvalued | E27: =IF(E$23>E18,"Overvalued", "Undervalued") -> Undervalued | F27: =IF(F$23>F18,"Overvalued", "Undervalued") -> Undervalued | G27: =IF(G$23>G18,"Overvalued", "Undervalued") -> Overvalued | H27: =IF(H$23>H18,"Overvalued", "Undervalued") -> Undervalued | I27: =IF(I$23>I18,"Overvalued", "Undervalued") -> Overvalued | J27: =IF(J$23>J18,"Overvalued", "Undervalued") -> Undervalued | K27: =IF(K$23>K18,"Overvalued", "Undervalued") -> Overvalued | L27: =IF(L$23>L18,"Overvalued", "Undervalued") -> Undervalued
C30: Metric | D30: Rank | G30: Comparables Valuation
C31: Return On Equity | D31: {=TRANSPOSE(M26:S26)} -> 2 | G31: 2027F Earnings | H31: =money -> [£'M] | I31: ='3-Statement'!N36 -> 1573.9873
C32: Net Debt to Total Equity | D32: 3 | G32: Shares Outstanding | H32: Unit | I32: =Inputs!F59/1000000 -> 9967.6399
C33: Asset Turnover | D33: 5 | G33: Average P/E | H33: x | I33: =F17 -> 14.309245
C34: Quick Ratio | D34: 6 | G34: Forward EPS | H34: =money -> [£'M] | I34: =I31/I32 -> 0.15790973
C35: Gross Profit Margin | D35: 4 | G35: Potential Share Price | H35: Pence/sh | I35: =I33*I34*100 -> 225.95691
C36: Net Income Margin | D36: 3 | G36: Current Share Price | H36: Pence/sh | I36: ='RES.INC'!F63 -> 209.7
C37: Company Market Capitalization | D37: 5 | G37: Judgement | H37: Text | I37: =IF(I36<I35, "Undervalued", "Overvalued") -> Undervalued

Sheet Cost of Equity
B2: =company_name -> BT GROUP PLC
C3: Cost of Equity
C5: ="Balance Sheet Check: "&IF(bs_check=0,"Balanced as all things should be","Error!!!") -> Balance Sheet Check: Balanced as all things should be
C8: Cost of Equity
D9: Cost of Equity using the Capital Asset Pricing Model (CAPM)
D10: Variables | E10: Values
D11: Risk Free Rate | E11: =Inputs!F61 -> 0.0537
D12: Beta | E12: =_xlfn.COVARIANCE.S(G20:G86,H20:H86)/_xlfn.VAR.S(H20:H86) -> 1.0371912
D13: Expected Market Return | E13: =(1+MEDIAN(H20:H86))^4-1 -> 0.091209485
D14: Equity Risk Premium | E14: =E13-E11 -> 0.037509485
D15: Cost of Equity | E15: =E11+E12*E14 -> 0.092604508
C17: Data from Refinitv Workspace
D19: Exchange Date | E19: Close | F19: Net | G19: BT.L | H19: R_FTSE100 | I19: Risk - Free Rate | J19: Equity Risk Premium
D20: 46295 | E20: 192 | F20: 1.9 | G20: 0.0099947396 | H20: 0.010372369 | I20: =_xlfn.XLOOKUP(C21,'FRED YTM'!$B$2:$B$802,'FRED YTM'!$C$2:$C$802)/(4*100) -> 0.01248425 | J20: =H20-I20 -> -0.0021118812
C21: 09/2026 | D21: 46203 | E21: 190.1 | F21: -20.4 | G21: -0.096912114 | H21: 0.031510989 | I21: =_xlfn.XLOOKUP(C22,'FRED YTM'!$B$2:$B$802,'FRED YTM'!$C$2:$C$802)/(4*100) -> 0.01199 | J21: =H21-I21 -> 0.019520989
C22: 06/2026 | D22: 46112 | E22: 210.5 | F22: 26.45 | G22: 0.14371095 | H22: 0.024676329 | I22: =_xlfn.XLOOKUP(C23,'FRED YTM'!$B$2:$B$802,'FRED YTM'!$C$2:$C$802)/(4*100) -> 0.01175175 | J22: =H22-I22 -> 0.012924579
C23: 03/2026 | D23: 46022 | E23: 184.05 | F23: -7.1 | G23: -0.037143604 | H23: 0.062130832 | I23: =_xlfn.XLOOKUP(C24,'FRED YTM'!$B$2:$B$802,'FRED YTM'!$C$2:$C$802)/(4*100) -> 0.0112065 | J23: =H23-I23 -> 0.050924332
C24: 12/2025 | D24: 45930 | E24: 191.15 | F24: -2.6 | G24: -0.013419355 | H24: 0.067283722 | I24: =_xlfn.XLOOKUP(C25,'FRED YTM'!$B$2:$B$802,'FRED YTM'!$C$2:$C$802)/(4*100) -> 0.01172125 | J24: =H24-I24 -> 0.055562472
C25: 09/2025 | D25: 45838 | E25: 193.75 | F25: 27.9 | G25: 0.1682243 | H25: 0.020756605 | I25: =_xlfn.XLOOKUP(C26,'FRED YTM'!$B$2:$B$802,'FRED YTM'!$C$2:$C$802)/(4*100) -> 0.011312 | J25: =H25-I25 -> 0.0094446054
C26: 06/2025 | D26: 45747 | E26: 165.85 | F26: 21.8 | G26: 0.15133634 | H26: 0.050139361 | I26: =_xlfn.XLOOKUP(C27,'FRED YTM'!$B$2:$B$802,'FRED YTM'!$C$2:$C$802)/(4*100) -> 0.011612 | J26: =H26-I26 -> 0.038527361
C27: 03/2025 | D27: 45657 | E27: 144.05 | F27: -3.85 | G27: -0.026031102 | H27: -0.007761368 | I27: =_xlfn.XLOOKUP(C28,'FRED YTM'!$B$2:$B$802,'FRED YTM'!$C$2:$C$802)/(4*100) -> 0.01108625 | J27: =H27-I27 -> -0.018847618
C28: 12/2024 | D28: 45565 | E28: 147.9 | F28: 7.55 | G28: 0.053794086 | H28: 0.008920741 | I28: =_xlfn.XLOOKUP(C29,'FRED YTM'!$B$2:$B$802,'FRED YTM'!$C$2:$C$802)/(4*100) -> 0.00976325 | J28: =H28-I28 -> -0.000842509
C29: 09/2024 | D29: 45473 | E29: 140.35 | F29: 30.7 | G29: 0.27998176 | H29: 0.026595009 | I29: =_xlfn.XLOOKUP(C30,'FRED YTM'!$B$2:$B$802,'FRED YTM'!$C$2:$C$802)/(4*100) -> 0.010411 | J29: =H29-I29 -> 0.016184009
C30: 06/2024 | D30: 45382 | E30: 109.65 | F30: -13.95 | G30: -0.11286408 | H30: 0.028368446 | I30: =_xlfn.XLOOKUP(C31,'FRED YTM'!$B$2:$B$802,'FRED YTM'!$C$2:$C$802)/(4*100) -> 0.0100825 | J30: =H30-I30 -> 0.018285946
C31: 03/2024 | D31: 45291 | E31: 123.6 | F31: 6.9 | G31: 0.059125964 | H31: 0.016450931 | I31: =_xlfn.XLOOKUP(C32,'FRED YTM'!$B$2:$B$802,'FRED YTM'!$C$2:$C$802)/(4*100) -> 0.0096555 | J31: =H31-I31 -> 0.0067954311
C32: 12/2023 | D32: 45199 | E32: 116.7 | F32: -5.65 | G32: -0.046178995 | H32: 0.010163937 | I32: =_xlfn.XLOOKUP(C33,'FRED YTM'!$B$2:$B$802,'FRED YTM'!$C$2:$C$802)/(4*100) -> 0.01104975 | J32: =H32-I32 -> -0.00088581253
... C39: 03/2022 | D39: 44561 | E39: 169.55 | F39: 9.75 | G39: 0.061013767 | H39: 0.042069197 | I39: =_xlfn.XLOOKUP(C40,'FRED YTM'!$B$2:$B$802,'FRED YTM'!$C$2:$C$802)/(4*100) -> 0.00209375 | J39: =H39-I39 -> 0.039975447
C40: 12/2021 | D40: 44469 | E40: 159.8 | F40: -34.2 | G40: -0.17628866 | H40: 0.0069556247
C41: 09/2021 | D41: 44377 | E41: 194 | F41: 39.2 | G41: 0.25322997 | H41: 0.0482362
D42: 44286 | E42: 154.8 | F42: 22.55 | G42: 0.1705104 | H42: 0.039177961
D43: 44196 | E43: 132.25 | F43: 33.87 | G43: 0.34427729 | H43: 0.10133138
D44: 44104 | E44: 98.38 | F44: -15.67 | G44: -0.13739588 | H44: -0.049214392
D45: 44012 | E45: 114.05 | F45: -3.85 | G45: -0.032654792 | H45: 0.08776155
D46: 43921 | E46: 117.9 | F46: -74.54 | G46: -0.38734151 | H46: -0.24799402
D47: 43830 | E47: 192.44 | F47: 13.86 | G47: 0.077612275 | H47: 0.018119087
D48: 43738 | E48: 178.58 | F48: -17.88 | G48: -0.091010893 | H48: -0.0023459289
D49: 43646 | E49: 196.46 | F49: -26.49 | G49: -0.11881588 | H49: 0.020117623
D50: 43555 | E50: 222.95 | F50: -15.15 | G50: -0.063628727 | H50: 0.081903887
D51: 43465 | E51: 238.1 | F51: 12.8 | G51: 0.056813138 | H51: -0.10413438
D52: 43373 | E52: 225.3 | F52: 7.5 | G52: 0.034435262 | H52: -0.016594364
D53: 43281 | E53: 217.8 | F53: -9.7 | G53: -0.042637363 | H53: 0.082237788
... D86: 40268 | E86: 123.9 | F86: -11.1 | G86: -0.082222222 | H86: 0.049282452

Sheet Cost of Capital
B2: =company_name -> BT GROUP PLC
C3: Cost of Capital
C5: ="Balance Sheet Check: "&IF(bs_check=0,"Balanced as all things should be","Error!!!") -> Balance Sheet Check: Balanced as all things should be
D7: =Inputs!D67 -> Uk Corporate Tax Rate | E7: =Inputs!E67 -> % | F7: =Inputs!F67 -> 0.25
D8: =Inputs!D59 -> Shares Outstanding | E8: =Inputs!E59 -> Unit | F8: =Inputs!F59 -> 9967639866
D9: =Inputs!D60 -> Current Share Price | E9: =Inputs!E60 -> Pence/Sh | F9: =Inputs!F60 -> 209.7
D10: BT Cost of Debt | F10: ='Debt Structure'!B53 -> 0.052527918
C13: Weighted Average Cost of Capital
D14: Capital Structure | F14: Values | G14: Weights | H14: Costs | I14: WACC
D15: Equity | F15: =F8*(F9/100) -> 2.0902141e+10 | G15: =F15/$F$17 -> 0.54556995 | H15: ='Cost of Equity'!E15 -> 0.092604508 | I15: =G15*H15 -> 0.050522236
D16: Market Value of Debt | F16: ='Debt Structure'!B52 -> 1.7410345e+10 | G16: =F16/$F$17 -> 0.45443005 | H16: =F10*(1-F7) -> 0.039395938 | I16: =G16*H16 -> 0.017902698
D17: Total | F17: =SUM(F14:F16) -> 3.8312486e+10 | G17: =SUM(G15:G16) -> 1 | I17: =SUM(I15:I16) -> 0.068424935

Sheet 3-Statement
B2: =company_name -> BT GROUP PLC
C3: 3 - Statement Model & Schedules
C5: ="Balance Sheet Check: "&IF(bs_check=0,"Balanced as all things should be","Error!!!") -> Balance Sheet Check: Balanced as all things should be
D6: Description | E6: Units | F6: Inputs | I6: Hist | J6: Hist | K6: Hist | L6: Hist | M6: Hist | N6: Forecast | O6: Forecast | P6: Forecast | Q6: Forecast | R6: Forecast | S6: Term
I7: 2022 | J7: 2023 | K7: 2024 | L7: 2025 | M7: =base_year -> 2026 | N7: =M7+1 -> 2027 | O7: =N7+1 -> 2028 | P7: =O7+1 -> 2029 | Q7: =P7+1 -> 2030 | R7: =Q7+1 -> 2031
B8: 3- Statements
C9: Income Statement
D11: ='Hist - IS'!C204 -> Revenue | I11: ='Hist - IS'!H204 -> 20845 | J11: ='Hist - IS'!G204 -> 20669 | K11: ='Hist - IS'!F204 -> 20835 | L11: ='Hist - IS'!E204 -> 20370 | M11: ='Hist - IS'!D204 -> 19646 | N11: =M11*(1+Inputs!N27) -> 19319.684 | O11: =N11*(1+Inputs!O27) -> 19416.283 | P11: =O11*(1+Inputs!P27) -> 19688.111 | Q11: =P11*(1+Inputs!Q27) -> 19963.744 | R11: =Q11*(1+Inputs!R27) -> 20243.237
D12: ='Hist - IS'!C207 -> Cost of Sales | I12: =-'Hist - IS'!H207 -> -7951 | J12: =-'Hist - IS'!G207 -> -7820 | K12: =-'Hist - IS'!F207 -> -7658 | L12: =-'Hist - IS'!E207 -> -6777 | M12: =-'Hist - IS'!D207 -> -6474 | N12: =-Inputs!N38 -> -6305.082 | O12: =-Inputs!O38 -> -6274.6218 | P12: =-Inputs!P38 -> -6299.3152 | Q12: =-Inputs!Q38 -> -6323.1667 | R12: =-Inputs!R38 -> -6346.1423
D13: Gross Profit | I13: =SUM(I11:I12) -> 12894 | J13: =SUM(J11:J12) -> 12849 | K13: =SUM(K11:K12) -> 13177 | L13: =SUM(L11:L12) -> 13593 | M13: =SUM(M11:M12) -> 13172 | N13: =SUM(N11:N12) -> 13014.602 | O13: =SUM(O11:O12) -> 13141.661 | P13: =SUM(P11:P12) -> 13388.796 | ... R13: =SUM(R11:R12) -> 13897.094
D14: Gross Profit Margin | I14: =I13/I$11 -> 0.6185656 | J14: =J13/J$11 -> 0.62165562 | K14: =K13/K$11 -> 0.6324454 | L14: =L13/L$11 -> 0.66730486 | M14: =M13/M$11 -> 0.67046727 | N14: =N13/N$11 -> 0.67364467 | O14: =O13/O$11 -> 0.67683712 | P14: =P13/P$11 -> 0.68004471 | ... R14: =R13/R$11 -> 0.68650555
D16: ='Hist - IS'!C217 -> SGA | I16: =-'Hist - IS'!H217 -> -5777 | J16: =-'Hist - IS'!G217 -> -5496 | K16: =-'Hist - IS'!F217 -> -6353 | L16: =-'Hist - IS'!E217 -> -6482 | M16: =-'Hist - IS'!D217 -> -5808 | N16: =-Inputs!N47 -> -5648.3478 | O16: =-Inputs!O47 -> -5735.6987 | P16: =-Inputs!P47 -> -5932.1629 | Q16: =-Inputs!Q47 -> -6000.7884 | R16: =-Inputs!R47 -> -6013.4269
D17: EBITDA | I17: =I13+I16 -> 7117 | J17: =J13+J16 -> 7353 | K17: =K13+K16 -> 6824 | L17: =L13+L16 -> 7111 | M17: =M13+M16 -> 7364 | N17: =N13+N16 -> 7366.2545 | O17: =O13+O16 -> 7405.9623 | P17: =P13+P16 -> 7456.6326 | ... R17: =R13+R16 -> 7883.6675
D18: EBITDA Margin | I18: =I17/I$11 -> 0.3414248 | J18: =J17/J$11 -> 0.35575016 | K18: =K17/K$11 -> 0.3275258 | L18: =L17/L$11 -> 0.3490918 | M18: =M17/M$11 -> 0.37483457 | N18: =N17/N$11 -> 0.38128234 | O18: =O17/O$11 -> 0.38143049 | P18: =P17/P$11 -> 0.37873784 | ... R18: =R17/R$11 -> 0.38944699
D20: ='Hist - IS'!C219 -> Depreciation & Amortization | I20: =-'Hist - IS'!H219 -> -4405 | J20: =-'Hist - IS'!G219 -> -4742 | K20: =-'Hist - IS'!F219 -> -4792 | L20: =-'Hist - IS'!E219 -> -4883 | M20: =-'Hist - IS'!D219 -> -4853 | N20: =-Inputs!N106 -> -4780.0893 | O20: =-Inputs!O106 -> -4525.9918 | P20: =-Inputs!P106 -> -4370.5595 | Q20: =-Inputs!Q106 -> -4179.0789 | R20: =-Inputs!R106 -> -4015.7088
D21: EBIT | I21: =I17+I20 -> 2712 | J21: =J17+J20 -> 2611 | K21: =K17+K20 -> 2032 | L21: =L17+L20 -> 2228 | M21: =M17+M20 -> 2511 | N21: =N17+N20 -> 2586.1652 | O21: =O17+O20 -> 2879.9705 | P21: =P17+P20 -> 3086.0731 | ... R21: =R17+R20 -> 3867.9587
D22: EBIT Margin | I22: =I21/I$11 -> 0.13010314 | J22: =J21/J$11 -> 0.12632445 | K22: =K21/K$11 -> 0.097528198 | L22: =L21/L$11 -> 0.10937653 | M22: =M21/M$11 -> 0.12781228 | N22: =N21/N$11 -> 0.13386167 | O22: =O21/O$11 -> 0.1483276 | P22: =P21/P$11 -> 0.15674806 | ... R22: =R21/R$11 -> 0.19107412
D24: ='Hist - IS'!C229 -> Interest Expense | I24: =-'Hist - IS'!H229 -> -761 | J24: =-'Hist - IS'!G229 -> -886 | K24: =-'Hist - IS'!F229 -> -1006 | L24: =-'Hist - IS'!E229 -> -1037 | M24: =-'Hist - IS'!D229 -> -963 | N24: =-N308+N310 -> -498.24722 | O24: =-O308+O310 -> -496.3373 | P24: =-P308+P310 -> -473.02778 | Q24: =-Q308+Q310 -> -452.13087 | R24: =-R308+R310 -> -421.83357
D25: ='Hist - IS'!C228 -> Interest Income | I25: ='Hist - IS'!H228 -> 12 | J25: ='Hist - IS'!G228 -> 63 | K25: ='Hist - IS'!F228 -> 181 | L25: ='Hist - IS'!E228 -> 151 | M25: ='Hist - IS'!D228 -> 98 | N25: =-N309 -> 10.731816 | O25: =-O309 -> 14.628362 | P25: =-P309 -> 12.594036 | Q25: =-Q309 -> 10.665909 | R25: =-R309 -> 12.065482
D26: Net Interest Expense | I26: =SUM(I24:I25) -> -749 | J26: =SUM(J24:J25) -> -823 | K26: =SUM(K24:K25) -> -825 | L26: =SUM(L24:L25) -> -886 | M26: =SUM(M24:M25) -> -865 | N26: =SUM(N24:N25) -> -487.5154 | O26: =SUM(O24:O25) -> -481.70894 | P26: =SUM(P24:P25) -> -460.43375 | ... R26: =SUM(R24:R25) -> -409.76809
D28: EBT | I28: =I21+I26 -> 1963 | J28: =J21+J26 -> 1788 | K28: =K21+K26 -> 1207 | L28: =L21+L26 -> 1342 | M28: =M21+M26 -> 1646 | N28: =N21+N26 -> 2098.6498 | O28: =O21+O26 -> 2398.2616 | P28: =P21+P26 -> 2625.6394 | ... R28: =R21+R26 -> 3458.1906
D30: Current Taxes | I30: =-'Hist - IS'!H235 -> 152 | J30: =-'Hist - IS'!G235 -> 5 | K30: =-'Hist - IS'!F235 -> -97 | L30: =-'Hist - IS'!E235 -> -84 | M30: =-'Hist - IS'!D235 -> -82 | N30: =-N275 -> -207.15409 | O30: =-O275 -> -282.05705 | P30: =-P275 -> -338.90149 | Q30: =-Q275 -> -437.30296 | R30: =-R275 -> -547.0393
D31: Deferred Taxes | I31: =-'Hist - IS'!H236 -> -841 | J31: =-'Hist - IS'!G236 -> 171 | K31: =-'Hist - IS'!F236 -> -234 | L31: =-'Hist - IS'!E236 -> -196 | M31: =-'Hist - IS'!D236 -> -277 | N31: =-N276 -> -317.50836 | O31: =-O276 -> -317.50836 | P31: =-P276 -> -317.50836 | Q31: =-Q276 -> -317.50836 | R31: =-R276 -> -317.50836
D32: Total Taxes | I32: =SUM(I30:I31) -> -689 | J32: =SUM(J30:J31) -> 176 | K32: =SUM(K30:K31) -> -331 | L32: =SUM(L30:L31) -> -280 | M32: =SUM(M30:M31) -> -359 | N32: =SUM(N30:N31) -> -524.66245 | O32: =SUM(O30:O31) -> -599.5654 | P32: =SUM(P30:P31) -> -656.40985 | ... R32: =SUM(R30:R31) -> -864.54765
D34: ='Hist - IS'!C239 -> Equity in Earnings/(Loss) of Affiliates (after Taxes) | I34: =-'Hist - IS'!H239 -> 0 | J34: =-'Hist - IS'!G239 -> -59 | K34: =-'Hist - IS'!F239 -> -21 | L34: =-'Hist - IS'!E239 -> -8 | M34: =-'Hist - IS'!D239 -> -210 | N34: =Inputs!N62 -> 0 | O34: =Inputs!O62 -> 0 | P34: =Inputs!P62 -> 0 | Q34: =Inputs!Q62 -> 0 | R34: =Inputs!R62 -> 0
D36: Net Income | I36: =I28+I32+I34 -> 1274 | J36: =J28+J32+J34 -> 1905 | K36: =K28+K32+K34 -> 855 | L36: =L28+L32+L34 -> 1054 | M36: =M28+M32+M34 -> 1077 | N36: =N28+N32+N34 -> 1573.9873 | O36: =O28+O32+O34 -> 1798.6962 | P36: =P28+P32+P34 -> 1969.2295 | ... R36: =R28+R32+R34 -> 2593.643
D39: EBITDA Margin | I39: =I17/I11 -> 0.3414248 | J39: =J17/J11 -> 0.35575016 | K39: =K17/K11 -> 0.3275258 | L39: =L17/L11 -> 0.3490918 | M39: =M17/M11 -> 0.37483457 | N39: =N17/N11 -> 0.38128234 | O39: =O17/O11 -> 0.38143049 | P39: =P17/P11 -> 0.37873784 | ... R39: =R17/R11 -> 0.38944699
D40: EBITDA Growth Rate | J40: =(J17-I17)/I17 -> 0.033160039 | K40: =(K17-J17)/J17 -> -0.071943424 | L40: =(L17-K17)/K17 -> 0.042057444 | M40: =(M17-L17)/L17 -> 0.035578681 | N40: =(N17-M17)/M17 -> 0.00030615269 | O40: =(O17-N17)/N17 -> 0.0053905016 | P40: =(P17-O17)/O17 -> 0.0068418258 | Q40: =(Q17-P17)/P17 -> 0.024562897 | R40: =(R17-Q17)/Q17 -> 0.031922138
D41: EBIT Margin | I41: =I21/I11 -> 0.13010314 | J41: =J21/J11 -> 0.12632445 | K41: =K21/K11 -> 0.097528198 | L41: =L21/L11 -> 0.10937653 | M41: =M21/M11 -> 0.12781228 | N41: =N21/N11 -> 0.13386167 | O41: =O21/O11 -> 0.1483276 | P41: =P21/P11 -> 0.15674806 | ... R41: =R21/R11 -> 0.19107412
D42: EBIT Growth Rate | J42: =J21/I21-1 -> -0.037241888 | K42: =K21/J21-1 -> -0.22175412 | L42: =L21/K21-1 -> 0.096456693 | M42: =M21/L21-1 -> 0.12701975 | N42: =N21/M21-1 -> 0.029934363 | O42: =O21/N21-1 -> 0.11360657 | P42: =P21/O21-1 -> 0.071564134 | Q42: =Q21/P21-1 -> 0.12139605 | R42: =R21/Q21-1 -> 0.11767772
D43: Net Income Margin | I43: =I36/I11 -> 0.061117774 | J43: =J36/J11 -> 0.092167013 | K43: =K36/K11 -> 0.041036717 | L43: =L36/L11 -> 0.051742759 | M43: =M36/M11 -> 0.05482032 | N43: =N36/N11 -> 0.081470655 | O43: =O36/O11 -> 0.092638546 | P43: =P36/P11 -> 0.10002126 | ... R43: =R36/R11 -> 0.12812393
D44: Net Income Growth Rate | J44: =J36/I36-1 -> 0.49529042 | K44: =K36/J36-1 -> -0.5511811 | L44: =L36/K36-1 -> 0.23274854 | M44: =M36/L36-1 -> 0.021821632 | N44: =N36/M36-1 -> 0.46145528 | O44: =O36/N36-1 -> 0.14276409 | P44: =P36/O36-1 -> 0.094809418 | Q44: =Q36/P36-1 -> 0.14990858 | R44: =R36/Q36-1 -> 0.14538248
C47: Balance Sheet
C49: Assets
D50: Cash & Cash Equivalents | L50: ='Hist - BS'!D248 -> 216 | M50: ='Hist - BS'!E248 -> 359 | N50: =N138 -> 1358.0905 | O50: =O138 -> 982.44736 | P50: =P138 -> 1032.5984 | Q50: =Q138 -> 673.94703 | R50: =R138 -> 1256.5301
D51: =Inputs!D85 -> Inventories | L51: ='Hist - BS'!D240 -> 331 | M51: ='Hist - BS'!E240 -> 366 | N51: =N156 -> 332.20058 | O51: =O156 -> 342.66204 | P51: =P156 -> 337.95365 | Q51: =Q156 -> 342.2732 | R51: =R156 -> 341.99138
D52: =Inputs!D86 -> Trade and other receivables | L52: ='Hist - BS'!D314 -> 3464 | M52: ='Hist - BS'!E314 -> 3549 | N52: =N157 -> 3387.7208 | O52: =O157 -> 3456.0808 | P52: =P157 -> 3478.3952 | Q52: =Q157 -> 3540.3106 | R52: =R157 -> 3583.1735
D53: =Inputs!D87 -> Preference shares in joint | L53: ='Hist - BS'!D242 -> 161 | M53: ='Hist - BS'!E242 -> 282 | N53: =N158 -> 282 | O53: =O158 -> 282 | P53: =P158 -> 282 | Q53: =Q158 -> 282 | R53: =R158 -> 282
D54: =Inputs!D88 -> Contract assets | L54: ='Hist - BS'!D243 -> 1194 | M54: ='Hist - BS'!E243 -> 1009 | N54: =N159 -> 982.67342 | O54: =O159 -> 977.92607 | P54: =P159 -> 981.77464 | Q54: =Q159 -> 985.49201 | R54: =R159 -> 989.07284
D55: =Inputs!D89 -> Assets classified as held | L55: ='Hist - BS'!D244 -> 245 | M55: ='Hist - BS'!E244 -> 0 | N55: =N160 -> 0 | O55: =O160 -> 0 | P55: =P160 -> 0 | Q55: =Q160 -> 0 | R55: =R160 -> 0
D56: =Inputs!D90 -> Short Term Investments | L56: ='Hist - BS'!D309 -> 2761 | M56: ='Hist - BS'!E309 -> 1550 | N56: =N161 -> 1550 | O56: =O161 -> 1550 | P56: =P161 -> 1550 | Q56: =Q161 -> 1550 | R56: =R161 -> 1550
D57: Total Current Assets | L57: =SUM(L50:L56) -> 8372 | M57: =SUM(M50:M56) -> 7115 | N57: =SUM(N50:N56) -> 7892.6853 | O57: =SUM(O50:O56) -> 7591.1162 | P57: =SUM(P50:P56) -> 7662.7219 | Q57: =SUM(Q50:Q56) -> 7374.0228 | R57: =SUM(R50:R56) -> 8002.7678
D58: =Inputs!D92 -> 0
D59: =Inputs!D93 -> Goodwill | L59: ='Hist - BS'!D253 -> 7310 | M59: ='Hist - BS'!E253 -> 7305 | N59: =N210 -> 7305 | O59: =O210 -> 7305 | P59: =P210 -> 7305 | Q59: =Q210 -> 7305 | R59: =R210 -> 7305
D60: Property Plant & Equipment | L60: ='Hist - BS'!D320 -> 26708 | M60: ='Hist - BS'!E320 -> 27682 | N60: =N205 -> 27860.693 | O60: =O205 -> 28091.817 | P60: =P205 -> 28284.906 | Q60: =Q205 -> 28483.877 | R60: =R205 -> 28668.168
D61: =Inputs!D94 -> Other intangible assets | L61: ='Hist - BS'!D254 -> 5123 | M61: ='Hist - BS'!E254 -> 4663 | N61: =N164 -> 4653.7964 | O61: =O164 -> 4575.3542 | P61: =P164 -> 4621.4501 | Q61: =Q164 -> 4624.8505 | R61: =R164 -> 4648.7298
D62: =Inputs!D95 -> Long Term Investments | L62: ='Hist - BS'!D325 -> 921 | M62: ='Hist - BS'!E325 -> 850 | N62: =N216 -> 850 | O62: =O216 -> 850 | P62: =P216 -> 850 | Q62: =Q216 -> 850 | R62: =R216 -> 850
D63: =Inputs!D96 -> Joint ventures and associates | L63: ='Hist - BS'!D259 -> 252 | M63: ='Hist - BS'!E259 -> 4 | N63: =N221 -> 4 | O63: =O221 -> 4 | P63: =P221 -> 4 | Q63: =Q221 -> 4 | R63: =R221 -> 4
D64: =Inputs!D97 -> Trade and other receivables | L64: ='Hist - BS'!D260 -> 655 | M64: ='Hist - BS'!E260 -> 681 | N64: =N165 -> 645.45785 | O64: =O165 -> 660.86116 | P64: =P165 -> 663.93998 | Q64: =Q165 -> 676.36497 | R64: =R165 -> 684.24726
D65: =Inputs!D98 -> Preference shares in joint | L65: ='Hist - BS'!D261 -> 234 | M65: ='Hist - BS'!E261 -> 0 | N65: =N226 -> 0 | O65: =O226 -> 0 | P65: =P226 -> 0 | Q65: =Q226 -> 0 | R65: =R226 -> 0
D66: =Inputs!D99 -> Contract assets | L66: ='Hist - BS'!D262 -> 306 | M66: ='Hist - BS'!E262 -> 382 | N66: =N166 -> 328.36228 | O66: =O166 -> 348.50579 | P66: =P166 -> 338.96964 | Q66: =Q166 -> 345.72759 | R66: =R166 -> 344.23662
D67: =Inputs!D100 -> Retirement benefit surplus | L67: ='Hist - BS'!D263 -> 142 | M67: ='Hist - BS'!E263 -> 170 | N67: =N167 -> 144.53216 | O67: =O167 -> 157.32553 | P67: =P167 -> 157.25446 | Q67: =Q167 -> 161.83518 | R67: =R167 -> 160.79235
D68: =Inputs!D101 -> Deferred tax assets | L68: ='Hist - BS'!D264 -> 959 | M68: ='Hist - BS'!E264 -> 1124 | N68: =M68+MAX(0,N31) -> 1124 | O68: =N68+MAX(0,O31) -> 1124 | P68: =O68+MAX(0,P31) -> 1124 | Q68: =P68+MAX(0,Q31) -> 1124 | R68: =Q68+MAX(0,R31) -> 1124
D69: Total Non-Current Assets | L69: =SUM(L59:L68) -> 42610 | M69: =SUM(M59:M68) -> 42861 | N69: =SUM(N59:N68) -> 42915.842 | O69: =SUM(O59:O68) -> 43116.863 | P69: =SUM(P59:P68) -> 43349.52 | Q69: =SUM(Q59:Q68) -> 43575.655 | R69: =SUM(R59:R68) -> 43789.174
D70: Total Assets | L70: =L57+L69 -> 50982 | M70: =M57+M69 -> 49976 | N70: =N57+N69 -> 50808.527 | O70: =O57+O69 -> 50707.979 | P70: =P57+P69 -> 51012.242 | Q70: =Q57+Q69 -> 50949.678 | R70: =R57+R69 -> 51791.942
C72: Liabilities
D73: Revolver | N73: =N470 -> 0 | O73: =O470 -> 0 | P73: =P470 -> 0 | Q73: =Q470 -> 0 | R73: =R470 -> 0
D74: =Inputs!D112 -> Derivative financial instruments | L74: ='Hist - BS'!D269 -> 106 | M74: ='Hist - BS'!E269 -> 85 | N74: =N173 -> 85 | O74: =O173 -> 85 | P74: =P173 -> 85 | Q74: =Q173 -> 85 | R74: =R173 -> 85
D75: =Inputs!D113 -> Trade and other payables | L75: ='Hist - BS'!D270 -> 5955 | M75: ='Hist - BS'!E270 -> 5895 | N75: =N174 -> 5640.7556 | O75: =O174 -> 5663.479 | P75: =P174 -> 5660.6819 | Q75: =Q174 -> 5694.7055 | R75: =R174 -> 5709.0795
D76: =Inputs!D114 -> Contract liabilities | L76: ='Hist - BS'!D271 -> 899 | M76: ='Hist - BS'!E271 -> 963 | N76: =N175 -> 899.82532 | O76: =O175 -> 928.03213 | P76: =P175 -> 929.00479 | Q76: =Q175 -> 948.10489 | R76: =R175 -> 958.28868
D77: =Inputs!D115 -> Lease liabilities | L77: ='Hist - BS'!D272 -> 705 | M77: ='Hist - BS'!E272 -> 779 | N77: =N176 -> 717.35493 | O77: =O176 -> 745.4165 | P77: =P176 -> 743.44361 | Q77: =Q176 -> 760.14304 | R77: =R176 -> 767.59539
D78: =Inputs!D116 -> Liabilities held for sale | L78: ='Hist - BS'!D273 -> 188 | M78: ='Hist - BS'!E273 -> 0 | N78: =N177 -> 0 | O78: =O177 -> 0 | P78: =P177 -> 0 | Q78: =Q177 -> 0 | R78: =R177 -> 0
D79: =Inputs!D117 -> Current tax liabilities | L79: ='Hist - BS'!D274 -> 82 | M79: ='Hist - BS'!E274 -> 66 | N79: =N178 -> 84.149991 | O79: =O178 -> 96.163588 | P79: =P178 -> 105.2808 | Q79: =Q178 -> 121.0633 | R79: =R178 -> 138.66378
D80: =Inputs!D118 -> Provisions | L80: ='Hist - BS'!D275 -> 258 | M80: ='Hist - BS'!E275 -> 201 | N80: =N179 -> 534.56507 | O80: =O179 -> 574.99034 | P80: =P179 -> 649.15197 | Q80: =Q179 -> 735.16921 | R80: =R179 -> 848.51917
D81: Total Current Liabiilities | L81: =SUM(L74:L80) -> 8193 | M81: =SUM(M74:M80) -> 7989 | N81: =SUM(N74:N80) -> 7961.651 | O81: =SUM(O74:O80) -> 8093.0815 | P81: =SUM(P74:P80) -> 8172.563 | Q81: =SUM(Q74:Q80) -> 8344.1859 | R81: =SUM(R74:R80) -> 8507.1466
D83: ='Hist - BS'!B331 -> Total loans and Borrowings | L83: ='Hist - BS'!J331 -> 18762 | M83: ='Hist - BS'!K331 -> 18536 | N83: =N303 -> 18281.344 | O83: =O303 -> 16727.376 | P83: =P303 -> 15334.249 | Q83: =Q303 -> 13314.429 | R83: =R303 -> 11913.82
D84: =Inputs!D122 -> Derivative financial instruments | L84: ='Hist - BS'!D281 -> 391 | M84: ='Hist - BS'!E281 -> 313 | N84: =N187 -> 313 | O84: =O187 -> 313 | P84: =P187 -> 313 | Q84: =Q187 -> 313 | R84: =R187 -> 313
D85: =Inputs!D123 -> Contract liabilities | L85: ='Hist - BS'!D282 -> 257 | M85: ='Hist - BS'!E282 -> 274 | N85: =N182 -> 269.44892 | O85: =O182 -> 270.79617 | P85: =P182 -> 274.58731 | Q85: =Q182 -> 278.43153 | R85: =R182 -> 282.32958
D86: =Inputs!D124 -> Lease liabilities | L86: ='Hist - BS'!D283 -> 3866 | M86: ='Hist - BS'!E283 -> 3405 | N86: =N183 -> 3405 | O86: =O183 -> 3405 | P86: =P183 -> 3405 | Q86: =Q183 -> 3405 | R86: =R183 -> 3405
D87: =Inputs!D125 -> Retirement benefit obligations | L87: ='Hist - BS'!D284 -> 4230 | M87: ='Hist - BS'!E284 -> 4379 | N87: =N185 -> 4258.6286 | O87: =O185 -> 4324.4877 | P87: =P185 -> 4472.6139 | Q87: =Q185 -> 4524.3548 | R87: =R185 -> 4533.8837
D88: =Inputs!D126 -> Other payables | L88: ='Hist - BS'!D285 -> 276 | M88: ='Hist - BS'!E285 -> 177 | N88: =N186 -> 214.58122 | O88: =O186 -> 192.54677 | P88: =P186 -> 203.84474 | Q88: =Q186 -> 199.32651 | R88: =R186 -> 202.70541
D89: =Inputs!D127 -> Deferred tax liabilities | L89: ='Hist - BS'!D286 -> 1717 | M89: ='Hist - BS'!E286 -> 1969 | N89: =M89-MIN(0,N31) -> 2286.5084 | O89: =N89-MIN(0,O31) -> 2604.0167 | P89: =O89-MIN(0,P31) -> 2921.5251 | Q89: =P89-MIN(0,Q31) -> 3239.0334 | R89: =Q89-MIN(0,R31) -> 3556.5418
D90: =Inputs!D128 -> Provisions | L90: ='Hist - BS'!D287 -> 382 | M90: ='Hist - BS'!E287 -> 370 | N90: =N184 -> 534.56507 | O90: =O184 -> 574.99034 | P90: =P184 -> 649.15197 | Q90: =Q184 -> 735.16921 | R90: =R184 -> 848.51917
D91: Total Non-Current Liabilites | L91: =SUM(L83:L90) -> 29881 | M91: =SUM(M83:M90) -> 29423 | N91: =SUM(N83:N90) -> 29563.076 | O91: =SUM(O83:O90) -> 28412.214 | P91: =SUM(P83:P90) -> 27573.972 | Q91: =SUM(Q83:Q90) -> 26008.744 | R91: =SUM(R83:R90) -> 25055.799
D92: Total Liabilities | L92: =L91+L81 -> 38074 | M92: =M91+M81 -> 37412 | N92: =N91+N81 -> 37524.727 | O92: =O91+O81 -> 36505.295 | P92: =P91+P81 -> 35746.535 | Q92: =Q91+Q81 -> 34352.93 | R92: =R91+R81 -> 33562.946
C94: Equity
D95: =Inputs!D133 -> Share capital | L95: ='Hist - BS'!D292 -> 499 | M95: ='Hist - BS'!E292 -> 499 | N95: =N232 -> 499 | O95: =O232 -> 499 | P95: =P232 -> 499 | Q95: =Q232 -> 499 | R95: =R232 -> 499
D96: =Inputs!D134 -> Share premium | L96: ='Hist - BS'!D293 -> 1051 | M96: ='Hist - BS'!E293 -> 1051 | N96: =N237 -> 1051 | O96: =O237 -> 1051 | P96: =P237 -> 1051 | Q96: =Q237 -> 1051 | R96: =R237 -> 1051
D97: =Inputs!D135 -> Own shares | L97: ='Hist - BS'!D294 -> -378 | M97: ='Hist - BS'!E294 -> -188 | N97: =N242 -> -188 | O97: =O242 -> -188 | P97: =P242 -> -188 | Q97: =Q242 -> -188 | R97: =R242 -> -188
D98: =Inputs!D136 -> Merger reserve | L98: ='Hist - BS'!D295 -> 998 | M98: ='Hist - BS'!E295 -> 998 | N98: =N247 -> 998 | O98: =O247 -> 998 | P98: =P247 -> 998 | Q98: =Q247 -> 998 | R98: =R247 -> 998
D99: =Inputs!D137 -> Other reserves | L99: ='Hist - BS'!D296 -> 828 | M99: ='Hist - BS'!E296 -> 650 | N99: =N252 -> 650 | O99: =O252 -> 650 | P99: =P252 -> 650 | Q99: =Q252 -> 650 | R99: =R252 -> 650
D100: =Inputs!D138 -> Retained earnings | L100: ='Hist - BS'!D297 -> 9910 | M100: ='Hist - BS'!E297 -> 9554 | N100: =N258 -> 10273.8 | O100: =O258 -> 11192.684 | P100: =P258 -> 12255.707 | Q100: =Q258 -> 13586.748 | R100: =R258 -> 15218.996
D101: Total Equity | L101: =SUM(L95:L100) -> 12908 | M101: =SUM(M95:M100) -> 12564 | N101: =SUM(N95:N100) -> 13283.8 | O101: =SUM(O95:O100) -> 14202.684 | P101: =SUM(P95:P100) -> 15265.707 | Q101: =SUM(Q95:Q100) -> 16596.748 | R101: =SUM(R95:R100) -> 18228.996
D102: Total Liabilities and Equity | L102: =L101+L92 -> 50982 | M102: =M101+M92 -> 49976 | N102: =N101+N92 -> 50808.527 | O102: =O101+O92 -> 50707.979 | P102: =P101+P92 -> 51012.242 | Q102: =Q101+Q92 -> 50949.678 | R102: =R101+R92 -> 51791.942
D104: Check | F104: =SUM(L104:R104) -> 0 | L104: =L102-L70 -> 0 | M104: =M102-M70 -> 0 | N104: =N102-N70 -> 0 | O104: =O102-O70 -> 0 | P104: =P102-P70 -> 0 | Q104: =Q102-Q70 -> 0 | R104: =R102-R70 -> 0
C107: Cashflow Statement
C109: Operating Cashflow
D110: =D36 -> Net Income | N110: =N36 -> 1573.9873 | O110: =O36 -> 1798.6962 | P110: =P36 -> 1969.2295 | Q110: =Q36 -> 2264.4339 | R110: =R36 -> 2593.643
D111: =D20 -> Depreciation & Amortization | N111: =-N20 -> 4780.0893 | O111: =-O20 -> 4525.9918 | P111: =-P20 -> 4370.5595 | Q111: =-Q20 -> 4179.0789 | R111: =-R20 -> 4015.7088
D112: =D31 -> Deferred Taxes | N112: =-N31 -> 317.50836 | O112: =-O31 -> 317.50836 | P112: =-P31 -> 317.50836 | Q112: =-Q31 -> 317.50836 | R112: =-R31 -> 317.50836
D113: =D34 -> Equity in Earnings/(Loss) of Affiliates (after Taxes) | N113: =-N34 -> 0 | O113: =-O34 -> 0 | P113: =-P34 -> 0 | Q113: =-Q34 -> 0 | R113: =-R34 -> 0
D114: =D194 -> Change in UFCF OWC | N114: =N192 -> 395.13134 | O114: =O192 -> 173.05557 | P114: =P192 -> 255.83631 | Q114: =Q192 -> 211.59068 | R114: =R192 -> 217.72673
D115: Operating Cashflows | N115: =SUM(N110:N114) -> 7066.7164 | O115: =SUM(O110:O114) -> 6815.2519 | P115: =SUM(P110:P114) -> 6913.1337 | Q115: =SUM(Q110:Q114) -> 6972.6119 | R115: =SUM(R110:R114) -> 7144.5869
C117: Investing Cashflow
D118: =D203 -> Capital Expenditures | N118: =-N203 -> -4958.7828 | O118: =-O203 -> -4757.1148 | P118: =-P203 -> -4563.6485 | Q118: =-Q203 -> -4378.0502 | R118: =-R203 -> -4200
D119: Long Term Investments | N119: =N215 -> 0 | O119: =O215 -> 0 | P119: =P215 -> 0 | Q119: =Q215 -> 0 | R119: =R215 -> 0
D120: Joint Ventures & Associates | N120: =N220 -> 0 | O120: =O220 -> 0 | P120: =P220 -> 0 | Q120: =Q220 -> 0 | R120: =R220 -> 0
D121: Preference Shares in Joint Ventures | N121: =N226 -> 0 | O121: =O226 -> 0 | P121: =P226 -> 0 | Q121: =Q226 -> 0 | R121: =R226 -> 0
D122: Investing Cashflows | N122: =SUM(N118:N121) -> -4958.7828 | O122: =SUM(O118:O121) -> -4757.1148 | P122: =SUM(P118:P121) -> -4563.6485 | Q122: =SUM(Q118:Q121) -> -4378.0502 | R122: =SUM(R118:R121) -> -4200
C124: Financing Cashflow
...

Sheet Debt Structure
A1: Debt Structure
A2: Name | C2: Issues | D2: Outstanding | E2: Issued
A3: Bonds | C3: 38 | D3: 1.8334841e+10 | E3: 1.8433185e+10
A4: Bonds to Be Issued | C4: 0 | D4: 0 | E4: 0
A5: Bonds (as Borrower) | C5: 0 | D5: 0 | E5: 0
A6: Bonds (as Borrower) - to Be Issued | C6: 0 | D6: 0 | E6: 0
A7: Loans | C7: 1 | D7: ="0" -> 0 | E7: 1.7825932e+09
A8: Total | C8: 39 | D8: 1.8334841e+10 | E8: 2.0215778e+10
A9: Inactive Bonds | C9: 273 | D9: ="0" -> 0 | E9: 4.8226041e+10
A13: Bonds
A14: Bonds
A15: Maturity | C15: Issues | D15: Outstanding (GBP) | E15: Issued (GBP)
A16: 2027 | C16: 1 | D16: 9.7618201e+08 | E16: 9.7618201e+08
A17: Description | B17: MV of Debt | C17: Asset Duplicated | D17: Maturity Date | E17: Amount Outstanding | F17: Issued Amount | G17: Coupon | I17: Coupon Class | J17: Country of Issue | K17: Currency | L17: ISIN | M17: RIC | N17: Cusip | O17: Issue Date | P17: Rank (Seniority) | Q17: Seniority (Legacy) | R17: Instrument Type | S17: Principal Index Link Flag | T17: Modified Duration | U17: Option Adjusted Duration | V17: Option Adjusted Spread | W17: Yield | X17: Yield Type | Y17: Yield Event | Z17: Yield Date | AA17: Last Price | AB17: Capital Tier | AC17: Government Bond Type | AD17: Is Convertible | AE17: Offering Type | AF17: Program Type | AG17: Domicile | AH17: Asset Status | AI17: Green Bonds | AJ17: Issuer | AK17: Collateral
A18: BTBRT / BT 1.500 23-Jun-2027 '27 MTN | B18: =E18*(AA18/100) -> 9.6404807e+08 | C18: -- | D18: 46561 | E18: 976182011 | F18: 976182011 | G18: 1.5 | I18: Fixed Coupon | J18: Eurobond | K18: Euro | L18: XS1637333748 | M18: GB163733374= | N18: -- | O18: 42909 | P18: Senior Unsecured | Q18: Senior Unsecured | R18: Note | S18: N | T18: 0.694946 | U18: 0.697701 | V18: 61.864224 | W18: 3.278186 | X18: IS | Y18: MAT | Z18: 46561 | AA18: 98.757 | AB18: N/A | AC18: -- | AD18: N | AE18: Regulation S | AF18: Medium Term Note Program | AG18: United Kingdom | AH18: Issued | AI18: N | AJ18: BRITISH TELECOMMUNICATIONS LTD | AK18: N/A
A19: BTBRT / BT 2.125 26-Sep-2028 '26 MTN | B19: =E19*(AA19/100) -> 4.1292075e+08 | C19: -- | D19: 47022 | E19: 424426961 | F19: 424426961 | G19: 2.125 | I19: Fixed Coupon | J19: Eurobond | K19: Euro | L19: XS1886403200 | M19: GB188640320= | N19: -- | O19: 43369 | P19: Senior Unsecured | Q19: Senior Unsecured | R19: Note | S19: N | T19: 1.914429 | U19: 1.91605 | V19: 48.09276 | W19: 3.574114 | X19: IS | Y19: MAT | Z19: 47022 | AA19: 97.289 | AB19: N/A | AC19: -- | AD19: N | AE19: Regulation S | AF19: Medium Term Note Program | AG19: United Kingdom | AH19: Issued | AI19: N | AJ19: BRITISH TELECOMMUNICATIONS LTD | AK19: N/A
A20: BTBRT / BT 5.125 04-Dec-2028 '28 | B20: =E20*(AA20/100) -> 5.2728656e+08 | C20: -- | D20: 47091 | E20: 529540812 | F20: 529540812 | G20: 5.125 | I20: Fixed Coupon | J20: United States | K20: US Dollar | L20: US111021AL54 | M20: 111021AL5= | N20: 111021AL5 | O20: 43438 | P20: Senior Unsecured | Q20: Senior Unsecured | R20: Note | S20: N | T20: 1.985975 | U20: 1.923427 | V20: 45.12328 | W20: 5.332504 | X20: CB | Y20: MAT | Z20: 47091 | AA20: 99.5743 | AB20: N/A | AC20: -- | AD20: N | AE20: Underwritten | AF20: -- | AG20: United Kingdom | AH20: Issued | AI20: N | AJ20: BRITISH TELECOMMUNICATIONS LTD | AK20: N/A
A21: BTBRT / BT 5.750 07-Dec-2028 | B21: =E21*(AA21/100) -> 604458000 | C21: -- | D21: 47094 | E21: 600000000 | F21: 600000000 | G21: 5.75 | I21: Fixed Coupon | J21: Eurobond | K21: British Pound | L21: XS0097283096 | M21: GB009728309= | N21: -- | O21: 36298 | P21: Senior Unsecured | Q21: Senior Unsecured | R21: Bond | S21: N | T21: 1.955589 | U21: 1.955589 | V21: 41.297924 | W21: 5.296972 | X21: IS | Y21: MAT | Z21: 47094 | AA21: 100.743 | AB21: N/A | AC21: -- | AD21: N | AE21: Regulation S | AF21: -- | AG21: United Kingdom | AH21: Issued | AI21: N | AJ21: BRITISH TELECOMMUNICATIONS LTD | AK21: N/A
A22: BTBRT / BT 1.125 12-Sep-2029 '29 MTN | B22: =E22*(AA22/100) -> 5.8856772e+08 | C22: -- | D22: 47373 | E22: 636640442 | F22: 636640442 | G22: 1.125 | I22: Fixed Coupon | J22: Eurobond | K22: Euro | L22: XS2051494495 | M22: GB205149449= | N22: -- | O22: 43720 | P22: Senior Unsecured | Q22: Senior Unsecured | R22: Note | S22: N | T22: 2.840907 | U22: 2.842622 | V22: 75.767184 | W22: 3.900222 | X22: IS | Y22: MAT | Z22: 47373 | AA22: 92.449 | AB22: N/A | AC22: -- | AD22: N | AE22: Regulation S | AF22: Medium Term Note Program | AG22: United Kingdom | AH22: Issued | AI22: N | AJ22: BRITISH TELECOMMUNICATIONS LTD | AK22: N/A
A23: BTBRT / BT 3.250 08-Nov-2029 '29 | B23: =E23*(AA23/100) -> 7.0681065e+08 | C23: -- | D23: 47430 | E23: 756486875 | F23: 756486875 | G23: 3.25 | I23: Fixed Coupon | J23: United States | K23: US Dollar | L23: US11102AAE10 | M23: 11102AAE1= | N23: 11102AAE1 | O23: 43777 | P23: Senior Unsecured | Q23: Senior Unsecured | R23: Note | S23: N | T23: 2.838259 | U23: 2.839643 | V23: 61.982311 | W23: 5.593184 | X23: CB | Y23: MAT | Z23: 47430 | AA23: 93.4333 | AB23: N/A | AC23: -- | AD23: N | AE23: Private placement-144A no reg rights | AF23: -- | AG23: United Kingdom | AH23: Issued | AI23: N | AJ23: BRITISH TELECOMMUNICATIONS LTD | AK23: N/A
A24: BTBRT / BT 9.625 15-Dec-2030 | B24: =E24*(AA24/100) -> 2.2919382e+09 | C24: -- | D24: 47832 | E24: 2019819956 | F24: 2118163250 | G24: 9.625 | I24: Variable Coupon | J24: United States | K24: US Dollar | L24: US111021AE12 | M24: GB012169353= | N24: 111021AE1 | O24: 36872 | P24: Senior Unsecured | Q24: Senior Unsecured | R24: Note | S24: N | T24: 3.402381 | U24: 3.402381 | V24: 92.610566 | W24: 5.942206 | X24: CB | Y24: MAT | Z24: 47833 | AA24: 113.4724 | AB24: N/A | AC24: -- | AD24: N | AE24: Underwritten | AF24: -- | AG24: United Kingdom | AH24: Issued | AI24: N | AJ24: BRITISH TELECOMMUNICATIONS LTD | AK24: N/A
A25: BTBRT / BT 3.750 13-May-2031 '31 MTN | B25: =E25*(AA25/100) -> 6.6893764e+08 | C25: -- | D25: 47981 | E25: 679083138 | F25: 679083138 | G25: 3.75 | I25: Fixed Coupon | J25: Eurobond | K25: Euro | L25: XS2582814039 | M25: GB258281403= | N25: -- | O25: 44970 | P25: Senior Unsecured | Q25: Senior Unsecured | R25: Note | S25: N | T25: 4.163538 | U25: 4.103998 | V25: 85.933943 | W25: 4.108838 | X25: IS | Y25: MAT | Z25: 47981 | AA25: 98.506 | AB25: N/A | AC25: -- | AD25: N | AE25: Regulation S | AF25: Medium Term Note Program | AG25: United Kingdom | AH25: Issued | AI25: N | AJ25: BRITISH TELECOMMUNICATIONS LTD | AK25: N/A
A26: BTBRT / BT 3.125 21-Nov-2031 '31 MTN | B26: =E26*(AA26/100) -> 445335000 | C26: -- | D26: 48173 | E26: 500000000 | F26: 500000000 | G26: 3.125 | H26: =(G26/100*B26)/1000000 -> 13.916719 | I26: Fixed Coupon | J26: Eurobond | K26: British Pound | L26: XS1720922415 | M26: GB172092241= | N26: -- | O26: 43060 | P26: Senior Unsecured | Q26: Senior Unsecured | R26: Note | S26: N | T26: 4.523907 | U26: 4.523411 | V26: 56.596281 | W26: 5.561804 | X26: IS | Y26: MAT | Z26: 48173 | AA26: 89.067 | AB26: N/A | AC26: -- | AD26: N | AE26: Regulation S | AF26: Medium Term Note Program | AG26: United Kingdom | AH26: Issued | AI26: N | AJ26: BRITISH TELECOMMUNICATIONS LTD | AK26: N/A
A27: BTBRT / BT 3.125 11-Feb-2032 '31 MTN | B27: =E27*(AA27/100) -> 6.8116368e+08 | C27: -- | D27: 48255 | E27: 721525834 | F27: 721525834 | G27: 3.125 | H27: =(G27/100*B27)/1000000 -> 21.286365 | I27: Fixed Coupon | J27: Eurobond | K27: Euro | L27: XS2994509706 | M27: GB299450970= | N27: -- | O27: 45699 | P27: Senior Unsecured | Q27: Senior Unsecured | R27: Note | S27: N | T27: 4.788758 | U27: 4.776965 | V27: 102.47166 | W27: 4.315463 | X27: IS | Y27: MAT | Z27: 48255 | AA27: 94.406 | AB27: N/A | AC27: -- | AD27: N | AE27: Regulation S | AF27: Euro Medium Term Note Program | AG27: United Kingdom | AH27: Issued | AI27: N | AJ27: BRITISH TELECOMMUNICATIONS LTD | AK27: N/A
A28: BTBRT / BT 3.375 30-Aug-2032 '32 MTN | B28: =E28*(AA28/100) -> 4.027727e+08 | C28: -- | D28: 48456 | E28: 424426961 | F28: 424426961 | G28: 3.375 | H28: =(G28/100*B28)/1000000 -> 13.593579 | I28: Fixed Coupon | J28: Eurobond | K28: Euro | L28: XS2496028924 | M28: GB249602892= | N28: -- | O28: 44803 | P28: Senior Unsecured | Q28: Senior Unsecured | R28: Note | S28: N | T28: 5.293195 | U28: 5.271123 | V28: 105.26451 | W28: 4.374098 | X28: IS | Y28: MAT | Z28: 48456 | AA28: 94.898 | AB28: N/A | AC28: -- | AD28: N | AE28: Regulation S | AF28: Medium Term Note Program | AG28: United Kingdom | AH28: Issued | AI28: N | AJ28: BRITISH TELECOMMUNICATIONS LTD | AK28: N/A
A29: BTBTF / BT 3.375 17-Nov-2032 '32 MTN | B29: =E29*(AA29/100) -> 6.8241913e+08 | C29: -- | D29: 48535 | E29: 721525834 | F29: 721525834 | G29: 3.375 | H29: =(G29/100*B29)/1000000 -> 23.031646 | I29: Fixed Coupon | J29: Eurobond | K29: Euro | L29: XS3227880021 | M29: GB322788002= | N29: -- | O29: 45978 | P29: Senior Unsecured | Q29: Senior Unsecured | R29: Note | S29: N | T29: 5.321028 | U29: 5.304801 | V29: 106.82639 | W29: 4.404324 | X29: IS | Y29: MAT | Z29: 48535 | AA29: 94.58 | AB29: N/A | AC29: -- | AD29: N | AE29: Regulation S | AF29: Euro Medium Term Note Program | AG29: United Kingdom | AH29: Issued | AI29: N | AJ29: BT FINANCE PLC | AK29: N/A
A30: BTBRT / BT 4.250 06-Jan-2033 '32 MTN | B30: =E30*(AA30/100) -> 7.1282423e+08 | C30: -- | D30: 48585 | E30: 721525834 | F30: 721525834 | G30: 4.25 | H30: =(G30/100*B30)/1000000 -> 30.29503 | I30: Fixed Coupon | J30: Eurobond | K30: Euro | L30: XS2675225531 | M30: GB267522553= | N30: -- | O30: 45175 | P30: Senior Unsecured | Q30: Senior Unsecured | R30: Note | S30: N | T30: 5.322946 | U30: 5.268976 | V30: 112.28518 | W30: 4.472195 | X30: IS | Y30: MAT | Z30: 48585 | AA30: 98.794 | AB30: N/A | AC30: -- | AD30: N | AE30: Regulation S | AF30: Medium Term Note Program | AG30: United Kingdom | AH30: Issued | AI30: N | AJ30: BRITISH TELECOMMUNICATIONS LTD | AK30: N/A
A31: BTBRT / BT 4.710 01-Mar-2033 MTN | B31: =E31*(AA31/100) -> 73882257 | C31: -- | D31: 48639 | E31: 78928976 | F31: 78928976 | G31: 4.71 | H31: =(G31/100*B31)/1000000 -> 3.4798543 | I31: Fixed Coupon | J31: Eurobond | K31: Norwegian Krone | L31: XS3168818238 | M31: GB316881823= | N31: -- | O31: 45901 | P31: Senior Unsecured | Q31: Unsecured | R31: Note | S31: N | T31: 4.476715 | U31: 6.052388 | V31: 98.427008 | W31: 5.743384 | X31: IS | Y31: MAT | Z31: 48639 | AA31: 93.606 | AB31: N/A | AC31: -- | AD31: N | AE31: Underwritten-Agent | AF31: Medium Term Note Program | AG31: United Kingdom | AH31: Issued | AI31: N | AJ31: BRITISH TELECOMMUNICATIONS LTD | AK31: N/A
A32: BTBRT / BT 3.640 25-Jun-2033 '33 MTN | B32: =E32*(AA32/100) -> 282648300 | C32: -- | D32: 48755 | E32: 330000000 | F32: 330000000 | G32: 3.64 | H32: =(G32/100*B32)/1000000 -> 10.288398 | I32: Fixed Coupon | J32: Eurobond | K32: British Pound | L32: XS1833075259 | M32: GB183307525= | N32: -- | O32: 43276 | P32: Senior Unsecured | Q32: Senior Unsecured | R32: Note | S32: N | T32: 5.771955 | U32: 5.769146 | V32: 101.76396 | W32: 6.227312 | X32: IS | Y32: MAT | Z32: 48757 | AA32: 85.651 | AB32: N/A | AC32: -- | AD32: N | AE32: Regulation S | AF32: Medium Term Note Program | AG32: United Kingdom | AH32: Issued | AI32: N | AJ32: BRITISH TELECOMMUNICATIONS LTD | AK32: N/A
A33: BTBRT / BT 1.613 25-Jun-2033 '33 | B33: =E33*(AA33/100) -> 300088800 | C33: -- | D33: 48755 | E33: 330000000 | F33: 330000000 | G33: 1.613 | H33: =(G33/100*B33)/1000000 -> 4.8404323 | I33: Fixed Coupon | J33: Eurobond | K33: British Pound | L33: XS1833077545 | M33: GB183307754= | N33: -- | O33: 43276 | P33: Senior Unsecured | Q33: Senior Unsecured | R33: Note | S33: Y | T33: 6.27452 | U33: 6.245989 | V33: -212.13423 | W33: 3.105583 | X33: IS | Y33: MAT | Z33: 48757 | AA33: 90.936 | AB33: N/A | AC33: -- | AD33: N | AE33: Regulation S | AF33: Medium Term Note Program | AG33: United Kingdom | AH33: Issued | AI33: N | AJ33: BRITISH TELECOMMUNICATIONS LTD | AK33: N/A
A34: BTBRT / BT 3.875 20-Jan-2034 '33 MTN | B34: =E34*(AA34/100) -> 7.2695735e+08 | C34: -- | D34: 48964 | E34: 759724261 | F34: 759724261 | G34: 3.875 | H34: =(G34/100*B34)/1000000 -> 28.169597 | I34: Fixed Coupon | J34: Eurobond | K34: Euro | L34: XS2839008948 | M34: GB283900894= | N34: -- | O34: 45463 | P34: Senior Unsecured | Q34: Senior Unsecured | R34: Note | S34: N | T34: 6.149032 | U34: 6.098211 | V34: 117.27217 | W34: 4.581509 | X34: IS | Y34: MAT | Z34: 48964 | AA34: 95.687 | AB34: N/A | AC34: -- | AD34: N | AE34: Regulation S | AF34: Medium Term Note Program | AG34: United Kingdom | AH34: Re-Opening | AI34: N | AJ34: BRITISH TELECOMMUNICATIONS LTD | AK34: N/A
A35: BTBTF / BT 3.875 02-Jun-2034 '34 MTN | B35: =E35*(AA35/100) -> 6.8801817e+08 | C35: -- | D35: 49097 | E35: 721525834 | F35: 721525834 | G35: 3.875 | H35: =(G35/100*B35)/1000000 -> 26.660704 | I35: Fixed Coupon | J35: Eurobond | K35: Euro | L35: XS3392699396 | M35: GB339269939= | N35: -- | O35: 46175 | P35: Senior Unsecured | Q35: Senior Unsecured | R35: Note | S35: N | T35: 6.506005 | U35: 6.454046 | V35: 118.76746 | W35: 4.605721 | X35: IS | Y35: MAT | Z35: 49097 | AA35: 95.356 | AB35: N/A | AC35: -- | AD35: N | AE35: Regulation S | AF35: Euro Medium Term Note Program | AG35: United Kingdom | AH35: Issued | AI35: N | AJ35: BT FINANCE PLC | AK35: N/A
A36: BTBRT / BT 3.750 03-Jan-2035 '34 MTN | B36: =E36*(AA36/100) -> 5.579398e+08 | C36: -- | D36: 49312 | E36: 594197746 | F36: 594197746 | G36: 3.75 | H36: =(G36/100*B36)/1000000 -> 20.922742 | I36: Fixed Coupon | J36: Eurobond | K36: Euro | L36: XS3084359036 | M36: GB308435903= | N36: -- | O36: 45811 | P36: Senior Unsecured | Q36: Senior Unsecured | R36: Note | S36: N | T36: 6.835356 | U36: 6.805564 | V36: 121.181 | W36: 4.656127 | X36: IS | Y36: MAT | Z36: 49312 | AA36: 93.898 | AB36: N/A | AC36: -- | AD36: N | AE36: Regulation S | AF36: Medium Term Note Program | AG36: United Kingdom | AH36: Issued | AI36: N | AJ36: BRITISH TELECOMMUNICATIONS LTD | AK36: N/A
A37: BTBRT / BT 6.375 23-Jun-2037 MTN | B37: =E37*(AA37/100) -> 4.94205e+08 | C37: -- | D37: 50214 | E37: 500000000 | F37: 500000000 | G37: 6.375 | H37: =(G37/100*B37)/1000000 -> 31.505569 | I37: Fixed Coupon | J37: Eurobond | K37: British Pound | L37: XS0306772699 | M37: GB030677269= | N37: -- | O37: 39254 | P37: Senior Unsecured | Q37: Senior Unsecured | R37: Note | S37: N | T37: 7.678187 | U37: 7.676515 | V37: 94.159348 | W37: 6.420218 | X37: IS | Y37: MAT | Z37: 50214 | AA37: 98.841 | AB37: N/A | AC37: -- | AD37: N | AE37: Regulation S | AF37: Medium Term Note Program | AG37: United Kingdom | AH37: Issued | AI37: N | AJ37: BRITISH TELECOMMUNICATIONS LTD | AK37: N/A
... A43: BTBRT / BT 1.774 25-Jun-2042 '42 | B43: =E43*(AA43/100) -> 2.47656e+08 | C43: -- | D43: 52042 | E43: 340000000 | F43: 340000000 | G43: 1.774 | H43: =(G43/100*B43)/1000000 -> 4.3934174 | I43: Fixed Coupon | J43: Eurobond | K43: British Pound | L43: XS1833078600 | M43: GB183307860= | N43: -- | O43: 43276 | P43: Senior Unsecured | Q43: Senior Unsecured | R43: Note | S43: Y | T43: 13.091628 | U43: 13.034254 | V43: -174.53169 | W43: 4.120174 | X43: IS | Y43: MAT | Z43: 52042 | AA43: 72.84 | AB43: N/A | AC43: -- | AD43: N | AE43: Regulation S | AF43: Medium Term Note Program | AG43: United Kingdom | AH43: Issued | AI43: N | AJ43: BRITISH TELECOMMUNICATIONS LTD | AK43: N/A
A44: BTBRT / BT 2.080 17-Feb-2043 MTN | B44: =E44*(AA44/100) -> 0 | C44: -- | D44: 52279 | E44: 47909238 | F44: 47909238 | G44: 2.08 | H44: =(G44/100*B44)/1000000 -> 0 | I44: Fixed Coupon | J44: Eurobond | K44: Japanese Yen | L44: XS2580882558 | M44: XS258088255=1M | N44: -- | O44: 44974 | P44: Senior Unsecured | Q44: Senior Unsecured | R44: Note | S44: N | T44: 0 | U44: 0 | V44: 0 | W44: 0 | X44: -- | Y44: -- | Z44: -- | AA44: 0 | AB44: N/A | AC44: -- | AD44: N | AE44: Regulation S | AF44: Medium Term Note Program | AG44: United Kingdom | AH44: Issued | AI44: N | AJ44: BRITISH TELECOMMUNICATIONS LTD | AK44: N/A
A45: BTBRT / BT 3.625 21-Nov-2047 '47 MTN | B45: =E45*(AA45/100) -> 157375000 | C45: -- | D45: 54017 | E45: 250000000 | F45: 250000000 | G45: 3.625 | H45: =(G45/100*B45)/1000000 -> 5.7048438 | I45: Fixed Coupon | J45: Eurobond | K45: British Pound | L45: XS1720923066 | M45: GB172092306= | N45: -- | O45: 43060 | P45: Senior Unsecured | Q45: Senior Unsecured | R45: Note | S45: N | T45: 12.269888 | U45: 12.05606 | V45: 95.98744 | W45: 6.927023 | X45: IS | Y45: MAT | Z45: 54017 | AA45: 62.95 | AB45: N/A | AC45: -- | AD45: N | AE45: Regulation S | AF45: Medium Term Note Program | AG45: United Kingdom | AH45: Issued | AI45: N | AJ45: BRITISH TELECOMMUNICATIONS LTD | AK45: N/A
A46: BTBRT / BT 4.250 08-Nov-2049 '49 | B46: =E46*(AA46/100) -> 2.6363568e+08 | C46: -- | D46: 54735 | E46: 378243437 | F46: 378243437 | G46: 4.25 | H46: =(G46/100*B46)/1000000 -> 11.204516 | I46: Fixed Coupon | J46: United States | K46: US Dollar | L46: US111021AN11 | M46: 111021AN1= | N46: 111021AN1 | O46: 43777 | P46: Senior Unsecured | Q46: Senior Unsecured | R46: Note | S46: N | T46: 12.414799 | U46: 12.200219 | V46: 117.35547 | W46: 6.889723 | X46: CB | Y46: MAT | Z46: 54735 | AA46: 69.7 | AB46: N/A | AC46: -- | AD46: N | AE46: Private placement-144A no reg rights | AF46: -- | AG46: United Kingdom | AH46: Issued | AI46: N | AJ46: BRITISH TELECOMMUNICATIONS LTD | AK46: N/A
A47: BTBRT / BT 5.125 03-Oct-2054 '29 FRN | B47: =E47*(AA47/100) -> 6.3547539e+08 | C47: -- | D47: 56525 | E47: 636640442 | F47: 636640442 | G47: 5.125 | H47: =(G47/100*B47)/1000000 -> 32.568114 | I47: Floating Coupon | J47: Eurobond | K47: Euro | L47: XS2794589403 | M47: GB279458940= | N47: -- | O47: 45385 | P47: Subordinated Unsecured | Q47: Subordinated Unsecured | R47: Note | S47: N | T47: 2.314254 | U47: 2.552134 | V47: 204.34253 | W47: 5.192155 | X47: IS | Y47: CALL | Z47: 47394 | AA47: 99.817 | AB47: N/A | AC47: -- | AD47: N | AE47: Regulation S | AF47: Medium Term Note Program | AG47: United Kingdom | AH47: Issued | AI47: N | AJ47: BRITISH TELECOMMUNICATIONS LTD | AK47: N/A
A48: BTBRT / BT 6.375 03-Dec-2055 '30 FRN | B48: =E48*(AA48/100) -> 390848000 | C48: -- | D48: 56951 | E48: 400000000 | F48: 400000000 | G48: 6.375 | H48: =(G48/100*B48)/1000000 -> 24.91656 | I48: Floating Coupon | J48: Eurobond | K48: British Pound | L48: XS3085605205 | M48: GB308560520= | N48: -- | O48: 45811 | P48: Subordinated Unsecured | Q48: Subordinated Unsecured | R48: Capital Security | S48: N | T48: 2.937369 | U48: 3.2754 | V48: 208.79153 | W48: 7.020492 | X48: IS | Y48: CALL | Z48: 47820 | AA48: 97.712 | AB48: N/A | AC48: -- | AD48: N | AE48: Regulation S | AF48: Medium Term Note Program | AG48: United Kingdom | AH48: Issued | AI48: N | AJ48: BRITISH TELECOMMUNICATIONS LTD | AK48: N/A
A49: BTBRT / BT 4.875 23-Nov-2081 '31 FRN | B49: =E49*(AA49/100) -> 3.5206332e+08 | C49: -- | D49: 66438 | E49: 378243437 | F49: 378243437 | G49: 4.875 | H49: =(G49/100*B49)/1000000 -> 17.163087 | I49: Floating Coupon | J49: United States | K49: US Dollar | L49: US11102AAG67 | M49: 11102AAG6= | N49: 11102AAG6 | O49: 44523 | P49: Junior Subordinated Unsecured | Q49: Junior Unsecured or Junior Subordinated Unsecured | R49: Capital Security | S49: N | T49: 4.021012 | U49: 4.162601 | V49: 149.62954 | W49: 7.975923 | X49: CB | Y49: MAT | Z49: 66439 | AA49: 93.0785 | AB49: N/A | AC49: -- | AD49: N | AE49: Private placement-144A no reg rights | AF49: -- | AG49: United Kingdom | AH49: Issued | AI49: N | AJ49: BRITISH TELECOMMUNICATIONS LTD | AK49: N/A
A50: BTBRT / BT 4.250 23-Nov-2081 '26 FRN | B50: =E50*(AA50/100) -> 3.7074173e+08 | C50: -- | D50: 66438 | E50: 378243437 | F50: 378243437 | G50: 4.25 | H50: =(G50/100*B50)/1000000 -> 15.756524 | I50: Floating Coupon | J50: United States | K50: US Dollar | L50: US11102AAF84 | M50: 11102AAF8= | N50: 11102AAF8 | O50: 44523 | P50: Subordinated Unsecured | Q50: Subordinated Unsecured | R50: Capital Security | S50: N | T50: 3.803962 | U50: 0.119295 | V50: 1620.3177 | W50: 7.285925 | X50: CB | Y50: MAT | Z50: 66439 | AA50: 98.0167 | AB50: N/A | AC50: -- | AD50: N | AE50: Private placement-144A no reg rights | AF50: -- | AG50: United Kingdom | AH50: Issued | AI50: N | AJ50: BRITISH TELECOMMUNICATIONS LTD | AK50: N/A
A51: BTBRT / BT 8.375 20-Dec-2083 '28 FRN | B51: =E51*(AA51/100) -> 7.25781e+08 | C51: -- | D51: 67195 | E51: 700000000 | F51: 700000000 | G51: 8.375 | H51: =(G51/100*B51)/1000000 -> 60.784159 | I51: Floating Coupon | J51: Eurobond | K51: British Pound | L51: XS2636324274 | M51: GB263632427= | N51: -- | O51: 45097 | P51: Junior Subordinated Unsecured | Q51: Junior Unsecured or Junior Subordinated Unsecured | R51: Capital Security | S51: N | T51: 1.821671 | U51: 1.716983 | V51: 136.94392 | W51: 6.315497 | X51: IS | Y51: CALL | Z51: 47016 | AA51: 103.683 | AB51: N/A | AC51: -- | AD51: N | AE51: Regulation S | AF51: Medium Term Note Program | AG51: United Kingdom | AH51: Issued | AI51: N | AJ51: BRITISH TELECOMMUNICATIONS LTD | AK51: N/A
A52: Total | B52: =SUM(B18:B51) -> 1.7410345e+10 | C52: 38 | E52: 1.8334841e+10 | F52: 1.8433185e+10 | G52: =AVERAGE(G18:G51) -> 4.0878824 | H52: =SUM(H26:H51) -> 464.3255 | W52: =AVERAGE(W18:W51) -> 5.2527918
A53: Yield | B53: =AVERAGE(W18:W51)/100 -> 0.052527918
A55: Loans
A56: Issue Date | C56: Purpose | D56: Amount Issued | E56: Facilities
A57: 30-Jan-2025 British Telecommunications Plc | C57: General Purpose | D57: 1.7825932e+09 | E57: 1
A58: Facility Type | C58: Maturity Date | D58: Facility Amount | E58: Country | F58: Currency | G58: Issue Date | I58: RIC | J58: Base Rate/Spd | K58: Bid Price (%) | L58: Ask Price (%) | M58: Mid Price (%) | N58: Discounted Spread (bps) | O58: Yield (%)
A59: Revolver/Line >= 1 Yr. | C59: 47513 | D59: 1782593237 | E59: United Kingdom | F59: EUR | G59: 45687 | I59: -- | J59: -- | K59: 0 | L59: 0 | M59: 0 | N59: 0 | O59: 0
A60: Total | D60: 1.7825932e+09 | E60: 1
A64: Debt List - Notes/Bonds
A65: Description | B65: Outstanding at Period End Date | C65: Coupon Value | D65: Coupon Class | E65: Maturity Date | F65: Currency | G65: Conv Price | I65: Conv Value | J65: Conv Rate
A66: 1.5% €1,150m bond due June 2027 | B66: 1015 | C66: 1.5 | D66: - | E66: Jun 2027 | F66: GBP | G66: - | I66: - | J66: -
A67: 2.125% €600m bond due September 2028 | B67: 441 | C67: 2.125 | D67: - | E67: Sep 2028 | F67: GBP | G67: - | I67: - | J67: -
A68: 5.125% $700m bond due December 2028 | B68: 538 | C68: 5.125 | D68: - | E68: Dec 2028 | F68: GBP | G68: - | I68: - | J68: -
A69: 5.75% £600m bond due December 2028 | B69: 638 | C69: 5.75 | D69: - | E69: Dec 2028 | F69: GBP | G69: - | I69: - | J69: -
A70: 1.125% €750m bond due September 2029 | B70: 656 | C70: 1.125 | D70: - | E70: Sep 2029 | F70: GBP | G70: - | I70: - | J70: -
A71: 3.25% $1,000m bond due November 2029 | B71: 765 | C71: 3.25 | D71: - | E71: Nov 2029 | F71: GBP | G71: - | I71: - | J71: -
A72: 9.625% $2,670m bond due December 2030 | B72: 2078 | C72: 9.625 | D72: - | E72: Dec 2030 | F72: GBP | G72: - | I72: - | J72: -
A73: 3.75% €800m bond due February 2031 | B73: 720 | C73: 3.75 | D73: - | E73: Nov 2031 | F73: GBP | G73: - | I73: - | J73: -
A74: 3.125% £500m bond due November 2031 | B74: 504 | C74: 3.125 | D74: - | E74: Nov 2031 | F74: GBP | G74: - | I74: - | J74: -
A75: 3.375% €500m bond due August 2032 | B75: 443 | C75: 3.375 | D75: - | E75: Aug 2032 | F75: GBP | G75: - | I75: - | J75: -
A76: 3.64% £330m bond due June 2033 | B76: 339 | C76: 3.64 | D76: - | E76: Jun 2033 | F76: GBP | G76: - | I76: - | J76: -
A77: 1.613% £330m index linked bond due June 2033 | B77: 417 | C77: 1.613 | D77: - | E77: Jun 2033 | F77: GBP | G77: - | I77: - | J77: -
... A98: 6.375% £400m hybrid bond due December 2055e | B98: 405 | C98: 6.375 | D98: - | E98: Dec 2055 | F98: GBP | G98: - | I98: - | J98: -
B99: =SUM(B66:B98) -> 18303

Sheet Hist - BS
B1: Company Fundamentals - Balance Sheet
B2: Company Name | D2: BT Group PLC (BT.L) | J2: ="Balance Sheet Check: "&IF(bs_check=0,"Balanced as all things should be","Error!!!") -> Balance Sheet Check: Balanced as all things should be
B3: Country of Exchange | D3: United Kingdom
B4: Country of Headquarters | D4: United Kingdom
B5: TRBC Industry Group | D5: Telecommunications Services
B6: CF Template | D6: IND
B7: Consolidation Basis | D7: Consolidated
B8: Scaling | D8: Millions
B9: Period | D9: Annual
B10: Export Date | D10: 46298.751
B11: Statement Data | D11: 2026 | E11: 2025 | F11: 2024 | G11: 2023 | H11: 2022
B12: Period End Date | D12: 46112 | E12: 45747 | F12: 45382 | G12: 45016 | H12: 44651
B13: Statement Date | D13: 46112 | E13: 45747 | F13: 45382 | G13: 45016 | H13: 44651
B14: Standardized Currency | D14: GBP | E14: GBP | F14: GBP | G14: GBP | H14: GBP
B15: Template Type | D15: Industrial - Differentiated | E15: Industrial - Differentiated | F15: Industrial - Differentiated | G15: Industrial - Differentiated | H15: Industrial - Differentiated
B17: Balance Sheet - Standardized (Currency: Standardized)
B18: Field Name | D18: 31-03-2026 | E18: 31-03-2025 | F18: 31-03-2024 | G18: 31-03-2023 | H18: 31-03-2022
B19: Current Assets
B20: Cash & Short-Term Investments | D20: 1718 | E20: 2814 | F20: 2780 | G20: 3940 | H20: 3456 | J20: =B20 -> Cash & Short-Term Investments
B21: Cash & Cash Equivalents | D21: 236 | E21: 183 | F21: 414 | G21: 392 | H21: 777
B22: Short-Term Investments - Total | D22: 1482 | E22: 2631 | F22: 2366 | G22: 3548 | H22: 2679
B23: Derivative Financial Instruments - Hedging - Short-Term | D23: 68 | E23: 130 | F23: 50 | G23: 82 | H23: 88
B24: Loans & Receivables - Net - Short-Term | D24: 3463 | E24: 3630 | F24: 4429 | G24: 4138 | H24: 3815
B25: Trade Accounts & Trade Notes Receivable - Net | C25: =D25 -> 1442 | D25: 1442 | E25: 1490 | F25: 1899 | G25: 1395 | H25: 1339
B26: Trade Accounts & Trade Notes Receivable - Gross | D26: 1601 | E26: 1661 | F26: 2068 | G26: 1563 | H26: 1562
B27: Provision - Trade Accounts & Trade Notes Receivable | D27: 159 | E27: 171 | F27: 169 | G27: 168 | H27: 223
B28: Income Tax - Receivables - Short-Term | D28: 433 | E28: 355 | F28: 423 | G28: 427 | H28: 496
B29: Receivables - Other - Total | C29: =D29 -> 1588 | D29: 1588 | E29: 1785 | F29: 2107 | G29: 2316 | H29: 1980
B30: Inventories - Total | D30: 366 | E30: 331 | F30: 409 | G30: 349 | H30: 300 | J30: =B30 -> Inventories - Total
B31: Prepaid Expenses - Short-Term | D31: 636 | E31: 613 | F31: 586 | G31: 545 | H31: 523
B32: Assets Held for Sale/Discontinued Operations - Short-Term | D32: 0 | E32: 245 | F32: 0 | G32: 21 | H32: 80
B33: Other Current Assets - Total | D33: 864 | E33: 609 | F33: 465 | G33: 382 | H33: 646
B34: Deferred Costs - Short-Term | D34: 459 | E34: 415 | F34: 383 | G34: 369 | H34: 336
B35: Restricted Accounts - Short-Term | D35: 123 | E35: 33
B36: Other Current Assets | D36: 282 | E36: 161 | F36: 82 | G36: 13 | H36: 310
B37: Total Current Assets | D37: 7115 | E37: 8372 | F37: 8719 | G37: 9457 | H37: 8908
B38: Non-Current Assets
B39: Investments - Long-Term | D39: 20 | E39: 17 | F39: 29 | G39: 29 | H39: 34
B40: Investments - Available for Sale/Held to Maturity - Long-Term | D40: 20 | E40: 17 | F40: 29 | G40: 29 | H40: 34
B41: Investments in Associates, Joint Ventures and Unconsolidated Subsidiaries | D41: 4 | E41: 486 | F41: 758 | G41: 901 | H41: 5
B42: Receivables & Loans - Long-Term | D42: 456 | E42: 397 | F42: 437 | G42: 467 | H42: 361
B43: Finance Lease Receivables - Long-Term | D43: 74 | E43: 91
B44: Receivables - Other - Net - Long-Term | D44: 382 | E44: 306 | F44: 437 | G44: 467 | H44: 361
B45: Derivative Financial Instruments - Hedging - Long-Term | D45: 830 | E45: 904 | F45: 1020 | G45: 1397 | H45: 1003
B46: Property, Plant & Equipment - Net - Total | D46: 27682 | E46: 26708 | F46: 26204 | G46: 25648 | H46: 25028
B47: Property, Plant & Equipment - excluding Assets Leased Out - Net - Total | D47: 27682 | E47: 26708 | F47: 26204 | G47: 25648 | H47: 25028
B48: Land & Buildings - Net | D48: 400 | E48: 411 | F48: 418 | G48: 449 | H48: 401
B49: Construction in Progress - Net | D49: 1173 | E49: 967 | F49: 1596 | G49: 1594 | H49: 1590
B50: Right of Use Tangible Assets - Total - Net | D50: 3032 | E50: 3328 | F50: 3642 | G50: 3981 | H50: 4429
B51: Right of Use Tangible Assets - Capital/Finance Lease - Net | D51: 3032 | E51: 3328 | F51: 3642 | G51: 3981 | H51: 4429
B52: Property, Plant & Equipment - Other - Net | D52: 23077 | E52: 22002 | F52: 20548 | G52: 19624 | H52: 18608
B53: Property, Plant & Equipment - Gross - Total | D53: 69388 | E53: 68951 | F53: 68298 | G53: 67426 | H53: 64200
B54: Property, Plant & Equipment - excluding Assets Leased Out - Gross | D54: 69388 | E54: 68951 | F54: 68298 | G54: 67426 | H54: 64200
B55: Land & Buildings - Gross | D55: 1066 | E55: 1046 | F55: 1150 | G55: 1165 | H55: 1022
... B67: Deferred Charges - Long-Term | D67: 315 | E67: 291 | F67: 229 | G67: 211 | H67: 226
B68: Prepaid Expenses - Long-Term | D68: 145 | E68: 120
B69: Pension Assets - Long-Term | D69: 170 | E69: 142 | F69: 70 | G69: 52
B70: Other Non-Current Assets | D70: 147 | E70: 153 | F70: 305 | G70: 194 | H70: 111
B71: Intangible Assets - Total - Net | D71: 11968 | E71: 12433 | F71: 12920 | G71: 13687 | H71: 13809
B72: Goodwill/Cost in Excess of Assets Purchased - Net | D72: 7305 | E72: 7310 | F72: 7434 | G72: 7955 | H72: 7917
B73: Intangible Assets - excluding Goodwill - Net - Total | D73: 4663 | E73: 5123 | F73: 5486 | G73: 5732 | H73: 5892
B74: Computer Software - Intangible Assets - Net | D74: 2768 | E74: 2876 | F74: 2823 | G74: 2653 | H74: 2396
B75: Licenses, Franchises, Copyrights, Property Rights, Prototypes, Contract Based, Models & Designs - Net | D75: 1851 | E75: 2023 | F75: 2212 | G75: 2396 | H75: 2582
B76: Intangible Assets - Other - Net | D76: 44 | E76: 224 | F76: 451 | G76: 683 | H76: 914
B77: Intangible Assets - Gross - Total | D77: 22330 | E77: 22286 | F77: 22484 | G77: 21850 | H77: 21107
B78: Goodwill/Cost in Excess of Assets Purchased - Gross | D78: 7793 | E78: 7798 | F78: 7922 | G78: 7955 | H78: 7917
B79: Intangible Assets - excluding Goodwill - Gross | D79: 14537 | E79: 14488 | F79: 14562 | G79: 13895 | H79: 13190
B80: Computer Software - Intangible Assets - Gross | D80: 7702 | E80: 7666 | F80: 7702 | G80: 7021 | H80: 6317
B81: Licenses, Franchises, Copyrights, Property Rights, Prototypes, Contract Based, Models & Designs - Gross | D81: 3453 | E81: 3440 | F81: 3478 | G81: 3491 | H81: 3490
... B89: Total Non-Current Assets | D89: 42861 | E89: 42610 | F89: 43020 | G89: 43295 | H89: 40866
B90: Total Assets
B91: Total Assets | D91: 49976 | E91: 50982 | F91: 51739 | G91: 52752 | H91: 49774
B92: Current Liabilities
B93: Trade Accounts Payable & Accruals - Short-Term | D93: 4871 | E93: 4730 | F93: 5206 | G93: 5235 | H93: 5265
B94: Trade Accounts & Trade Notes Payable - Short-Term | D94: 3825 | E94: 3727 | F94: 4119 | G94: 4196 | H94: 4143
B95: Accrued Expenses - Short-Term | D95: 1046 | E95: 1003 | F95: 1087 | G95: 1039 | H95: 1122
B96: Short-Term Debt & Current Portion of Long-Term Debt | D96: 1199 | E96: 2797 | F96: 2161 | G96: 2572 | H96: 1668
B97: Short-Term Debt & Notes Payable | D97: 105 | E97: 117 | F97: 11 | G97: 11
B98: Current Portion of Long-Term Debt including Capitalized Leases | D98: 1094 | E98: 2680 | F98: 2150 | G98: 2561 | H98: 1668
B99: Current Portion of Long-Term Debt excluding Capitalized Leases | D99: 315 | E99: 1975 | F99: 1384 | G99: 1761 | H99: 873
B100: Capitalized Leases - Current Portion | D100: 779 | E100: 705 | F100: 766 | G100: 800 | H100: 795
B101: Derivative Liabilities - Hedging - Short-Term | D101: 85 | E101: 106 | F101: 94 | G101: 86 | H101: 51
B102: Liabilities Held for Sale/Discontinued Operations - Short-Term | D102: 0 | E102: 188 | F102: 0 | G102: 4 | H102: 40
B103: Income Taxes - Payable - Short-Term | D103: 66 | E103: 82 | F103: 92 | G103: 78 | H103: 90
B104: Other Current Liabilities - Total | D104: 2188 | E104: 2382 | F104: 2265 | G104: 2417 | H104: 1932
B105: Deferred Income - Short-Term | D105: 1341 | E105: 1317 | F105: 1261 | G105: 1391 | H105: 1178
B106: Provisions - Short-Term | D106: 201 | E106: 258 | F106: 238 | G106: 229 | H106: 222
B107: Other Current Liabilities | D107: 646 | E107: 807 | F107: 766 | G107: 797 | H107: 532
B108: Total Current Liabilities | D108: 8409 | E108: 10285 | F108: 9818 | G108: 10392 | H108: 9046
B109: Non-Current Liabilities
B110: Debt - Long-Term - Total | D110: 21521 | E110: 20536 | F110: 21320 | G110: 21308 | H110: 20277
B111: Long-Term Debt excluding Capitalized Leases | D111: 18116 | E111: 16670 | F111: 17131 | G111: 16749 | H111: 15312
B112: Debt - Non-Convertible - Long-Term | D112: 18116 | E112: 16670 | F112: 17131 | G112: 16749 | H112: 15312
B113: Capitalized Lease Obligations - Long-Term | D113: 3405 | E113: 3866 | F113: 4189 | G113: 4559 | H113: 4965
B114: Derivative Liabilities - Hedging - Long-Term | D114: 313 | E114: 391 | F114: 445 | G114: 297 | H114: 819
B115: Deferred Tax & Investment Tax Credits - Long-Term | D115: 1969 | E115: 1717 | F115: 1533 | G115: 1620 | H115: 1960
B116: Deferred Tax - Liability - Long-Term | D116: 1969 | E116: 1717 | F116: 1533 | G116: 1620 | H116: 1960
B117: Other Non-Current Liabilities - Total | D117: 5200 | E117: 5145 | F117: 6105 | G117: 4621 | H117: 2376
B118: Provisions - Long-Term | D118: 4749 | E118: 4612 | F118: 5293 | G118: 3508 | H118: 1582
B119: Post Employment Benefits - Pension & Other - Long-Term | D119: 4379 | E119: 4230 | F119: 4882 | G119: 3139 | H119: 1143
...

Sheet Hist - IS
C1: Company Fundamentals - Income Statement
C2: Company Name | D2: BT Group PLC (BT.L)
C3: Country of Exchange | D3: United Kingdom
C4: Country of Headquarters | D4: United Kingdom
C5: TRBC Industry Group | D5: Telecommunications Services
C6: CF Template | D6: IND
C7: Consolidation Basis | D7: Consolidated
C8: Scaling | D8: Millions
C9: Period | D9: Annual
C10: Export Date | D10: 46298.751
C11: Statement Data | D11: 2026 | E11: 2025 | F11: 2024 | G11: 2023 | H11: 2022
C12: Period End Date | D12: 46112 | E12: 45747 | F12: 45382 | G12: 45016 | H12: 44651
C13: Statement Date | D13: 46112 | E13: 45747 | F13: 45382 | G13: 45016 | H13: 44651
C14: Standardized Currency | D14: GBP | E14: GBP | F14: GBP | G14: GBP | H14: GBP
C15: Template Type | D15: Industrial - Operating | E15: Industrial - Operating | F15: Industrial - Operating | G15: Industrial - Operating | H15: Industrial - Operating
C17: Income Statement - Standardized (Currency: Standardized)
C18: Field Name | D18: 31-03-2026 | E18: 31-03-2025 | F18: 31-03-2024 | G18: 31-03-2023 | H18: 31-03-2022
C19: Revenues
C20: Revenue from Goods & Services | D20: 19646 | E20: 20370 | F20: 20835 | G20: 20669 | H20: 20845
C21: Sales of Goods & Services - Net - Unclassified | D21: 19646 | E21: 20370 | F21: 20835 | G21: 20669 | H21: 20845
C22: Revenue from Business Activities - Total | D22: 19646 | E22: 20370 | F22: 20835 | G22: 20669 | H22: 20845
C23: Operating Expenses
C24: Cost of Operating Revenue | D24: 11327 | E24: 11660 | F24: 12450 | G24: 12562 | H24: 12356
C25: Cost of Revenues - Total | D25: 11327 | E25: 11660 | F25: 12450 | G25: 12562 | H25: 12356
C26: Cost of Revenues - Unclassified | D26: 6474 | E26: 6777 | F26: 7658 | G26: 7820 | H26: 7951
C27: Amortization in Cost of Revenues | D27: 1274 | E27: 1300 | F27: 1248 | G27: 1175 | H27: 1048
C28: Depreciation in Cost of Revenues | D28: 3579 | E28: 3583 | F28: 3544 | G28: 3567 | H28: 3357
C29: Gross Profit - Industrials/Property - Total | D29: 8319 | E29: 8710 | F29: 8385 | G29: 8107 | H29: 8489
C30: Selling, General & Administrative Expenses - Total | D30: 4113 | E30: 4350 | F30: 4477 | G30: 4470 | H30: 4624
C31: Selling, General & Administrative Expenses - Unclassified | D31: 244 | E31: 330 | F31: 367 | G31: 363 | H31: 312
C32: Labor & Related Expenses including Stock-Based Compensation in Selling, General & Administrative Expenses | D32: 3723 | E32: 3849 | F32: 3945 | G32: 3969 | H32: 4210
C33: Selling, General & Administrative Expenses - Other - Total | D33: 146 | E33: 171 | F33: 165 | G33: 138 | H33: 102
C34: Provision for Doubtful Accounts & Write-off | D34: 146 | E34: 171 | F34: 165 | G34: 138 | H34: 102
C35: Other Operating Expense/(Income) - Net | D35: 829 | E35: 1034 | F35: 600 | G35: 451 | H35: 693
... C39: Operating Expenses - Total | D39: 16269 | E39: 17044 | F39: 17527 | G39: 17483 | H39: 17673
C40: Operating Profit | D40: =D26+D27+D28+D30+D37-D36+D38 -> 16269
C41: Operating Profit before Non-Recurring Income/Expense | D41: 3377 | E41: 3326 | F41: 3308 | G41: 3186 | H41: 3172
C42: Non-Operating Expenses
C43: Financing Income/(Expense) - Net - Total | D43: -865 | E43: -886 | F43: -825 | G43: -823 | H43: -749
C44: Interest Expense - Net of (Interest Income) | D44: 872 | E44: 903 | F44: 838 | G44: 830 | H44: 749
C45: Interest Income - Non-Bank | D45: 91 | E45: 134 | F45: 168 | G45: 56 | H45: 12
C46: Interest Expense - Net of Capitalized Interest | D46: 963 | E46: 1037 | F46: 1006 | G46: 886 | H46: 761
C47: Non-Interest Financial Income/(Expense) - Total | D47: 7 | E47: 17 | F47: 13 | G47: 7
B48: =D41+D43+D49 -> 2486 | C48: Non-Interest Financial Income/(Expense) - Other - Net | D48: 7 | E48: 17 | F48: 13 | G48: 7
C49: Other Non-Operating Income/(Expense) - Total | D49: -26 | E49: -19 | F49: -20 | G49: -14
C50: Normalized Pre-tax Profit | D50: 2486 | E50: 2421 | F50: 2463 | G50: 2349 | H50: 2423
C51: Non-Recurring Income/Expense
C52: Non-Recurring Income/(Expense) - Total | D52: -840 | E52: -1079 | F52: -1256 | G52: -561 | H52: -460
C53: Impairment - Tangible & Intangible Fixed Assets | D53: 87 | E53: 211 | F53: 606 | G53: 76
C54: Impairment - Fixed Assets | D54: 48 | E54: 204 | F54: 118 | G54: 76
C55: Impairment - Goodwill | F55: 488
C56: Impairment - Intangibles excluding Goodwill | D56: 39 | E56: 7
C57: Impairment - Financial Investments | D57: 23 | E57: 44
C58: Restructuring Charges | D58: 336 | E58: 448 | F58: 388 | G58: 300 | H58: 347
C59: Litigation Expenses/Settlements | D59: 40
C60: Unrealized Adjustments on Derivatives for Hedging | D60: -169 | E60: -48 | F60: -41 | G60: 11 | H60: -72
C61: Fair Value Adjustments - Financial Investments | D61: -1 | E61: -75
C62: Sale & Acquisition of Group Companies - Gain/(Loss) | D62: -1 | E62: -19 | F62: 22 | G62: -144 | H62: 28
C63: COVID-19 Non-Recurring Income/(Expense) - Total | G63: 0 | H63: 19
C64: COVID-19 Non-Recurring Income/(Expense) - Other | G64: 0 | H64: 19
C65: Non-Recurring Income/(Expense) - Other - Total | D65: -183 | E65: -234 | F65: -243 | G65: -52 | H65: -88
C66: Pre-Tax Income
B67: =B48+D52 -> 1646 | C67: Income before Taxes | D67: 1646 | E67: 1342 | F67: 1207 | G67: 1788 | H67: 1963
C68: Taxes
C69: Income Taxes | D69: 359 | E69: 280 | F69: 331 | G69: -176 | H69: 689
C70: Income Taxes for the Year - Current | D70: 82 | E70: 84 | F70: 97 | G70: -5 | H70: -152
C71: Income Taxes - Domestic - Current | D71: 51 | E71: 17 | F71: 10 | G71: 0 | H71: 0
C72: Income Taxes - Foreign - Current | D72: 60 | E72: 71 | F72: 77 | G72: 67 | H72: 78
B73: =D74+D70 -> 359 | C73: Income Taxes - Other (KFAS/NLST) - Current | D73: -29 | E73: -4 | F73: 10 | G73: -72 | H73: -230
C74: Income Taxes - Deferred | D74: 277 | E74: 196 | F74: 234 | G74: -171 | H74: 841
C75: Income Taxes - Domestic - Deferred | G75: 0 | H75: 420
C76: Income Taxes - Other - Deferred | D76: 277 | E76: 196 | F76: 234 | G76: -171 | H76: 421
C77: Net Income After Tax
B78: =B67-B73 -> 1287 | C78: Net Income after Tax | D78: 1287 | E78: 1062 | F78: 876 | G78: 1964 | H78: 1274
C79: After Tax Income/Expense
C80: Equity in Earnings/(Loss) of Affiliates (after Taxes) | D80: -210 | E80: -8 | F80: -21 | G80: -59 | H80: 0
C81: Income before Discontinued Operations & Extraordinary Items | D81: 1077 | E81: 1054 | F81: 855 | G81: 1905 | H81: 1274
C82: Net Income before Minority Interest | D82: 1077 | E82: 1054 | F82: 855 | G82: 1905 | H82: 1274
C83: Net Income after Minority Interest | D83: 1077 | E83: 1054 | F83: 855 | G83: 1905 | H83: 1274
C84: Net Income
C85: Income Available to Common Shares | D85: 1077 | E85: 1054 | F85: 855 | G85: 1905 | H85: 1274
C86: Other Comprehensive Income
C87: Other Comprehensive Income - Starting Line | D87: 1077 | E87: 1054 | F87: 855 | G87: 1905 | H87: 1274
C88: Other Comprehensive Income - Foreign Currency | D88: -39 | E88: -50 | F88: -66 | G88: 87 | H88: 65
C89: Other Comprehensive Income - Unrealized Investment Gain/(Loss) | D89: 3 | E89: -6 | F89: 0 | G89: -3 | H89: 6
C90: Other Comprehensive Income - Hedging Gain/(Loss) | D90: -183 | E90: 224 | F90: -286 | G90: 342 | H90: 150
C91: Other Comprehensive Income - Associated Companies | D91: 11 | E91: -5 | F91: -11 | G91: -1
C92: Other Comprehensive Income - Pension Related | D92: -736 | E92: 88 | F92: -2444 | G92: -2876 | H92: 2865
C93: Other Comprehensive Income - Income Tax | D93: 209 | E93: -78 | F93: 678 | G93: 642 | H93: -430
C94: Other Comprehensive Income - Net of Tax - Total | D94: -735 | E94: 173 | F94: -2129 | G94: -1809 | H94: 2656
C95: Comprehensive Income before Minority Interest - Total | D95: 342 | E95: 1227 | F95: -1274 | G95: 96 | H95: 3930
C96: Comprehensive Income - Attributable to Parent Company Equity Holders - Total | D96: 342 | E96: 1227 | F96: -1274 | G96: 96 | H96: 3930
C97: Share/Per Share - Basic
C98: Net Income - Basic - including Extraordinary Items Applicable to Common - Total | D98: 1077 | E98: 1054 | F98: 855 | G98: 1905 | H98: 1274
C99: Income available to Common excluding Extraordinary Items | D99: 1077 | E99: 1054 | F99: 855 | G99: 1905 | H99: 1274
C100: Shares used to calculate Basic EPS - Total | D100: 9818 | E100: 9779 | F100: 9823 | G100: 9803 | H100: 9866
C101: EPS - Basic - including Extraordinary Items Applicable to Common - Total | D101: 0.11 | E101: 0.11 | F101: 0.09 | G101: 0.19 | H101: 0.13
C102: EPS - Basic - excluding Extraordinary Items Applicable to Common - Total | D102: 0.11 | E102: 0.11 | F102: 0.09 | G102: 0.19 | H102: 0.13
C103: EPS - Basic - excluding Extraordinary Items - Normalized - Total | D103: 0.2 | E103: 0.22 | F103: 0.21 | G103: 0.25 | H103: 0.18
C104: Allocated Net Income including Extraordinary Items Applicable to Common - Issue Specific | D104: 1077 | E104: 1054 | F104: 855 | G104: 1905 | H104: 1274
...

Sheet Hist - CS
A1: Company Fundamentals - Cash Flow
A2: Company Name | B2: BT Group PLC (BT.L)
A3: Country of Exchange | B3: United Kingdom
A4: Country of Headquarters | B4: United Kingdom
A5: TRBC Industry Group | B5: Telecommunications Services
A6: CF Template | B6: IND
A7: Consolidation Basis | B7: Consolidated
A8: Scaling | B8: Millions
A9: Period | B9: Annual
A10: Export Date | B10: 46298.751
A11: Statement Data | B11: 2026 | C11: 2025 | D11: 2024 | E11: 2023 | F11: 2022
A12: Period End Date | B12: 46112 | C12: 45747 | D12: 45382 | E12: 45016 | F12: 44651
A13: Statement Date | B13: 46112 | C13: 45747 | D13: 45382 | E13: 45016 | F13: 44651
A14: Standardized Currency | B14: GBP | C14: GBP | D14: GBP | E14: GBP | F14: GBP
A15: Template Type | B15: Industrial - Indirect | C15: Industrial - Indirect | D15: Industrial - Indirect | E15: Industrial - Indirect | F15: Industrial - Indirect
A17: Cash Flow - Standardized (Currency: Standardized)
A18: Field Name | B18: 31-03-2026 | C18: 31-03-2025 | D18: 31-03-2024 | E18: 31-03-2023 | F18: 31-03-2022
A19: Operating Cash Flow - Indirect
A20: Profit/(Loss) - Starting Line - Cash Flow | B20: 1436 | C20: 1334 | D20: 1186 | E20: 1729 | F20: 1963
A21: Non-cash Items & Reconciliation Adjustments - Cash Flow | B21: 6369 | C21: 6350 | D21: 6490 | E21: 5956 | F21: 5366
A22: Equity Income/(Loss) in Net Earnings - Cash Flow - to Reconcile | B22: 210 | C22: 8 | D22: 21 | E22: 59 | F22: 0
A23: Financial Income/(Expense) - Cash Flow - to Reconcile | B23: 1251 | C23: 1150 | D23: 1007 | E23: 831 | F23: 922
A24: Other Non-Cash Items & Reconciliation Adjustments - Cash Flow - to Reconcile | B24: 34 | C24: 55 | D24: 76 | E24: 89 | F24: 76
A25: Depreciation, Depletion & Amortization including Impairment - Cash Flow - to Reconcile | B25: 4940 | C25: 5094 | D25: 5398 | E25: 4818 | F25: 4405
A26: Depreciation & Depletion - Property, Plant & Equipment - Cash Flow - to Reconcile | B26: 4913 | C26: 4978 | E26: 4818 | F26: 4405
A27: Impairment - Property, Plant & Equipment including Intangible Assets - Cash Flow - to Reconcile | B27: 27 | C27: 116
A28: Assets Sale - Gain/(Loss) - Cash Flow - to Reconcile | B28: -67 | C28: -32 | D28: -12 | E28: 159 | F28: -37
A29: Financial Assets - Unrealized Gain/(Loss) - Cash Flow - to Reconcile | B29: 1 | C29: 75
A30: Income Taxes - Paid/(Reimbursed) - Cash Flow | B30: 58 | C30: -35 | D30: 59 | E30: -136 | F30: 52
A31: Interest Paid - Cash | B31: 1028 | C31: 956 | D31: 865 | E31: 709 | F31: 755
A32: ] | B32: 96 | C32: 132 | D32: 140 | E32: 41 | F32: 6
A33: Cash Flow from Operating Activities before Changes in Working Capital | B33: 6815 | C33: 6895 | D33: 6892 | E33: 7153 | F33: 6528
A34: Working Capital - Increase/(Decrease) - Cash Flow | B34: -717 | C34: -730 | D34: -1664 | E34: -1097 | F34: -1367 | G34: Working Capital negative
A35: Accounts Receivables - Decrease/(Increase) - Cash Flow | B35: 80 | C35: 454 | D35: -686 | E35: -302 | F35: -104
A36: Inventories - Decrease/(Increase) - Cash Flow | B36: -35 | C36: 78 | D36: -60 | E36: -47 | F36: -3
A37: Other Assets - Decrease/(Increase) - Cash Flow | D37: 0 | E37: 7 | F37: -17
A38: Accounts Payable and Accrued Expenses - Increase/(Decrease) - Cash Flow | B38: 28 | C38: -386 | D38: -89 | E38: 232 | F38: 99
A39: Other Liabilities - Increase/(Decrease) -Total - Cash Flow | B39: -790 | C39: -876 | D39: -829 | E39: -987 | F39: -1342
A40: Net Cash Flow from Operating Activities | B40: 6098 | C40: 6165 | D40: 5228 | E40: 6056 | F40: 5161
A41: Investing Cash Flow
A42: Capital Expenditures - Net - Cash Flow | B42: 5129 | C42: 4901 | D42: 4967 | E42: 5307 | F42: 4605
A43: Property, Plant & Equipment - Purchased/(Sold) - Net - Cash Flow | B43: 5129 | C43: 4901 | D43: 4967 | E43: 5307 | F43: 4605
A44: Property, Plant & Equipment - Purchased - Cash Flow | B44: 5169 | C44: 4937 | D44: 4969 | E44: 5307 | F44: 4607
A45: Property, Plant & Equipment Sold - Cash Flow | B45: 40 | C45: 36 | D45: 2 | E45: 0 | F45: 2
A46: Capital Expenditures - Total | B46: 5169 | C46: 4937 | D46: 4969 | E46: 5307 | F46: 4607
A47: Acquisition & Disposals of Business - Assets - Sold/(Acquired) - Net - Cash Flow | B47: 81 | C47: 145 | D47: 198 | E47: -236 | F47: 76
A48: Acquisition of Business - Cash Flow | E48: 265 | F48: 0
A49: Business - Sold - Cash Flow | E49: 29 | F49: 76
A50: Investments excluding Loans - Decrease/(Increase) - Cash Flow | B50: 1145 | C50: -267 | D50: 1173 | E50: -842 | F50: 962
A51: Investment Securities - Unclassified - Sold/(Purchased) - Net - Total - Cash Flow | B51: 1145 | C51: -267 | D51: 1173 | E51: -842 | F51: 962
A52: Investment Securities - Sold/Matured - Unclassified - Cash Flow | B52: 12840 | C52: 13891 | D52: 12389 | E52: 11868 | F52: 13402
A53: Investment Securities - Purchased - Unclassified - Cash Flow | B53: 11695 | C53: 14158 | D53: 11216 | E53: 12710 | F53: 12440
A54: Investments - Associated Companies & Joint Ventures - Sold/(Purchased) - Cash Flow | B54: 112 | C54: 63
A55: Other Investing Cash Flow - Decrease/(Increase) | B55: -77 | C55: -183 | D55: -86 | E55: -52 | F55: 1
A56: Net Cash Flow from Investing Activities | B56: -3868 | C56: -5143 | D56: -3682 | E56: -6437 | F56: -3566
A57: Financing Cash Flow
A58: Dividends Paid - Cash - Total - Cash Flow | B58: 807 | C58: 788 | D58: 759 | E58: 751 | F58: 228
A59: Dividends - Common - Cash Paid | B59: 807 | C59: 788 | D59: 759 | E59: 751 | F59: 228
A60: Stock - Total - Issuance/(Retirement) - Net - Cash Flow | B60: -30 | C60: -73 | D60: -76 | E60: -133 | F60: -171
A61: Stock - Issuance/(Retirement) - Net - Excluding Options/Warrants - Cash Flow | B61: -126 | C61: -79 | D61: -133 | E61: -138 | F61: -184
A62: Stock - Common - Issuance/(Retirement) - Net - Cash Flow | B62: -126 | C62: -79 | D62: -133 | E62: -138 | F62: -184
A63: Stock - Common - Repurchased/Retired - Cash Flow | B63: 126 | C63: 79 | D63: 133 | E63: 138 | F63: 184
A64: Options Exercised - Cash Flow | B64: 96 | C64: 6 | D64: 57 | E64: 5 | F64: 13
A65: Debt - Long-Term & Short-Term - Issuance/(Retirement) - Total - Cash Flow | B65: -1235 | C65: -282 | D65: -182 | E65: 963 | F65: -1289
A66: Debt - Issued/(Reduced) - Long-Term & Short-Term - Cash Flow | B66: -504 | C66: 457 | D66: 566 | E66: 1690 | F66: -630
A67: Debt - Issued - Long-Term & Short-Term - Cash Flow | B67: 1843 | C67: 2552 | D67: 2242 | E67: 2203 | F67: 744
A68: Debt - Reduced - Long-Term & Short-Term - Cash Flow | B68: 2347 | C68: 2095 | D68: 1676 | E68: 513 | F68: 1374
A69: Debt - Issued/(Reduced) - Long-Term - Cash Flow | B69: -731 | C69: -739 | D69: -748 | E69: -727 | F69: -659
... A74: Net Cash Flow from Financing Activities | B74: -2078 | C74: -1155 | D74: -1563 | E74: 73 | F74: -1803
A75: Foreign Exchange Effects
A76: Foreign Exchange Effects - Cash Flow | B76: -10 | C76: -9 | D76: -8 | E76: -3 | F76: 4
A77: Change in Cash
A78: Net Change in Cash - Total | B78: 142 | C78: -142 | D78: -25 | E78: -311 | F78: -204
A79: Net Cash from Continuing Operations | B79: 142 | C79: -142 | D79: -25 | E79: -311 | F79: -204
A80: Net Cash - Beginning Balance | B80: 214 | C80: 356 | D80: 381 | E80: 692 | F80: 896
A81: Net Cash - Ending Balance | B81: 356 | C81: 214 | D81: 356 | E81: 381 | F81: 692
A82: Supplemental
A83: Income Taxes - Paid/(Reimbursed) - Cash Flow - Supplemental | B83: 58 | C83: -35 | D83: 59 | E83: -136 | F83: 52
A84: Interest Paid - Cash Flow - Supplemental | B84: 1028 | C84: 956 | D84: 865 | E84: 709 | F84: 755
A85: Interest & Dividends - Received - Cash Flow - Supplemental | B85: 96 | C85: 132 | D85: 140 | E85: 41 | F85: 6
A86: CF from Optg Activities before Change in WC & Int Payments | B86: 7843 | C86: 7851 | D86: 7757 | E86: 7862 | F86: 7283
A87: Non-GAAP Free Cash Flow - Company Reported | B87: 1901 | C87: 2088 | D87: 986 | E87: 1300
A88: Contract Assets - Decrease/(Increase) - Cash Flow | B88: 100 | C88: 219 | D88: 157 | E88: -17 | F88: -51
A89: Contract Liabilities - Increase/(Decrease) - Cash Flow | B89: 77 | C89: 99 | D89: 39 | E89: 41 | F89: -93
A90: Cash Dividends Paid & Common Stock Buyback - Net | B90: 933 | C90: 867 | D90: 892 | E90: 889 | F90: 412
A91: Common Stock Buyback - Net | B91: 126 | C91: 79 | D91: 133 | E91: 138 | F91: 184
A92: Depreciation, Depletion & Amortization - Cash Flow | B92: 4913 | C92: 4978 | E92: 4818 | F92: 4405
A93: Free Cash Flow to Equity | B93: -266 | C93: 982 | D93: 79 | E93: 1712 | F93: -733
A94: Free Cash Flow Net of Dividends | B94: 122 | C94: 440 | D94: -500 | E94: -2 | F94: 326
A95: Free Cash Flow | B95: 929 | C95: 1228 | D95: 259 | E95: 749 | F95: 554
A96: Dividends Provided/Paid - Common | B96: 822 | C96: 801 | D96: 783 | E96: 760 | F96: 755
B101: =B96/'3-Statement'!M36 -> 0.7632312 | C101: ='Hist - CS'!C96/'3-Statement'!L36 -> 0.75996205 | D101: =D96/'3-Statement'!K36 -> 0.91578947

Sheet FRED YTM
A1: observation_date | B1: m_date | C1: IRLTLT01GBM156N
A2: 21916 | B2: =TEXT(A2,"mm/YYYY") -> 01/1960 | C2: 5.33
A3: 21947 | B3: =TEXT(A3,"mm/YYYY") -> 02/1960 | C3: 5.4
A4: 21976 | B4: =TEXT(A4,"mm/YYYY") -> 03/1960 | C4: 5.59
A5: 22007 | B5: =TEXT(A5,"mm/YYYY") -> 04/1960 | C5: 5.67
A6: 22037 | B6: =TEXT(A6,"mm/YYYY") -> 05/1960 | C6: 5.69
A7: 22068 | B7: =TEXT(A7,"mm/YYYY") -> 06/1960 | C7: 6.04
A8: 22098 | B8: =TEXT(A8,"mm/YYYY") -> 07/1960 | C8: 6.01
A9: 22129 | B9: =TEXT(A9,"mm/YYYY") -> 08/1960 | C9: 6.03
A10: 22160 | B10: =TEXT(A10,"mm/YYYY") -> 09/1960 | C10: 6.1
A11: 22190 | B11: =TEXT(A11,"mm/YYYY") -> 10/1960 | C11: 6.1
A12: 22221 | B12: =TEXT(A12,"mm/YYYY") -> 11/1960 | C12: 6.14
A13: 22251 | B13: =TEXT(A13,"mm/YYYY") -> 12/1960 | C13: 6.17
... A802: 46266 | B802: =TEXT(A802,"mm/YYYY") -> 09/2026 | C802: 4.9937

Sheet FInancial Summary
A1: Company Fundamentals - Financial Summary
A2: Company Name | B2: BT Group PLC (BT.L)
A3: Country of Exchange | B3: United Kingdom
A4: Country of Headquarters | B4: United Kingdom
A5: TRBC Industry Group | B5: Telecommunications Services
A6: CF Template | B6: IND
A7: Consolidation Basis | B7: Consolidated
A8: Scaling | B8: Millions
A9: Period | B9: Annual
A10: Export Date | B10: 46299.951
A11: Statement Data | B11: 2026 | C11: 2025 | D11: 2024 | E11: 2023 | F11: 2022
A12: Period End Date | B12: 46112 | C12: 45747 | D12: 45382 | E12: 45016 | F12: 44651
A13: Statement Date | B13: 46112 | C13: 45747 | D13: 45382 | E13: 45016 | F13: 44651
A14: Standardized Currency | B14: GBP | C14: GBP | D14: GBP | E14: GBP | F14: GBP
A15: Template Type | B15: Industrial - Operating | C15: Industrial - Operating | D15: Industrial - Operating | E15: Industrial - Operating | F15: Industrial - Operating
A17: Financial Summary - Standardized (Currency: Standardized)
A18: Field Name | B18: 31-03-2026 | C18: 31-03-2025 | D18: 31-03-2024 | E18: 31-03-2023 | F18: 31-03-2022
A19: Selected Income Statement Items
A20: Revenue from Business Activities - Total | B20: 19646 | C20: 20370 | D20: 20835 | E20: 20669 | F20: 20845
A21: Gross Profit - Industrials/Property - Total | B21: 8319 | C21: 8710 | D21: 8385 | E21: 8107 | F21: 8489
A22: Operating Profit before Non-Recurring Income/Expense | B22: 3377 | C22: 3326 | D22: 3308 | E22: 3186 | F22: 3172
A23: Earnings before Interest, Taxes, Depreciation & Amortization (EBITDA) | B23: 8230 | C23: 8209 | D23: 8100 | E23: 7928 | F23: 7577
A24: Income before Discontinued Operations & Extraordinary Items | B24: 1077 | C24: 1054 | D24: 855 | E24: 1905 | F24: 1274
A25: Selected Balance Sheet Items
A26: Cash & Cash Equivalents | B26: 236 | C26: 183 | D26: 414 | E26: 392 | F26: 777
A27: Cash & Short-Term Investments | B27: 1718 | C27: 2814 | D27: 2780 | E27: 3940 | F27: 3456
A28: Total Assets | B28: 49976 | C28: 50982 | D28: 51739 | E28: 52752 | F28: 49774
A29: Debt - Total | B29: 22720 | C29: 23333 | D29: 23481 | E29: 23880 | F29: 21945
A30: Common Equity - Total | B30: 12564 | C30: 12908 | D30: 12518 | E30: 14514 | F30: 15296
A31: Selected Cash Flow Items
A32: Net Cash Flow from Operating Activities | B32: 6098 | C32: 6165 | D32: 5228 | E32: 6056 | F32: 5161
A33: Depreciation, Depletion & Amortization including Impairment - Cash Flow - to Reconcile | B33: 4940 | C33: 5094 | D33: 5398 | E33: 4818 | F33: 4405
A34: Capital Expenditures - Net - Cash Flow | B34: 5129 | C34: 4901 | D34: 4967 | E34: 5307 | F34: 4605
A35: Net Change in Cash - Total | B35: 142 | C35: -142 | D35: -25 | E35: -311 | F35: -204
A36: Free Cash Flow Net of Dividends | B36: 122 | C36: 440 | D36: -500 | E36: -2 | F36: 326
A37: Selected Per Share Data
A38: Dividend Yield - Common Stock - Gross - Issue Specific - % | B38: 3.9 | C38: 4.88 | D38: 7.02 | E38: 5.28 | F38: 1.27
A39: Dividend Yield - Common Stock - Net - Issue Specific - % | B39: 3.9 | C39: 4.88 | D39: 7.02 | E39: 5.28 | F39: 1.27
A40: EPS - Diluted - excluding Extraordinary Items Applicable to Common - Total | B40: 0.11 | C40: 0.11 | D40: 0.09 | E40: 0.19 | F40: 0.13
A41: Shares used to calculate Diluted EPS - Total | B41: 9939 | C41: 9960 | D41: 9998 | E41: 10057 | F41: 10136
A42: Company Reported Non-GAAP Measures
A43: Non-GAAP Revenues - Company Reported | B43: 19646 | C43: 20370 | D43: 20835 | E43: 20669 | F43: 20845
A44: Non-GAAP Income from Operations - Company Reported | B44: 3355 | C44: 3276
A45: Non-GAAP Adjusted Net Earnings - Company Reported | B45: 1793 | C45: 1835
A46: Non-GAAP Adjusted EBITDA - Company Reported | B46: 8230 | C46: 8209 | D46: 8100 | E46: 7928 | F46: 7577
A47: Non-GAAP EPS Basic - Company Reported | B47: 0.18 | C47: 0.19 | D47: 0.19 | E47: 0.21 | F47: 0.2
A48: Non-GAAP EPS Diluted - Company Reported | B48: 0.18 | C48: 0.18 | D48: 0.18 | E48: 0.22 | F48: 0.2
A49: Non-GAAP Free Cash Flow - Company Reported | B49: 1901 | C49: 2088 | D49: 986 | E49: 1300
A50: Profitability / Return
A51: Gross Profit Margin - % | B51: 42.34 | C51: 42.76 | D51: 40.24 | E51: 39.22 | F51: 40.72
A52: EBITDA Margin - % | B52: 41.89 | C52: 40.3 | D52: 38.88 | E52: 38.36 | F52: 36.35
A53: Operating Margin - % | B53: 17.19 | C53: 16.33 | D53: 15.88 | E53: 15.41 | F53: 15.22
A54: Income before Tax Margin - % | B54: 8.38 | C54: 6.59 | D54: 5.79 | E54: 8.65 | F54: 9.42
A55: Income Tax Rate - % | B55: 21.81 | C55: 20.86 | D55: 27.42 | E55: -9.84 | F55: 35.1
A56: Net Margin - % | B56: 5.48 | C56: 5.17 | D56: 4.1 | E56: 9.22 | F56: 6.11
A57: Free Cash Flow | B57: 929 | C57: 1228 | D57: 259 | E57: 749 | F57: 554
A58: Return on Average Common Equity - % (Income available to Common excluding Extraordinary Items) | B58: 8.46 | C58: 8.29 | D58: 6.33 | E58: 12.78 | F58: 9.45
A59: Return on Average Total Assets - % (Income before Discontinued Operations & Extraordinary Items) | B59: 2.13 | C59: 2.05 | D59: 1.64 | E59: 3.72 | F59: 2.53
A60: Return on Invested Capital - % | B60: 5.12 | C60: 5.19 | D60: 4.26 | E60: 7.61 | F60: 4.93
A61: Growth
A62: Revenue from Business Activities - Total | B62: 19646 | C62: 20370 | D62: 20835 | E62: 20669 | F62: 20845
A63: Operating Profit before Non-Recurring Income/Expense | B63: 3377 | C63: 3326 | D63: 3308 | E63: 3186 | F63: 3172
A64: Earnings before Interest, Taxes, Depreciation & Amortization (EBITDA) | B64: 8230 | C64: 8209 | D64: 8100 | E64: 7928 | F64: 7577
A65: Income before Discontinued Operations & Extraordinary Items | B65: 1077 | C65: 1054 | D65: 855 | E65: 1905 | F65: 1274
A66: EPS - Diluted - excluding Extraordinary Items Applicable to Common - Total | B66: 0.11 | C66: 0.11 | D66: 0.09 | E66: 0.19 | F66: 0.13
A67: Common Shares - Outstanding - Total | B67: 9967.64 | C67: 9956.84 | D67: 9951.83 | E67: 9931.94 | F67: 9926.7
A68: Financial Strength / Leverage
A69: Total Debt Percentage of Total Assets | B69: 45.46 | C69: 45.77 | D69: 45.38 | E69: 45.27 | F69: 44.09
A70: Total Debt Percentage of Total Capital | B70: 64.39 | C70: 64.38 | D70: 65.23 | E70: 62.2 | F70: 58.93
A71: Total Debt Percentage of Total Equity | B71: 180.83 | C71: 180.76 | D71: 187.58 | E71: 164.53 | F71: 143.47
A72: Debt Service | B72: 2870 | C72: 3382 | D72: 3204.5 | E72: 2950 | F72: 2403.5
A73: Debt Service Percentage of Normalized after Tax Profit | B73: 134.93 | C73: 157.96 | D73: 150.3 | E73: 116.83 | F73: 138.61
A74: Interest Coverage Ratio | B74: 3.51 | C74: 3.21 | D74: 3.29 | E74: 3.6 | F74: 4.17
A75: Dividend Coverage - % | B75: 131.02 | C75: 131.59 | D75: 109.2 | E75: 250.66 | F75: 168.74
A76: Earnings Retention Rate | B76: 0.24 | C76: 0.24 | D76: 0.08 | E76: 0.6 | F76: 0.41
A77: Dividend Payout Ratio - % | B77: 76.32 | C77: 76 | D77: 91.58 | E77: 39.9 | F77: 59.26
A78: Enterprise Value Breakdown
A79: Market Capitalization | B79: 20981.88 | C79: 16513.41 | D79: 10912.18 | E79: 14480.76 | F79: 18085.96
A80: Debt - Total | B80: 22720 | C80: 23333 | D80: 23481 | E80: 23880 | F80: 21945
A81: Cash & Short Term Investments - Total | B81: 1718 | C81: 2814 | D81: 2780 | E81: 3940 | F81: 3456
A82: Enterprise Value | B82: 41983.88 | C82: 37032.41 | D82: 31613.18 | E82: 34420.76 | F82: 36574.96
A83: Dupont / Earning Power
A84: Asset Turnover | B84: 0.39 | C84: 0.4 | D84: 0.4 | E84: 0.4 | F84: 0.41
A85: Income before Tax Margin - % | B85: 8.38 | C85: 6.59 | D85: 5.79 | E85: 8.65 | F85: 9.42
A86: Pretax ROA - % | B86: 3.26 | C86: 2.61 | D86: 2.31 | E86: 3.49 | F86: 3.9
A87: Total Assets to Total Shareholders Equity - including Minority Interest & Hybrid Debt | B87: 3.96 | C87: 4.04 | D87: 3.87 | E87: 3.44 | F87: 3.73
A88: Pretax ROE - % | B88: 12.92 | C88: 10.56 | D88: 8.93 | E88: 12 | F88: 14.55
A89: Tax Complement | B89: 0.78 | C89: 0.79 | D89: 0.73 | E89: 1.1 | F89: 0.65
A90: Return on Average Common Equity - % (Income available to Common excluding Extraordinary Items) | B90: 8.46 | C90: 8.29 | D90: 6.33 | E90: 12.78 | F90: 9.45
A91: Earnings Retention Rate | B91: 0.24 | C91: 0.24 | D91: 0.08 | E91: 0.6 | F91: 0.41
A92: Reinvestment Rate - % | B92: 2 | C92: 1.99 | D92: 0.53 | E92: 7.68 | F92: 3.85
A93: Productivity
A94: Net Income after Tax per Employee | B94: 15840 | C94: 12000 | D94: 9279.66 | E94: 20092.07 | F94: 12862.19
A95: Sales per Employee | B95: 241796.92 | C95: 230169.49 | D95: 220709.75 | E95: 211447.57 | F95: 210449.27
A96: Total Assets per Employee | B96: 647357.51 | C96: 597678.78 | D96: 564220.28 | E96: 543274.97 | F96: 505833.33
A97: Liquidity
A98: Current Ratio | B98: 0.85 | C98: 0.81 | D98: 0.89 | E98: 0.91 | F98: 0.98
A99: Quick Ratio | B99: 0.8 | C99: 0.78 | D99: 0.85 | E99: 0.88 | F99: 0.95
A100: Working Capital to Total Assets | B100: -0.03 | C100: -0.04 | D100: -0.02 | E100: -0.02 | F100: 0
A101: Operating
...
