Workbook
Name Audit_check: Guide!$G$133
Name Base_year: Guide!$E$32
Name Circular_Toggle: Guide!$E$19
Name company: Guide!$E$11
Name currency: Guide!$E$20
Name Date_last_historical: Guide!$E$28
Name Floating: "Floating"
Name Forecast_year: Guide!$E$33
Name l_scenarios: Scn!$D$16:$D$18
Name Last_updated: Guide!$E$22
Name Live_Scenario: Scn!$D$15
Name Modeler: Guide!$E$23
Name models: Guide!$B$49
Name months_in_period: Guide!$E$31
Name onths_in_period: Guide!$E$31
Name S_Scenarios: Scn!$F$15
Name Version: Guide!$E$21

Sheet Cover
D9: =company -> Nestle Nigeria
D10: ="Financial model for "&Base_year+1&" - "&Forecast_year -> Financial model for 2023 - 2027
D14: WIP:
D15: Live Scenario yet to be automated
D16: Audit Check

Sheet Guide
D2: =company -> Nestle Nigeria | O2: =Version -> Ver 1.01.
D3: =models -> Model Style Guide
B8: Model Details
C9: This section highlights general information about the company being modeled and technical information about thee project
C10: Company Information
D11: Company Name | E11: Nestle Nigeria
D12: Purpose of the Model | E12: Support 5 year strategic plan
D13: Industry | E13: FMCG
D14: Location | E14: Nigeria
C16: Model Information
D17: Model Owner | E17: Srategic mgt team
D18: Circularity in Model | E18: Deliberate circularity in th interest income and interest expense lines of theCalculation sheet
D19: Iteration Toggle | E19: FALSE
D20: Currency | E20: ₦ Th's
D21: Version | E21: =INDEX(D:D,MATCH("Ω",D:D,1)) -> Ver 1.01. | F21: Ω
D22: Last Updated | E22: =INDEX(E:E,MATCH("Ω",E:E,1)) -> Date Modified
D23: Current Modeler | E23: =INDEX(F:F,MATCH("Ω",F:F,1)) -> Opeoluwa Kuku
B25: Model Structure & Navigation
C27: Major Timings
D28: Latest Historical Financials end Date | E28: 44926
D29: Model Forecast period | E29: 5
D30: Months in the Year | E30: 12
D31: Months in each time period | E31: 12
D32: Historical Financial Year | E32: =YEAR(E28) -> 2022
D33: Forecast Period End Year | E33: =E32+E29 -> 2027
C35: Sheet Structure
D36: Cover
D37: Guide
D38: Summary
D39: Historicals & Restructured Financials
D40: Inputs & Assumptions
D41: Scenario Inputs
D42: Calculatios
D43: Income Statement
D44: Balance Sheet
D45: Cash Flow Statement
D46: Ratio Analysis
D47: Valuation Analysis
B49: Model Style Guide
C50: This style guide will help you efficiently navigate through and interprete sections of this model
C51: Style Guide
D52: Input Cells | E52: 1234.56
D54: Linked Cells | E54: 1234.56
D56: Formula Cells | E56: 1234.56
D58: Historical Cells | E58: 1234.56
D60: Percent Cells | E60: 0.2345
D62: Subtotal Cells | E62: 1234.56
D64: Total cells | E64: 1234.56
D66: Multiples Cells | E66: 23.4
D68: Title Cells | E68: Title Cells
D70: Sub-title Cells | E70: Sub-title Cells
D72: Heading 1 | E72: Heading 1
D74: Heading 2 | E74: Heading 2
D76: Table Headers | E76: Table Headers
D78: FLAG: TRUE | E78: 1
D80: FLAG: FALSE | E80: 0
D82: Blank style
B84: Names
C85: This contains the names of named cells contained in the model, it comes in handy for auditing exercises
C86: Names used in the Model
D88: Names | E88: Description
D89: company | E89: =Guide!$E$11
D90: Last_updated | E90: =Guide!$E$22
D91: Modeler | E91: =Guide!$E$23
D92: models | E92: =Guide!$B$49
D93: Version | E93: =Guide!$E$21
B95: Glossary
C96: Key terms and definitions
C97: Key Terms
D99: Term | E99: Description
D100: IS | E100: Income Statement
D101: PL | E101: Profit and Loss Statement
D102: BS | E102: Balance Sheet
D103: CF | E103: Cashflow Statement
D104: EBIT | E104: Earnings Before Interest and Taxes
D105: EBITDA | E105: Earnings Before Interest, Taxes, Depreciatiton and Amortistion
D106: FMCG | E106: Fast Moving Consumer Goods
D107: Base Year | E107: Last audited records
B112: Summary Audit Control
B113: This section contains the summary of each section
C114: Model Audit Checks
D116: Model Check Description | F116: Error Count | G116: Status
D117: Base (Historical) BS Check | F117: =Hist!I162 -> 0 | G117: =IF(F117=0,"OK", "ERROR") -> OK
D118: Base (Historical) BS Solvency Check | F118: =Hist!I163 -> 0 | G118: =IF(F118=0,"OK", "ERROR") -> OK
D119: Restructured (Historical) BS Check | F119: =Hist!I164 -> 0 | G119: =IF(F119=0,"OK", "ERROR") -> OK
D120: Restructured BS Solvency Check | F120: =Hist!I165 -> 0 | G120: =IF(F120=0,"OK", "ERROR") -> OK
D121: Restructured P/Lvs Audit check | F121: =Hist!I114 -> 0 | G121: =IF(F121=0,"OK", "ERROR") -> OK
D122: =Hist!D305 -> Reconciliation of Trade and Other Receivables | F122: =Hist!I305 -> 0 | G122: =IF(F122=0,"OK", "ERROR") -> OK
D123: Detailed loans and borrowing Vs Audit cheeck | F123: =Hist!J368 -> 0 | G123: =IF(F123=0,"OK", "ERROR") -> OK
D124: =Hist!D222 -> Recon depreciation classification | F124: =Hist!I222 -> 0 | G124: =IF(F124=0,"OK", "ERROR") -> OK
D125: =Hist!D239 -> Recon impairment classification | F125: =Hist!I239 -> 0 | G125: =IF(F125=0,"OK", "ERROR") -> OK
D126: =Hist!D266 -> Recon of Tax Expense | F126: =Hist!I266 -> 0 | G126: =IF(F126=0,"OK", "ERROR") -> OK
D128: Restructuring Depreciation check | F128: =Hist!I217 -> 0 | G128: =IF(F128=0,"OK", "ERROR") -> OK
D129: Forecast Balance Sheet Check | F129: =BS!I52 -> 0 | G129: =IF(F129=0,"OK", "ERROR") -> OK
D130: Recon of historical loans and borrowings in calculation sheet | F130: =Calc!J178 -> 0 | G130: =IF(F130=0,"OK", "ERROR") -> OK
D131: =Hist!D344 -> Trade Payables Reconciliation | F131: =Hist!I344 -> 0 | G131: =IF(F131=0,"OK", "ERROR") -> OK
D133: GENERAL CHECK | F133: =SUM(F117:F131) -> 0 | G133: =IF(F133=0,"OK", "ERROR") -> OK
B136: Version Control
C137: This section documents the different changes to the model, to track versions efficiently
C138: Change Log
...

Sheet Summary
B2: =company -> Nestle Nigeria
C3: Summary
D4: =Live_Scenario -> Live Scenario: Base Case | H4: Start Date | J4: =I5+1 -> 43831 | K4: =J5+1 -> 44197 | L4: =K5+1 -> 44562 | M4: =L5+1 -> 44927 | N4: =M5+1 -> 45292 | O4: =N5+1 -> 45658 | P4: =O5+1 -> 46023 | Q4: =P5+1 -> 46388
D5: ="Audit Check: "& Audit_check -> Audit Check: OK | H5: End Date | I5: =EOMONTH(J5,-months_in_period) -> 43830 | J5: =EOMONTH(K5,-months_in_period) -> 44196 | K5: =EOMONTH(L5,-months_in_period) -> 44561 | L5: =Date_last_historical -> 44926 | M5: =EOMONTH(L5,months_in_period) -> 45291 | N5: =EOMONTH(M5,months_in_period) -> 45657 | O5: =EOMONTH(N5,months_in_period) -> 46022 | P5: =EOMONTH(O5,months_in_period) -> 46387 | Q5: =EOMONTH(P5,months_in_period) -> 46752
D6: Actual | J6: =(J5<=Date_last_historical)*1 -> 1 | K6: =(K5<=Date_last_historical)*1 -> 1 | L6: =(L5<=Date_last_historical)*1 -> 1 | M6: =(M5<=Date_last_historical)*1 -> 0 | N6: =(N5<=Date_last_historical)*1 -> 0 | O6: =(O5<=Date_last_historical)*1 -> 0 | P6: =(P5<=Date_last_historical)*1 -> 0 | Q6: =(Q5<=Date_last_historical)*1 -> 0
D7: Forecast | J7: =(J5>=Date_last_historical)*1 -> 0 | K7: =(K5>=Date_last_historical)*1 -> 0 | L7: =(L5>Date_last_historical)*1 -> 0 | M7: =(M5>=Date_last_historical)*1 -> 1 | N7: =(N5>=Date_last_historical)*1 -> 1 | O7: =(O5>=Date_last_historical)*1 -> 1 | P7: =(P5>=Date_last_historical)*1 -> 1 | Q7: =(Q5>=Date_last_historical)*1 -> 1
D8: Description | E8: Units | F8: Inputs | I8: Row Totals | J8: Hist | K8: Hist | L8: Hist | M8: Proj | N8: Proj | O8: Proj | P8: Proj | Q8: Proj

Sheet Hist
B2: =company -> Nestle Nigeria
C3: Historicals & Restructured Financials
D4: =Live_Scenario -> Live Scenario: Base Case | H4: Start Date | J4: =I5+1 -> 43831 | K4: =J5+1 -> 44197 | L4: =K5+1 -> 44562 | M4: =L5+1 -> 44927 | N4: =M5+1 -> 45292 | O4: =N5+1 -> 45658 | P4: =O5+1 -> 46023 | Q4: =P5+1 -> 46388
D5: ="Audit Check: "& Audit_check -> Audit Check: OK | H5: End Date | I5: =EOMONTH(J5,-months_in_period) -> 43830 | J5: =EOMONTH(K5,-months_in_period) -> 44196 | K5: =EOMONTH(L5,-months_in_period) -> 44561 | L5: =Date_last_historical -> 44926 | M5: =EOMONTH(L5,months_in_period) -> 45291 | N5: =EOMONTH(M5,months_in_period) -> 45657 | O5: =EOMONTH(N5,months_in_period) -> 46022 | P5: =EOMONTH(O5,months_in_period) -> 46387 | Q5: =EOMONTH(P5,months_in_period) -> 46752
D6: Actual | J6: =(J5<=Date_last_historical)*1 -> 1 | K6: =(K5<=Date_last_historical)*1 -> 1 | L6: =(L5<=Date_last_historical)*1 -> 1 | M6: =(M5<=Date_last_historical)*1 -> 0 | N6: =(N5<=Date_last_historical)*1 -> 0 | O6: =(O5<=Date_last_historical)*1 -> 0 | P6: =(P5<=Date_last_historical)*1 -> 0 | Q6: =(Q5<=Date_last_historical)*1 -> 0
D7: Forecast | J7: =(J5>Date_last_historical)*1 -> 0 | K7: =(K5>Date_last_historical)*1 -> 0 | L7: =(L5>Date_last_historical)*1 -> 0 | M7: =(M5>Date_last_historical)*1 -> 1 | N7: =(N5>Date_last_historical)*1 -> 1 | O7: =(O5>Date_last_historical)*1 -> 1 | P7: =(P5>Date_last_historical)*1 -> 1 | Q7: =(Q5>Date_last_historical)*1 -> 1
D8: Description | E8: Units | F8: Inputs | I8: Row Totals | J8: Hist | K8: Hist | L8: Hist | M8: Proj | N8: Proj | O8: Proj | P8: Proj | Q8: Proj
B10: Financial Statements - Per Audit
B11: These are the financial statement numbers extracted from the latest audited accounts (As is)
C12: Statement of Profit or loss and other Comprehensive Income
D13: Revenue | E13: =currency -> ₦ Th's | J13: 287084087 | K13: 351822329 | L13: 446819260
D14: Cost of sales | E14: =currency -> ₦ Th's | J14: -167872616 | K14: -219985914 | L14: -291054270
D15: Gross Profit | E15: =currency -> ₦ Th's | J15: 119211471 | K15: 131836414 | L15: 155764990
D16: Marketing and distribution expenses | E16: =currency -> ₦ Th's | J16: -43843396 | K16: -48097581 | L16: -57331351
D17: Administrative expenses | E17: =currency -> ₦ Th's | J17: -10949492 | K17: -11494450 | L17: -11538113
B18: Need to model this newkline | D18: Impairment of financial assets | J18: 0 | K18: -278438 | L18: -29043
D19: Results from operating activities | E19: =currency -> ₦ Th's | J19: 64418583 | K19: 71965945 | L19: 86866483
D20: Finance income | E20: =currency -> ₦ Th's | J20: 646546 | K20: 1987042 | L20: 4777113
D21: Finance costs | E21: =currency -> ₦ Th's | J21: -4426686 | K21: -12077645 | L21: -20534225
D22: Net finance cost | E22: =currency -> ₦ Th's | J22: -3780140 | K22: -10090603 | L22: -15757112
D23: Profit before income tax | E23: =currency -> ₦ Th's | J23: 60638443 | K23: 61875342 | L23: 71109371
D24: Income tax expense | E24: =currency -> ₦ Th's | J24: -21426418 | K24: -21838065 | L24: -22143883
D25: Profit for the year | E25: =currency -> ₦ Th's | J25: 39212025 | K25: =SUM(K13:K14,K16:K18,K20:K21,K24) -> 40037278 | L25: 48965488
C27: Statement of Financial Position
D28: Assets
D29: Property, plant and equipment | E29: =currency -> ₦ Th's | J29: 87265836 | K29: 98964157 | L29: =116739370-1+N("Rounding error per audited account") -> 116739369
D30: Right of Use Assets | E30: =currency -> ₦ Th's | J30: 5054528 | K30: 4848732 | L30: 4976420
D31: Long term receivables | E31: =currency -> ₦ Th's | J31: 2363177 | K31: 2501289 | L31: 2816337
D32: Total non-current assets | E32: =currency -> ₦ Th's | J32: =SUM(J29:J31) -> 94683541 | K32: =SUM(K29:K31) -> 106314178 | L32: =SUM(L29:L31) -> 124532126
D33: Inventories | E33: =currency -> ₦ Th's | J33: 52222267 | K33: 58964125 | L33: 88340532
D34: Right of return assets | E34: =currency -> ₦ Th's | J34: 52263 | K34: 45443 | L34: 72879
D35: Trade and other receivables | E35: =currency -> ₦ Th's | J35: 39555290 | K35: =43302758-2+N(("rounding error per audit")) -> 43302756 | L35: 82237026
D36: Prepayments | E36: =currency -> ₦ Th's | J36: 968426 | K36: 1093841 | L36: 1929038
D37: Cash and short term-deposit | E37: =currency -> ₦ Th's | J37: 58703209 | K37: 100518159 | L37: 117932430
D38: Total current assets | E38: =currency -> ₦ Th's | J38: =SUM(J33:J37) -> 151501455 | K38: =SUM(K33:K37) -> 203924324 | L38: =SUM(L33:L37) -> 290511905
D39: Total assets | E39: =currency -> ₦ Th's | J39: =J32+J38 -> 246184996 | K39: =K32+K38 -> 310238502 | L39: =L32+L38 -> 415044031
D40: Equity
D41: Share capital | E41: =currency -> ₦ Th's | J41: 396328 | K41: 396328 | L41: 396328
D42: Share premium | E42: =currency -> ₦ Th's | J42: 32262 | K42: 32262 | L42: 32262
D43: Share based payment reserve | E43: =currency -> ₦ Th's | J43: 113811 | K43: =113459-3+N("rounding error per audited") -> 113456 | L43: 90127
D44: Retained earnings | E44: =currency -> ₦ Th's | J44: 28754583 | K44: 20836160 | L44: 29772507
D45: Total Equity | E45: =currency -> ₦ Th's | J45: =SUM(J41:J44) -> 29296984 | K45: =SUM(K41:K44) -> 21378206 | L45: =SUM(L41:L44) -> 30291224
D46: Liabilities
D47: Interest bearing Loans and borrowings | E47: =currency -> ₦ Th's | J47: 33834202 | K47: 76432859 | L47: 147006556
D48: Employee benefits | E48: =currency -> ₦ Th's | J48: 4471021 | K48: 4038600 | L48: 4359648
B49: Need to model this newkline | D49: Lease liabilities | E49: =currency -> ₦ Th's | J49: 568084 | K49: 283135 | L49: 127889
D50: Deferred tax liabilities | E50: =currency -> ₦ Th's | J50: 11984354 | K50: 12587716 | L50: 14854152
D51: Total non- current liabilities | E51: =currency -> ₦ Th's | J51: =SUM(J47:J50) -> 50857661 | K51: =SUM(K47:K50) -> 93342310 | L51: =SUM(L47:L50) -> 166348245
D52: Trade and other payables | E52: =currency -> ₦ Th's | J52: 116512689 | K52: 148384425 | L52: 166161861
D53: Contract liabilities | E53: =currency -> ₦ Th's | J53: 8647246 | K53: 15452355 | L53: 16548425
D54: Refund liabilities | E54: =currency -> ₦ Th's | J54: 90805 | K54: 78963 | L54: 112333
D55: Bank Overdraft | E55: =currency -> ₦ Th's | J55: 2551 | K55: 2352 | L55: 0
D56: Current tax liabilities | E56: =currency -> ₦ Th's | J56: 30476315 | K56: 28281629 | L56: 26208706
B57: Need to model this newkline | D57: Lease liabilities | E57: =currency -> ₦ Th's | J57: 231270 | K57: 184821 | L57: 53717
D58: Interest bearing Loans and borrowings | E58: =currency -> ₦ Th's | J58: 6377484 | K58: 431943 | L58: 8293512
D59: Provisions | E59: =currency -> ₦ Th's | J59: 3691991 | K59: 2701498 | L59: 1026008
D60: Total current liabilities | E60: =currency -> ₦ Th's | J60: =SUM(J52:J59) -> 166030351 | K60: =SUM(K52:K59) -> 195517986 | L60: =SUM(L52:L59) -> 218404562
D61: Total liabilities | E61: =currency -> ₦ Th's | J61: =J51+J60 -> 216888012 | K61: =K51+K60 -> 288860296 | L61: =L51+L60 -> 384752807
D62: Total equity and liabilities | E62: =currency -> ₦ Th's | J62: =J61+J45 -> 246184996 | K62: =K61+K45 -> 310238502 | L62: =L61+L45 -> 415044031
J63: =J62-J39 -> 0 | K63: =K62-K39 -> 0 | L63: =L62-L39 -> 0
C64: Financial Summary
C65: The financial information presented reflects historical summaries based on International Financial Reporting Standards.
D66: Funds Employed
D67: Share Capital | E67: =currency -> ₦ Th's
D68: Share Premium | E68: =currency -> ₦ Th's
D69: Share based payment reserve | E69: =currency -> ₦ Th's
D70: Retained Earnings | E70: =currency -> ₦ Th's
D71: Shareholder's Fund | E71: =currency -> ₦ Th's
D72: Current Liabilities | E72: =currency -> ₦ Th's
D73: Non-current Liabilities | E73: =currency -> ₦ Th's
E74: =currency -> ₦ Th's
D76: Asset Employed
D77: Non Current assets | E77: =currency -> ₦ Th's
D78: Current assets | E78: =currency -> ₦ Th's
E79: =currency -> ₦ Th's
D81: Revenue | E81: =currency -> ₦ Th's
D83: Profit before income tax | E83: =currency -> ₦ Th's
D84: Profit for the year | E84: =currency -> ₦ Th's
D86: Other comprehensive income, net of tax | E86: =currency -> ₦ Th's
D87: Declared dividend* | E87: =currency -> ₦ Th's
D89: Per 50k share data:
D90: Basic earnings per share | E90: ₦/share
D91: Diluted earnings per share | E91: ₦/share
D92: Declared dividend per share | E92: ₦/share
D93: Net assets per share | E93: ₦/share
B96: Financial Statement Normalized
B97: Statement of Profit or Loss
D99: Revenue | J99: =J13 -> 287084087 | K99: =K13 -> 351822329 | L99: =L13 -> 446819260
D100: Cost of Sales | J100: =J186 -> 162807627 | K100: =K186 -> 214296403 | L100: =L186 -> 284557646
D101: Gross Profit | J101: =J99-J100 -> 124276460 | K101: =K99-K100 -> 137525926 | L101: =L99-L100 -> 162261614
D102: SG&A Expenses | J102: =J205 -> 52543061 | K102: =K205 -> 57316411 | L102: =L205 -> 66347382
D103: EBITDA | J103: =J101-J102 -> 71733399 | K103: =K101-K102 -> 80209515 | L103: =L101-L102 -> 95914232
D104: Depreciation | J104: =J216 -> 7314816 | K104: =K216 -> 7965131 | L104: =L216 -> 9018706
D105: Impairement | J105: =J244 -> 0 | K105: =K244 -> 278438 | L105: =L244 -> 29043
D106: EBIT | J106: =J103-J104-J105 -> 64418583 | K106: =K103-K104-K105 -> 71965946 | L106: =L103-L104-L105 -> 86866483
D107: Interest income | J107: =J252 -> 646546 | K107: =K252 -> 1987042 | L107: =L252 -> 4777113
D108: Interest Expense | J108: =J257 -> 2698404 | K108: =K257 -> 7342611 | L108: =L257 -> 12682244
D109: Net Foreign Exchange Loss | J109: =J256 -> 1728282 | K109: =K256 -> 4735034 | L109: =L256 -> 7851981
D110: EBT | J110: =J106+J107-J108-J109 -> 60638443 | K110: =K106+K107-K108-K109 -> 61875343 | L110: =L106+L107-L108-L109 -> 71109371
D111: Current Tax Expense | J111: =J263 -> 21899010 | K111: =K263 -> 21234703 | L111: =L263 -> 19877447
...

Sheet Inps
B2: =company -> Nestle Nigeria
C3: Inputs & Assumptions
D4: =Live_Scenario -> Live Scenario: Base Case | H4: Start Date | J4: =I5+1 -> 43831 | K4: =J5+1 -> 44197 | L4: =K5+1 -> 44562 | M4: =L5+1 -> 44927 | N4: =M5+1 -> 45292 | O4: =N5+1 -> 45658 | P4: =O5+1 -> 46023 | Q4: =P5+1 -> 46388
D5: ="Audit Check: "& Audit_check -> Audit Check: OK | H5: End Date | I5: =EOMONTH(J5,-months_in_period) -> 43830 | J5: =EOMONTH(K5,-months_in_period) -> 44196 | K5: =EOMONTH(L5,-months_in_period) -> 44561 | L5: =Date_last_historical -> 44926 | M5: =EOMONTH(L5,months_in_period) -> 45291 | N5: =EOMONTH(M5,months_in_period) -> 45657 | O5: =EOMONTH(N5,months_in_period) -> 46022 | P5: =EOMONTH(O5,months_in_period) -> 46387 | Q5: =EOMONTH(P5,months_in_period) -> 46752
D6: Actual | J6: =(J5<=Date_last_historical)*1 -> 1 | K6: =(K5<=Date_last_historical)*1 -> 1 | L6: =(L5<=Date_last_historical)*1 -> 1 | M6: =(M5<=Date_last_historical)*1 -> 0 | N6: =(N5<=Date_last_historical)*1 -> 0 | O6: =(O5<=Date_last_historical)*1 -> 0 | P6: =(P5<=Date_last_historical)*1 -> 0 | Q6: =(Q5<=Date_last_historical)*1 -> 0
D7: Forecast | J7: =(J5>=Date_last_historical)*1 -> 0 | K7: =(K5>=Date_last_historical)*1 -> 0 | L7: =(L5>Date_last_historical)*1 -> 0 | M7: =(M5>=Date_last_historical)*1 -> 1 | N7: =(N5>=Date_last_historical)*1 -> 1 | O7: =(O5>=Date_last_historical)*1 -> 1 | P7: =(P5>=Date_last_historical)*1 -> 1 | Q7: =(Q5>=Date_last_historical)*1 -> 1
D8: Description | E8: Units | F8: Inputs | I8: Row Totals | J8: Hist | K8: Hist | L8: Hist | M8: Proj | N8: Proj | O8: Proj | P8: Proj | Q8: Proj
B10: General Assumptions
C11: Assumptions in this section generally affect multiple sections and calculations of the financial model
C12: Timings and Counters
D13: Simple Counter | E13: Counter | J13: =K13-1 -> -2 | K13: =L13-1 -> -1 | L13: =0 -> 0 | M13: =L13+1 -> 1 | N13: =M13+1 -> 2 | O13: =N13+1 -> 3 | P13: =O13+1 -> 4 | Q13: =P13+1 -> 5
D14: Year | E14: Year | J14: =YEAR(J5) -> 2020 | K14: =YEAR(K5) -> 2021 | L14: =YEAR(L5) -> 2022 | M14: =YEAR(M5) -> 2023 | N14: =YEAR(N5) -> 2024 | O14: =YEAR(O5) -> 2025 | P14: =YEAR(P5) -> 2026 | Q14: =YEAR(Q5) -> 2027
D15: Days in the year | E15: Days | J15: =J5-I5 -> 366 | K15: =K5-J5 -> 365 | L15: =L5-K5 -> 365 | M15: =M5-L5 -> 365 | N15: =N5-M5 -> 366 | O15: =O5-N5 -> 365 | P15: =P5-O5 -> 365 | Q15: =Q5-P5 -> 365
B18: Profit Or Loss Assumptions
C19: Assumptions in this section generally affect multiple sections and calculations of the financial model
D22: =Hist!D99 -> Revenue | E22: yoy % growth from scn sheet | J22: 0 | K22: =(Hist!K13/Hist!J13)-1 -> 0.22550272 | L22: =(Hist!L13/Hist!K13)-1 -> 0.27001393 | M22: =Scn!M23 -> 0.22 | N22: =Scn!N23 -> 0.22 | O22: =Scn!O23 -> 0.22 | P22: =Scn!P23 -> 0.22 | Q22: =Scn!Q23 -> 0.22
D23: =Hist!D100 -> Cost of Sales | E23: % of Revenue | J23: =Hist!J100/Hist!J99 -> 0.56710781 | K23: =Hist!K100/Hist!K99 -> 0.60910404 | L23: =Hist!L100/Hist!L99 -> 0.63685179 | M23: =Scn!M29 -> 0.6571 | N23: =Scn!N29 -> 0.6571 | O23: =Scn!O29 -> 0.6571 | P23: =Scn!P29 -> 0.6571 | Q23: =Scn!Q29 -> 0.6571
D24: =Hist!D101 -> Gross Profit
D25: =Hist!D102 -> SG&A Expenses | E25: % of Revenue | J25: =Hist!J102/Hist!J99 -> 0.18302324 | K25: =Hist!K102/Hist!K99 -> 0.16291294 | L25: =Hist!L102/Hist!L99 -> 0.14848819 | M25: =Scn!M35 -> 0.14848819 | N25: =Scn!N35 -> 0.14848819 | O25: =Scn!O35 -> 0.14848819 | P25: =Scn!P35 -> 0.14848819 | Q25: =Scn!Q35 -> 0.14848819
D27: =Hist!D104 -> Depreciation | E27: % of previous PP&E | J27: 0 | K27: =Hist!K104/Hist!J120 -> 0.086277075 | L27: =Hist!L104/Hist!K120 -> 0.086874627 | M27: 0.0957 | N27: 0.0957 | O27: 0.0957 | P27: 0.0957 | Q27: 0.0957
D28: =Hist!D105 -> Impairement | E28: Fixed amount | J28: =Hist!J105 -> 0 | K28: =Hist!K105 -> 278438 | L28: =Hist!L105 -> 29043 | M28: 29043 | N28: 29043 | O28: 29043 | P28: 29043 | Q28: 29043
D30: =Hist!D107 -> Interest income
D31: =Hist!D108 -> Interest Expense
D32: =Hist!D109 -> Net Foreign Exchange Loss | E32: Fixed amount | J32: =Hist!J109 -> 1728282 | K32: =Hist!K109 -> 4735034 | L32: =Hist!L109 -> 7851981 | M32: 7851981 | N32: 7851981 | O32: 7851981 | P32: 7851981 | Q32: 7851981
D34: =Hist!D111 -> Current Tax Expense | E34: Statutory Tax Rate | J34: 0.32 | K34: 0.32 | L34: 0.32 | M34: 0.32 | N34: 0.32 | O34: 0.32 | P34: 0.32 | Q34: 0.32
D35: Reduction in EBT for Timing difference | E35: Implied reduction on EBT based on govt financials | J35: =Hist!J112/Inps!J34 -> -1476850 | K35: =Hist!K112/Inps!K34 -> 1885506.2 | L35: =Hist!L112/Inps!L34 -> 7082612.5 | M35: 3300000 | N35: 3300000 | O35: 3300000 | P35: 3300000 | Q35: 3300000
D36: Total Tax | E36: Effective Tax Rate | J36: =(Hist!J112+Hist!J111)/Hist!J110 -> 0.3533471 | K36: =(Hist!K112+Hist!K111)/Hist!K110 -> 0.35293647 | L36: =(Hist!L112+Hist!L111)/Hist!L110 -> 0.31140597
D37: Dividend Payout Ratio | E37: Dividend Payout Ratio | M37: 0.8 | N37: 0.8 | O37: 0.8 | P37: 0.8 | Q37: 0.8
B41: Balance Sheet Assumptions
C42: Assumptions in this section generally affect multiple sections and calculations of the financial model
B43: =Hist!B118 -> Assets
C44: =Hist!C119 -> Non - Current Assets
D45: =Hist!D120 -> PP&E
D46: Maintanable Capex | E46: Inflation factor | M46: =Scn!M41 -> 1.2 | N46: =Scn!N41 -> 1.2 | O46: =Scn!O41 -> 1.2 | P46: =Scn!P41 -> 1.2 | Q46: =Scn!Q41 -> 1.2 | R46: replacing currentt capex for maintaining production
D47: Incremental Capex | E47: Fixed factor | M47: 0 | N47: 0 | O47: 0 | P47: 0 | Q47: 0 | R47: You can also use historicals for determining the rate at which a business acquires new properties every year and use sales as the driver… e.g fast food restaurants and new locations
C48: =Hist!C123 -> Current Assets
D49: =Hist!D124 -> Trade Receivables | E49: % of revenues | J49: =ABS((L49/K49)-1) -> 0.028404045 | K49: =Hist!K124/Hist!K99 -> 0.011955512 | L49: =Hist!L124/Hist!L99 -> 0.012295097 | M49: 0.0694 | N49: 0.0694 | O49: 0.0694 | P49: 0.0694 | Q49: 0.0694 | R49: =L49/K49-1 -> 0.028404045
D50: =Hist!D125 -> Staff Loans | E50: Ending Balance | J50: =ABS((L50/K50)-1) -> 0.041318139 | K50: =Hist!K125 -> 2870047 | L50: =Hist!L125 -> 2988632 | M50: 2866469 | N50: 2866469 | O50: 2866469 | P50: 2866469 | Q50: 2866469 | R50: predictive power, should idealy be under 1%
D51: =Hist!D126 -> Deposit with Company registrars for dividend | E51: % EAT | J51: =ABS((L51/K51)-1) -> 0.25936443 | K51: =Hist!K126/Hist!K113 -> 0.069965346 | L51: =Hist!L126/Hist!L113 -> 0.051818824 | M51: 0.0545 | N51: 0.0545 | O51: 0.0545 | P51: 0.0545 | Q51: 0.0545
D52: =Hist!D127 -> Advance payment to suppliers | E52: & COGS | J52: =ABS((L52/K52)-1) -> 0.50433835 | K52: =Hist!K127/Hist!K100 -> 0.15989016 | L52: =Hist!L127/Hist!L100 -> 0.2405289 | M52: 0.21 | N52: 0.21 | O52: 0.21 | P52: 0.21 | Q52: 0.21
D53: =Hist!D128 -> Other receivables | E53: Ending Balance | J53: =ABS((L53/K53)-1) -> 2.3149101 | K53: =Hist!K128 -> 1708116 | L53: =Hist!L128 -> 5662251 | M53: 1170424 | N53: 1170424 | O53: 1170424 | P53: 1170424 | Q53: 1170424
D54: =Hist!D129 -> Total Prepayments | E54: % SG&A | J54: =ABS((L54/K54)-1) -> 0.52349763 | K54: =Hist!K129/Hist!K102 -> 0.019084255 | L54: =Hist!L129/Hist!L102 -> 0.029074817 | M54: 0.016787004 | N54: 0.016787004 | O54: 0.016787004 | P54: 0.016787004 | Q54: 0.016787004
D55: =Hist!D130 -> Inventories | E55: % COGS | J55: =ABS((L55/K55)-1) -> 0.1282797 | K55: =Hist!K130/Hist!K100 -> 0.27515219 | L55: =Hist!L130/Hist!L100 -> 0.31044863 | M55: 0.1909 | N55: 0.1909 | O55: 0.1909 | P55: 0.1909 | Q55: 0.1909
B59: =Hist!B134 -> Liability & Equity
C60: =Hist!C135 -> Equity
D61: =Hist!D136 -> Share capital | E61: Ending balance | J61: =Hist!J136 -> 396328 | K61: =Hist!K136 -> 396328 | L61: =Hist!L136 -> 396328 | M61: 396328 | N61: 396328 | O61: 396328 | P61: 396328 | Q61: 396328
D62: =Hist!D137 -> Share premium | E62: Ending balance | J62: =Hist!J137 -> 32262 | K62: =Hist!K137 -> 32262 | L62: =Hist!L137 -> 32262 | M62: 32262 | N62: 32262 | O62: 32262 | P62: 32262 | Q62: 32262
D63: =Hist!D138 -> Share based payment reserve | E63: Ending balance | J63: =Hist!J138 -> 113811 | K63: =Hist!K138 -> 113456 | L63: =Hist!L138 -> 90127 | M63: 90127 | N63: 90127 | O63: 90127 | P63: 90127 | Q63: 90127
C66: =Hist!C141 -> Non - Current Liabilities
D67: =Hist!D142 -> Total Loans and Borrowings | E67: Ending balance | J67: =Hist!J142 -> 40211686 | K67: =Hist!K142 -> 76864802 | L67: =Hist!L142 -> 155300068
D68: =Hist!D143 -> Employee benefits | E68: Ending balance | J68: =Hist!J143 -> 4471021 | K68: =Hist!K143 -> 4038600 | L68: =Hist!L143 -> 4359648 | M68: 4307927 | N68: 4307927 | O68: 4307927 | P68: 4307927 | Q68: 4307927
D69: =Hist!D144 -> Lease liabilities | E69: Ending balance | J69: =Hist!J144 -> 799354 | K69: =Hist!K144 -> 467956 | L69: =Hist!L144 -> 181606 | M69: 181606 | N69: 181606 | O69: 181606 | P69: 181606 | Q69: 181606
C71: =Hist!C147 -> Current Liabilities
D72: =Hist!D148 -> Contract liabilities | E72: % of Revs | J72: =ABS(L72/K72-1) -> 0.15675553 | K72: =Hist!K148/Hist!K$99 -> 0.043920905 | L72: =Hist!L148/Hist!L$99 -> 0.03703606 | M72: 0.0178 | N72: 0.0178 | O72: 0.0178 | P72: 0.0178 | Q72: 0.0178
D73: =Hist!D149 -> Refund liabilities | E73: % of Revs | J73: =ABS(L73/K73-1) -> 0.12014755 | K73: =Hist!K149/Hist!K$99 -> 0.00022443999 | L73: =Hist!L149/Hist!L$99 -> 0.0002514059 | M73: 0.0013 | N73: 0.0013 | O73: 0.0013 | P73: 0.0013 | Q73: 0.0013
D74: =Hist!D150 -> Current tax liabilities | E74: % of EBT | J74: =ABS(L74/K74-1) -> 0.1936345 | K74: =Hist!K150/Hist!K$110 -> 0.4570743 | L74: =Hist!L150/Hist!L$110 -> 0.36856895 | M74: 0.4213 | N74: 0.4213 | O74: 0.4213 | P74: 0.4213 | Q74: 0.4213
D75: =Hist!D151 -> Provisions | E75: % of EBT | J75: =ABS(L75/K75-1) -> 0.66952632 | K75: =Hist!K151/Hist!K$110 -> 0.043660332 | L75: =Hist!L151/Hist!L$110 -> 0.014428591 | M75: 0.0211 | N75: 0.0211 | O75: 0.0211 | P75: 0.0211 | Q75: 0.0211
D76: =Hist!D152 -> Trade Payables | E76: % of COGS | J76: =ABS(L76/K76-1) -> 0.12746849 | K76: =Hist!K152/Hist!K100 -> 0.54883277 | L76: =Hist!L152/Hist!L100 -> 0.47887389 | M76: 0.3112 | N76: 0.3112 | O76: 0.3112 | P76: 0.3112 | Q76: 0.3112
D77: =Hist!D153 -> Other payables and accruals | E77: % of SG&A | J77: =ABS(L77/K77-1) -> 0.20058826 | K77: =Hist!K153/Hist!K102 -> 0.3728402 | L77: =Hist!L153/Hist!L102 -> 0.29805283 | M77: 0.3277 | N77: 0.3277 | O77: 0.3277 | P77: 0.3277 | Q77: 0.3277
D78: =Hist!D154 -> Dividend payable | E78: % of EAT | J78: =ABS(L78/K78-1) -> 0.11989801 | K78: =Hist!K154/Hist!K113 -> 0.23482301 | L78: =Hist!L154/Hist!L113 -> 0.20666819 | M78: 0.1402 | N78: 0.1402 | O78: 0.1402 | P78: 0.1402 | Q78: 0.1402
B81: Financing Assumptions
C82: All the assumptions necessary for building the debt schedules, revolver (bank overdraft) section and interest icome computations
C83: Long Term Debt Assumptions
C85: S/N | D85: =Hist!D361 -> Name of the Loans | E85: =Hist!E361 -> Issue Year | F85: =Hist!F361 -> Due Year | G85: =Hist!G361 -> Category | H85: =Hist!H361 -> Benchmark | I85: =Hist!I361 -> Rate | J85: =Hist!J361 -> Amount(2019)
C86: 1 | D86: =Hist!D362 -> Loan from related party | F86: =Hist!F362 -> 2027 | G86: =Hist!G362 -> Floating | H86: =Hist!H362 -> LIBOR | I86: =Hist!I362 -> 0.11 | J86: =Hist!J362 -> 58570728
C87: 2 | D87: =Hist!D363 -> Loan from related party | F87: =Hist!F363 -> 2027 | G87: =Hist!G363 -> Floating | H87: =Hist!H363 -> LIBOR | I87: =Hist!I363 -> 0.07 | J87: =Hist!J363 -> 51018981
C88: 3 | D88: =Hist!D364 -> Loan from related party | F88: =Hist!F364 -> 2028 | G88: =Hist!G364 -> Floating | H88: =Hist!H364 -> LIBOR | I88: =Hist!I364 -> 0.04 | J88: =Hist!J364 -> 23754913
C89: 4 | D89: =Hist!D365 -> Loan from related party | F89: =Hist!F365 -> 2029 | G89: =Hist!G365 -> Floating | H89: =Hist!H365 -> SOFR | I89: =Hist!I365 -> 0.1 | J89: =Hist!J365 -> 13661934
C90: 5 | D90: =Hist!D366 -> Import Trade Obligations | F90: =Hist!F366 -> 2023 | G90: =Hist!G366 -> Floating | H90: =Hist!H366 -> SOFR | I90: =Hist!I366 -> 0.06 | J90: =Hist!J366 -> 8293512
C91: 6 | D91: New Debt 1 | E91: 2023 | F91: 2025 | G91: Fixed | I91: 0.12 | J91: 5000000
C92: 7 | D92: New Debt 2 | E92: 2024 | F92: 2026 | G92: Floating | H92: Monetary Rate | I92: 0.07 | J92: 1000000
C93: 8 | D93: New Debt 3 | E93: 2025 | F93: 2028 | G93: Floating | H93: NIBOR | I93: 0.08 | J93: 6000000
C94: 9 | D94: New Debt 4 | E94: 2026 | F94: 2030 | G94: Floating | I94: 0.09 | J94: 3000000
C95: 10 | D95: New Debt 5 | E95: 2027 | F95: 2032 | G95: Fixed | I95: 0.1 | J95: 2000000
C98: Interest Rates Assumptions
D99: Monetary Rate | E99: % | M99: 0.05 | N99: 0.06 | O99: 0.06 | P99: 0.08 | Q99: 0.09
D100: LIBOR | E100: % | M100: 0.08 | N100: 0.07 | O100: 0.07 | P100: 0.05 | Q100: 0.04
D101: NIBOR | E101: % | M101: 0.1 | N101: 0.09 | O101: 0.09 | P101: 0.07 | Q101: 0.06
D102: Interest rate on Cash | E102: % | M102: 0.04 | N102: 0.04 | O102: 0.04 | P102: 0.04 | Q102: 0.04
D103: Interest Rate on Revolver | E103: % | M103: 0.08 | N103: 0.08 | O103: 0.08 | P103: 0.08 | Q103: 0.08

Sheet Scn
B2: =company -> Nestle Nigeria
C3: Scenario Inputs
D4: =Live_Scenario -> Live Scenario: Base Case | H4: Start Date | J4: =I5+1 -> 43831 | K4: =J5+1 -> 44197 | L4: =K5+1 -> 44562 | M4: =L5+1 -> 44927 | N4: =M5+1 -> 45292 | O4: =N5+1 -> 45658 | P4: =O5+1 -> 46023 | Q4: =P5+1 -> 46388
D5: ="Audit Check: "& Audit_check -> Audit Check: OK | H5: End Date | I5: =EOMONTH(J5,-months_in_period) -> 43830 | J5: =EOMONTH(K5,-months_in_period) -> 44196 | K5: =EOMONTH(L5,-months_in_period) -> 44561 | L5: =Date_last_historical -> 44926 | M5: =EOMONTH(L5,months_in_period) -> 45291 | N5: =EOMONTH(M5,months_in_period) -> 45657 | O5: =EOMONTH(N5,months_in_period) -> 46022 | P5: =EOMONTH(O5,months_in_period) -> 46387 | Q5: =EOMONTH(P5,months_in_period) -> 46752
D6: Actual | J6: =(J5<=Date_last_historical)*1 -> 1 | K6: =(K5<=Date_last_historical)*1 -> 1 | L6: =(L5<=Date_last_historical)*1 -> 1 | M6: =(M5<=Date_last_historical)*1 -> 0 | N6: =(N5<=Date_last_historical)*1 -> 0 | O6: =(O5<=Date_last_historical)*1 -> 0 | P6: =(P5<=Date_last_historical)*1 -> 0 | Q6: =(Q5<=Date_last_historical)*1 -> 0
D7: Forecast | J7: =(J5>=Date_last_historical)*1 -> 0 | K7: =(K5>=Date_last_historical)*1 -> 0 | L7: =(L5>Date_last_historical)*1 -> 0 | M7: =(M5>=Date_last_historical)*1 -> 1 | N7: =(N5>=Date_last_historical)*1 -> 1 | O7: =(O5>=Date_last_historical)*1 -> 1 | P7: =(P5>=Date_last_historical)*1 -> 1 | Q7: =(Q5>=Date_last_historical)*1 -> 1
D8: Description | E8: Units | F8: Inputs | I8: Row Totals | J8: Hist | K8: Hist | L8: Hist | M8: Proj | N8: Proj | O8: Proj | P8: Proj | Q8: Proj
B10: Scenario & Sensitiviy Analysis Tool
C11: This section enables us to build multiple scenarios for highly uncertain and critical assumptions to assess their impacts on the model outputs
C13: Scenario Picker
D15: =_xlfn.CONCAT("Live Scenario: ",INDEX(l_scenarios,S_Scenarios,1)) -> Live Scenario: Base Case | F15: 1
D16: Base Case | R16: ctrl+shift+7 to turn items into a list
D17: Best Case
D18: Worst Case
C22: Revenue Scenarios (YoY Growth Rate)
D23: =_xlfn.CONCAT("Used in the model: ",INDEX(l_scenarios,S_Scenarios,1)) -> Used in the model: Base Case | M23: {=INDEX(M24:M26,S_Scenarios,1)} -> 0.22 | N23: {=INDEX(N24:N26,S_Scenarios,1)} -> 0.22 | O23: {=INDEX(O24:O26,S_Scenarios,1)} -> 0.22 | P23: {=INDEX(P24:P26,S_Scenarios,1)} -> 0.22 | Q23: {=INDEX(Q24:Q26,S_Scenarios,1)} -> 0.22
D24: =$D$16 -> Base Case | E24: % | M24: 0.22 | N24: 0.22 | O24: 0.22 | P24: 0.22 | Q24: 0.22
D25: =$D$17 -> Best Case | E25: % | M25: 0.27 | N25: 0.27 | O25: 0.27 | P25: 0.27 | Q25: 0.27
D26: =$D$18 -> Worst Case | E26: % | K26: Based on the 2019 model, which may be a better representation of the growth prospect of the company before the naira devaluation | M26: 0.1 | N26: 0.1 | O26: 0.1 | P26: 0.1 | Q26: 0.1
C28: COGS Scenarios (% of Revenue)
D29: =_xlfn.CONCAT("Used in the model: ",INDEX(l_scenarios,S_Scenarios,1)) -> Used in the model: Base Case | M29: {=INDEX(M30:M32,S_Scenarios,1)} -> 0.6571 | N29: {=INDEX(N30:N32,S_Scenarios,1)} -> 0.6571 | O29: {=INDEX(O30:O32,S_Scenarios,1)} -> 0.6571 | P29: {=INDEX(P30:P32,S_Scenarios,1)} -> 0.6571 | Q29: {=INDEX(Q30:Q32,S_Scenarios,1)} -> 0.6571
D30: =$D$16 -> Base Case | E30: % | M30: 0.6571 | N30: 0.6571 | O30: 0.6571 | P30: 0.6571 | Q30: 0.6571
D31: =$D$17 -> Best Case | E31: % | M31: 0.6044 | N31: 0.6044 | O31: 0.6044 | P31: 0.6044 | Q31: 0.6044
D32: =$D$18 -> Worst Case | E32: % | M32: 0.69 | N32: 0.69 | O32: 0.69 | P32: 0.69 | Q32: 0.69
C34: SG&A Scenarios (% of Revenue)
D35: =_xlfn.CONCAT("Used in the model: ",INDEX(l_scenarios,S_Scenarios,1)) -> Used in the model: Base Case | M35: {=INDEX(M36:M38,S_Scenarios,1)} -> 0.14848819 | N35: {=INDEX(N36:N38,S_Scenarios,1)} -> 0.14848819 | O35: {=INDEX(O36:O38,S_Scenarios,1)} -> 0.14848819 | P35: {=INDEX(P36:P38,S_Scenarios,1)} -> 0.14848819 | Q35: {=INDEX(Q36:Q38,S_Scenarios,1)} -> 0.14848819
D36: =$D$16 -> Base Case | E36: % | M36: 0.14848819 | N36: 0.14848819 | O36: 0.14848819 | P36: 0.14848819 | Q36: 0.14848819
D37: =$D$17 -> Best Case | E37: % | M37: =M36-1% -> 0.13848819 | N37: =N36-1% -> 0.13848819 | O37: =O36-1% -> 0.13848819 | P37: =P36-1% -> 0.13848819 | Q37: =Q36-1% -> 0.13848819
D38: =$D$18 -> Worst Case | E38: % | M38: =M36+1% -> 0.15848819 | N38: =N36+1% -> 0.15848819 | O38: =O36+1% -> 0.15848819 | P38: =P36+1% -> 0.15848819 | Q38: =Q36+1% -> 0.15848819
C40: Maintainable CAPEX Scenario
D41: =_xlfn.CONCAT("Used in the model: ",INDEX(l_scenarios,S_Scenarios,1)) -> Used in the model: Base Case | M41: {=INDEX(M42:M44,S_Scenarios,1)} -> 1.2 | N41: {=INDEX(N42:N44,S_Scenarios,1)} -> 1.2 | O41: {=INDEX(O42:O44,S_Scenarios,1)} -> 1.2 | P41: {=INDEX(P42:P44,S_Scenarios,1)} -> 1.2 | Q41: {=INDEX(Q42:Q44,S_Scenarios,1)} -> 1.2
D42: =$D$16 -> Base Case | E42: % | M42: 1.2 | N42: 1.2 | O42: 1.2 | P42: 1.2 | Q42: 1.2
D43: =$D$17 -> Best Case | E43: % | M43: 1.15 | N43: 1.15 | O43: 1.15 | P43: 1.15 | Q43: 1.15
D44: =$D$18 -> Worst Case | E44: % | M44: 1.25 | N44: 1.25 | O44: 1.25 | P44: 1.25 | Q44: 1.25

Sheet Calc
B2: =company -> Nestle Nigeria
C3: Calculations
D4: =Live_Scenario -> Live Scenario: Base Case | H4: Start Date | J4: =I5+1 -> 43831 | K4: =J5+1 -> 44197 | L4: =K5+1 -> 44562 | M4: =L5+1 -> 44927 | N4: =M5+1 -> 45292 | O4: =N5+1 -> 45658 | P4: =O5+1 -> 46023 | Q4: =P5+1 -> 46388
D5: ="Audit Check: "& Audit_check -> Audit Check: OK | H5: End Date | I5: =EOMONTH(J5,-months_in_period) -> 43830 | J5: =EOMONTH(K5,-months_in_period) -> 44196 | K5: =EOMONTH(L5,-months_in_period) -> 44561 | L5: =Date_last_historical -> 44926 | M5: =EOMONTH(L5,months_in_period) -> 45291 | N5: =EOMONTH(M5,months_in_period) -> 45657 | O5: =EOMONTH(N5,months_in_period) -> 46022 | P5: =EOMONTH(O5,months_in_period) -> 46387 | Q5: =EOMONTH(P5,months_in_period) -> 46752
D6: Actual | J6: =(J5<=Date_last_historical)*1 -> 1 | K6: =(K5<Date_last_historical)*1 -> 1 | L6: =(L5<=Date_last_historical)*1 -> 1 | M6: =(M5<=Date_last_historical)*1 -> 0 | N6: =(N5<=Date_last_historical)*1 -> 0 | O6: =(O5<=Date_last_historical)*1 -> 0 | P6: =(P5<=Date_last_historical)*1 -> 0 | Q6: =(Q5<=Date_last_historical)*1 -> 0
D7: Forecast | J7: =(J5>=Date_last_historical)*1 -> 0 | K7: =(K5>=Date_last_historical)*1 -> 0 | L7: =(L5>Date_last_historical)*1 -> 0 | M7: =(M5>=Date_last_historical)*1 -> 1 | N7: =(N5>=Date_last_historical)*1 -> 1 | O7: =(O5>=Date_last_historical)*1 -> 1 | P7: =(P5>=Date_last_historical)*1 -> 1 | Q7: =(Q5>=Date_last_historical)*1 -> 1
D8: Description | E8: Units | F8: Inputs | I8: Row Totals | J8: Hist | K8: Hist | L8: Hist | M8: Proj | N8: Proj | O8: Proj | P8: Proj | Q8: Proj
B10: Profit or Loss Calculations
C11: Calculations for the profit or loss projections
C12: Revenue Computations
D13: =Inps!D22 -> Revenue | E13: =Inps!E22 -> yoy % growth from scn sheet | M13: =Inps!M22 -> 0.22 | N13: =Inps!N22 -> 0.22 | O13: =Inps!O22 -> 0.22 | P13: =Inps!P22 -> 0.22 | Q13: =Inps!Q22 -> 0.22
D14: Revenue Calculations | E14: =currency -> ₦ Th's | J14: =Hist!J99 -> 287084087 | K14: =Hist!K99 -> 351822329 | L14: =Hist!L99 -> 446819260 | M14: =L14*(1+M13) -> 5.451195e+08 | N14: =M14*(1+N13) -> 6.6504579e+08 | O14: =N14*(1+O13) -> 8.1135586e+08 | P14: =O14*(1+P13) -> 9.8985415e+08 | Q14: =P14*(1+Q13) -> 1.2076221e+09
C17: COGS & SG&A Computations
D18: Assumptions
D19: =Inps!D23 -> Cost of Sales | E19: =Inps!E23 -> % of Revenue | M19: =Inps!M23 -> 0.6571 | N19: =Inps!N23 -> 0.6571 | O19: =Inps!O23 -> 0.6571 | P19: =Inps!P23 -> 0.6571 | Q19: =Inps!Q23 -> 0.6571
D20: =Inps!D25 -> SG&A Expenses | E20: =Inps!E25 -> % of Revenue | M20: =Inps!M25 -> 0.14848819 | N20: =Inps!N25 -> 0.14848819 | O20: =Inps!O25 -> 0.14848819 | P20: =Inps!P25 -> 0.14848819 | Q20: =Inps!Q25 -> 0.14848819
D22: Computations
D23: =D19 -> Cost of Sales | E23: =currency -> ₦ Th's | M23: =M$14*M19 -> 3.5819802e+08 | N23: =N$14*N19 -> 4.3700159e+08 | O23: =O$14*O19 -> 5.3314194e+08 | P23: =P$14*P19 -> 6.5043316e+08 | Q23: =Q$14*Q19 -> 7.9352846e+08
D24: =D20 -> SG&A Expenses | E24: =currency -> ₦ Th's | M24: =M$14*M20 -> 80943806 | N24: =N$14*N20 -> 98751443 | O24: =O$14*O20 -> 1.2047676e+08 | P24: =P$14*P20 -> 1.4698165e+08 | Q24: =Q$14*Q20 -> 1.7931761e+08
C27: Other Profit or Loss Computations
D28: Assumptions
D29: =Inps!D28 -> Impairement | E29: =Inps!E28 -> Fixed amount | M29: =Inps!M28 -> 29043 | N29: =Inps!N28 -> 29043 | O29: =Inps!O28 -> 29043 | P29: =Inps!P28 -> 29043 | Q29: =Inps!Q28 -> 29043
D30: =Inps!D32 -> Net Foreign Exchange Loss | E30: =Inps!E32 -> Fixed amount | M30: =Inps!M32 -> 7851981 | N30: =Inps!N32 -> 7851981 | O30: =Inps!O32 -> 7851981 | P30: =Inps!P32 -> 7851981 | Q30: =Inps!Q32 -> 7851981
D32: Computations
D33: =D29 -> Impairement | E33: =currency -> ₦ Th's | M33: =M29 -> 29043 | N33: =N29 -> 29043 | O33: =O29 -> 29043 | P33: =P29 -> 29043 | Q33: =Q29 -> 29043
D34: =D30 -> Net Foreign Exchange Loss | E34: =currency -> ₦ Th's | M34: =M30 -> 7851981 | N34: =N30 -> 7851981 | O34: =O30 -> 7851981 | P34: =P30 -> 7851981 | Q34: =Q30 -> 7851981
C37: Income Tax Schedule
D38: Assumptions
D39: Statutory Tax Rate | E39: =Inps!E34 -> Statutory Tax Rate | M39: =Inps!M34 -> 0.32 | N39: =Inps!N34 -> 0.32 | O39: =Inps!O34 -> 0.32 | P39: =Inps!P34 -> 0.32 | Q39: =Inps!Q34 -> 0.32
D40: =Inps!D35 -> Reduction in EBT for Timing difference | E40: =Inps!E35 -> Implied reduction on EBT based on govt financials | M40: =Inps!M35 -> 3300000 | N40: =Inps!N35 -> 3300000 | O40: =Inps!O35 -> 3300000 | P40: =Inps!P35 -> 3300000 | Q40: =Inps!Q35 -> 3300000
D42: Accounting EBT (from P/L) | M42: =IS!M21 -> 65837999 | N42: =IS!N21 -> 89266299 | O42: =IS!O21 -> 1.1784701e+08 | P42: =IS!P21 -> 1.5594664e+08 | Q42: =IS!Q21 -> 2.0779001e+08
D43: Less: Reduction in EBT for timing difference | M43: =M40 -> 3300000 | N43: =N40 -> 3300000 | O43: =O40 -> 3300000 | P43: =P40 -> 3300000 | Q43: =Q40 -> 3300000
D44: Government Tax | M44: =M42-M43 -> 62537999 | N44: =N42-N43 -> 85966299 | O44: =O42-O43 -> 1.1454701e+08 | P44: =P42-P43 -> 1.5264664e+08 | Q44: =Q42-Q43 -> 2.0449001e+08
D46: Tax computations
D47: Current tax (cash Taxes) | M47: =M44*M39 -> 20012160 | N47: =N44*N39 -> 27509216 | O47: =O44*O39 -> 36655044 | P47: =P44*P39 -> 48846925 | Q47: =Q44*Q39 -> 65436802 | R47: What we are actually paying to the govt
D48: Deferred Tax | M48: =M49-M47 -> 1056000 | N48: =N49-N47 -> 1056000 | O48: =O49-O47 -> 1056000 | P48: =P49-P47 -> 1056000 | Q48: =Q49-Q47 -> 1056000
D49: Total Income Tax | M49: =M42*M39 -> 21068160 | N49: =N42*N39 -> 28565216 | O49: =O42*O39 -> 37711044 | P49: =P42*P39 -> 49902925 | Q49: =Q42*Q39 -> 66492802
B52: Balance Sheet Computations
C53: Calculations and Schedulesfor the balance sheet projections
B54: Operating Working Capital Computations
C55: Linked OWC Inputs
D56: Assets
D57: =Inps!D49 -> Trade Receivables | E57: =Inps!E49 -> % of revenues | M57: =Inps!M49 -> 0.0694 | N57: =Inps!N49 -> 0.0694 | O57: =Inps!O49 -> 0.0694 | P57: =Inps!P49 -> 0.0694 | Q57: =Inps!Q49 -> 0.0694
D58: =Inps!D50 -> Staff Loans | E58: =Inps!E50 -> Ending Balance | M58: =Inps!M50 -> 2866469 | N58: =Inps!N50 -> 2866469 | O58: =Inps!O50 -> 2866469 | P58: =Inps!P50 -> 2866469 | Q58: =Inps!Q50 -> 2866469
D59: =Inps!D51 -> Deposit with Company registrars for dividend | E59: =Inps!E51 -> % EAT | M59: =Inps!M51 -> 0.0545 | N59: =Inps!N51 -> 0.0545 | O59: =Inps!O51 -> 0.0545 | P59: =Inps!P51 -> 0.0545 | Q59: =Inps!Q51 -> 0.0545
D60: =Inps!D52 -> Advance payment to suppliers | E60: =Inps!E52 -> & COGS | M60: =Inps!M52 -> 0.21 | N60: =Inps!N52 -> 0.21 | O60: =Inps!O52 -> 0.21 | P60: =Inps!P52 -> 0.21 | Q60: =Inps!Q52 -> 0.21
D61: =Inps!D53 -> Other receivables | E61: =Inps!E53 -> Ending Balance | M61: =Inps!M53 -> 1170424 | N61: =Inps!N53 -> 1170424 | O61: =Inps!O53 -> 1170424 | P61: =Inps!P53 -> 1170424 | Q61: =Inps!Q53 -> 1170424
D62: =Inps!D54 -> Total Prepayments | E62: =Inps!E54 -> % SG&A | M62: =Inps!M54 -> 0.016787004 | N62: =Inps!N54 -> 0.016787004 | O62: =Inps!O54 -> 0.016787004 | P62: =Inps!P54 -> 0.016787004 | Q62: =Inps!Q54 -> 0.016787004
D63: =Inps!D55 -> Inventories | E63: =Inps!E55 -> % COGS | M63: =Inps!M55 -> 0.1909 | N63: =Inps!N55 -> 0.1909 | O63: =Inps!O55 -> 0.1909 | P63: =Inps!P55 -> 0.1909 | Q63: =Inps!Q55 -> 0.1909
D64: Liabilities
D65: =Inps!D68 -> Employee benefits | E65: =Inps!E68 -> Ending balance | M65: =Inps!M68 -> 4307927 | N65: =Inps!N68 -> 4307927 | O65: =Inps!O68 -> 4307927 | P65: =Inps!P68 -> 4307927 | Q65: =Inps!Q68 -> 4307927
D66: =Inps!D72 -> Contract liabilities | E66: =Inps!E72 -> % of Revs | M66: =Inps!M72 -> 0.0178 | N66: =Inps!N72 -> 0.0178 | O66: =Inps!O72 -> 0.0178 | P66: =Inps!P72 -> 0.0178 | Q66: =Inps!Q72 -> 0.0178
D67: =Inps!D73 -> Refund liabilities | E67: =Inps!E73 -> % of Revs | M67: =Inps!M73 -> 0.0013 | N67: =Inps!N73 -> 0.0013 | O67: =Inps!O73 -> 0.0013 | P67: =Inps!P73 -> 0.0013 | Q67: =Inps!Q73 -> 0.0013
D68: =Inps!D74 -> Current tax liabilities | E68: =Inps!E74 -> % of EBT | M68: =Inps!M74 -> 0.4213 | N68: =Inps!N74 -> 0.4213 | O68: =Inps!O74 -> 0.4213 | P68: =Inps!P74 -> 0.4213 | Q68: =Inps!Q74 -> 0.4213
D69: =Inps!D75 -> Provisions | E69: =Inps!E75 -> % of EBT | M69: =Inps!M75 -> 0.0211 | N69: =Inps!N75 -> 0.0211 | O69: =Inps!O75 -> 0.0211 | P69: =Inps!P75 -> 0.0211 | Q69: =Inps!Q75 -> 0.0211
D70: =Inps!D76 -> Trade Payables | E70: =Inps!E76 -> % of COGS | M70: =Inps!M76 -> 0.3112 | N70: =Inps!N76 -> 0.3112 | O70: =Inps!O76 -> 0.3112 | P70: =Inps!P76 -> 0.3112 | Q70: =Inps!Q76 -> 0.3112
D71: =Inps!D77 -> Other payables and accruals | E71: =Inps!E77 -> % of SG&A | M71: =Inps!M77 -> 0.3277 | N71: =Inps!N77 -> 0.3277 | O71: =Inps!O77 -> 0.3277 | P71: =Inps!P77 -> 0.3277 | Q71: =Inps!Q77 -> 0.3277
D72: =Inps!D78 -> Dividend payable | E72: =Inps!E78 -> % of EAT | M72: =Inps!M78 -> 0.1402 | N72: =Inps!N78 -> 0.1402 | O72: =Inps!O78 -> 0.1402 | P72: =Inps!P78 -> 0.1402 | Q72: =Inps!Q78 -> 0.1402
C75: Linked P/L Ittems
C76: Income Statement items to be used for OWC computations
D77: =IS!D10 -> Revenue | E77: =IS!E10 -> 0 | M77: =IS!M10 -> 5.451195e+08 | N77: =IS!N10 -> 6.6504579e+08 | O77: =IS!O10 -> 8.1135586e+08 | P77: =IS!P10 -> 9.8985415e+08 | Q77: =IS!Q10 -> 1.2076221e+09
D78: =IS!D11 -> Cost of Sales | E78: =IS!E11 -> 0 | M78: =IS!M11 -> 3.5819802e+08 | N78: =IS!N11 -> 4.3700159e+08 | O78: =IS!O11 -> 5.3314194e+08 | P78: =IS!P11 -> 6.5043316e+08 | Q78: =IS!Q11 -> 7.9352846e+08
D79: =IS!D13 -> SG&A Expenses | E79: =IS!E13 -> 0 | M79: =IS!M13 -> 80943806 | N79: =IS!N13 -> 98751443 | O79: =IS!O13 -> 1.2047676e+08 | P79: =IS!P13 -> 1.4698165e+08 | Q79: =IS!Q13 -> 1.7931761e+08
D80: =IS!D21 -> EBT | E80: =IS!E21 -> 0 | M80: =IS!M21 -> 65837999 | N80: =IS!N21 -> 89266299 | O80: =IS!O21 -> 1.1784701e+08 | P80: =IS!P21 -> 1.5594664e+08 | Q80: =IS!Q21 -> 2.0779001e+08
D81: =IS!D24 -> Net Profit | E81: =IS!E24 -> 0 | M81: =IS!M24 -> 44769839 | N81: =IS!N24 -> 60701083 | O81: =IS!O24 -> 80135969 | P81: =IS!P24 -> 1.0604371e+08 | Q81: =IS!Q24 -> 1.412972e+08
C84: Operating Working Capital Schedule
D85: =BS!D16 -> Trade Receivables | E85: % of revenues | L85: =BS!L16 -> 5493686 | M85: =M57*M77 -> 37831293 | N85: =N57*N77 -> 46154178 | O85: =O57*O77 -> 56308097 | P85: =P57*P77 -> 68695878 | Q85: =Q57*Q77 -> 83808971
D86: =BS!D17 -> Staff Loans | E86: Ending Balance | L86: =BS!L17 -> 2988632 | M86: =M58 -> 2866469 | N86: =N58 -> 2866469 | O86: =O58 -> 2866469 | P86: =P58 -> 2866469 | Q86: =Q58 -> 2866469
D87: =BS!D18 -> Deposit with Company registrars for dividend | E87: % EAT | L87: =BS!L18 -> 2537334 | M87: =M59*M81 -> 2439956.2 | N87: =N59*N81 -> 3308209 | O87: =O59*O81 -> 4367410.3 | P87: =P59*P81 -> 5779382.5 | Q87: =Q59*Q81 -> 7700697.7
D88: =BS!D19 -> Advance payment to suppliers | E88: & COGS | L88: =BS!L19 -> 68444339 | M88: =M60*M78 -> 75221585 | N88: =N60*N78 -> 91770333 | O88: =O60*O78 -> 1.1195981e+08 | P88: =P60*P78 -> 1.3659096e+08 | Q88: =Q60*Q78 -> 1.6664098e+08
D89: =BS!D20 -> Other receivables | E89: Ending Balance | L89: =BS!L20 -> 5662251 | M89: =M61 -> 1170424 | N89: =N61 -> 1170424 | O89: =O61 -> 1170424 | P89: =P61 -> 1170424 | Q89: =Q61 -> 1170424
D90: =BS!D21 -> Total Prepayments | E90: % SG&A | L90: =BS!L21 -> 1929038 | M90: =M62*M79 -> 1358804 | N90: =N62*N79 -> 1657740.9 | O90: =O62*O79 -> 2022443.9 | P90: =P62*P79 -> 2467381.6 | Q90: =Q62*Q79 -> 3010205.5
D91: =BS!D22 -> Inventories | E91: % COGS | L91: =BS!L22 -> 88340532 | M91: =M63*M78 -> 68380002 | N91: =N63*N78 -> 83423603 | O91: =O63*O78 -> 1.017768e+08 | P91: =P63*P78 -> 1.2416769e+08 | Q91: =Q63*Q78 -> 1.5148458e+08
D92: Total Assets | L92: =SUM(L85:L91) -> 175395812 | M92: =SUM(M85:M91) -> 1.8926853e+08 | N92: =SUM(N85:N91) -> 2.3035096e+08 | O92: =SUM(O85:O91) -> 2.8047145e+08 | P92: =SUM(P85:P91) -> 3.4173819e+08 | Q92: =SUM(Q85:Q91) -> 4.1668233e+08
D93: =BS!D35 -> Employee benefits | L93: =BS!L35 -> 4359648 | M93: =M65 -> 4307927 | N93: =N65 -> 4307927 | O93: =O65 -> 4307927 | P93: =P65 -> 4307927 | Q93: =Q65 -> 4307927
D94: =BS!D36 -> Lease liabilities | L94: =BS!L36 -> 181606 | M94: =M141 -> 181606 | N94: =N141 -> 181606 | O94: =O141 -> 181606 | P94: =P141 -> 181606 | Q94: =Q141 -> 181606
D95: =BS!D37 -> Deferred tax liabilities | L95: =BS!L37 -> 14854152 | M95: =L95+IS!M23 -> 15910152 | N95: =M95+IS!N23 -> 16966152 | O95: =N95+IS!O23 -> 18022152 | P95: =O95+IS!P23 -> 19078152 | Q95: =P95+IS!Q23 -> 20134152
D96: =BS!D40 -> Contract liabilities | E96: % of Revs | L96: =BS!L40 -> 16548425 | M96: =M66*M77 -> 9703127.1 | N96: =N66*N77 -> 11837815 | O96: =O66*O77 -> 14442134 | P96: =P66*P77 -> 17619404 | Q96: =Q66*Q77 -> 21495673
D97: =BS!D41 -> Refund liabilities | E97: % of Revs | L97: =BS!L41 -> 112333 | M97: =M67*M77 -> 708655.35 | N97: =N67*N77 -> 864559.52 | O97: =O67*O77 -> 1054762.6 | P97: =P67*P77 -> 1286810.4 | Q97: =Q67*Q77 -> 1569908.7
D98: =BS!D42 -> Current tax liabilities | E98: % of EBT | L98: =BS!L42 -> 26208706 | M98: =M68*M80 -> 27737549 | N98: =N68*N80 -> 37607892 | O98: =O68*O80 -> 49648947 | P98: =P68*P80 -> 65700319 | Q98: =Q68*Q80 -> 87541930
D99: =BS!D43 -> Provisions | E99: % of EBT | L99: =BS!L43 -> 1026008 | M99: =M69*M80 -> 1389181.8 | N99: =N69*N80 -> 1883518.9 | O99: =O69*O80 -> 2486572 | P99: =P69*P80 -> 3290474.1 | Q99: =Q69*Q80 -> 4384369.2
D100: =BS!D44 -> Trade Payables | E100: % off COGS | L100: =BS!L44 -> 136267227 | M100: =M70*M78 -> 1.1147122e+08 | N100: =N70*N78 -> 1.3599489e+08 | O100: =O70*O78 -> 1.6591377e+08 | P100: =P70*P78 -> 2.024148e+08 | Q100: =Q70*Q78 -> 2.4694606e+08
D101: =BS!D45 -> Other payables and accruals | E101: % of SG&A | L101: =BS!L45 -> 19775025 | M101: =M71*M79 -> 26525285 | N101: =N71*N79 -> 32360848 | O101: =O71*O79 -> 39480235 | P101: =P71*P79 -> 48165886 | Q101: =Q71*Q79 -> 58762381
D102: Total Liability | L102: =SUM(L93:L101) -> 219333130 | M102: =SUM(M93:M101) -> 1.9793471e+08 | N102: =SUM(N93:N101) -> 2.4200521e+08 | O102: =SUM(O93:O101) -> 2.9553811e+08 | P102: =SUM(P93:P101) -> 3.6204538e+08 | Q102: =SUM(Q93:Q101) -> 4.45324e+08
D103: Total Assets - Total Liabilities | L103: =L92-L102 -> -43937318 | M103: =M92-M102 -> -8666174.5 | N103: =N92-N102 -> -11654255 | O103: =O92-O102 -> -15066660 | P103: =P92-P102 -> -20307189 | Q103: =Q92-Q102 -> -28641677
D104: Change in OWC | L104: =K103-L103 -> 43937318 | M104: =L103-M103 -> -35271144 | N104: =M103-N103 -> 2988080.9 | O104: =N103-O103 -> 3412404.4 | P104: =O103-P103 -> 5240529.3 | Q104: =P103-Q103 -> 8334487.8 | R104: The formula (previous-current) is like this because a reduction in assets increases cash, and also an increase in liabilities increases cash
R105: So like change in asset is previous year - current year, while change in liability is current - previous
C107: =BS!D12 -> PP&E
D108: Beginning Balance | M108: =L112 -> 121715789 | N108: =M112 -> 1.2401639e+08 | O108: =N112 -> 1.2636102e+08 | P108: =O112 -> 1.2875052e+08 | Q108: =P112 -> 1.3118577e+08
D109: Capex | M109: =Inps!M46*Calc!M110+Inps!M47 -> 13977841 | N109: =Inps!N46*Calc!N110+Inps!N47 -> 14242042 | O109: =Inps!O46*Calc!O110+Inps!O47 -> 14511299 | P109: =Inps!P46*Calc!P110+Inps!P47 -> 14785710 | Q109: =Inps!Q46*Calc!Q110+Inps!Q47 -> 15065373
D110: Depreciation | M110: =Inps!M27*L112 -> 11648201 | N110: =Inps!N27*M112 -> 11868368 | O110: =Inps!O27*N112 -> 12092749 | P110: =Inps!P27*O112 -> 12321425 | Q110: =Inps!Q27*P112 -> 12554478
D111: =Inps!D28 -> Impairement | M111: =Inps!M28 -> 29043 | N111: =Inps!N28 -> 29043 | O111: =Inps!O28 -> 29043 | P111: =Inps!P28 -> 29043 | Q111: =Inps!Q28 -> 29043
D112: Ending Balance | L112: =BS!L12 -> 121715789 | M112: =M108+M109-M110-M111 -> 1.2401639e+08 | N112: =N108+N109-N110-N111 -> 1.2636102e+08 | O112: =O108+O109-O110-O111 -> 1.2875052e+08 | P112: =P108+P109-P110-P111 -> 1.3118577e+08 | Q112: =Q108+Q109-Q110-Q111 -> 1.3366762e+08
C114: Equity
C115: =BS!D28 -> Share capital
D116: Beginning Balance | M116: =L118 -> 396328 | N116: =M118 -> 396328 | O116: =N118 -> 396328 | P116: =O118 -> 396328 | Q116: =P118 -> 396328
D117: Change | M117: =Inps!M61-Inps!L61 -> 0 | N117: =Inps!N61-Inps!M61 -> 0 | O117: =Inps!O61-Inps!N61 -> 0 | P117: =Inps!P61-Inps!O61 -> 0 | Q117: =Inps!Q61-Inps!P61 -> 0
D118: Ending Balance | L118: =BS!L28 -> 396328 | M118: =SUM(M116:M117) -> 396328 | N118: =SUM(N116:N117) -> 396328 | O118: =SUM(O116:O117) -> 396328 | P118: =SUM(P116:P117) -> 396328 | Q118: =SUM(Q116:Q117) -> 396328
C120: =BS!D29 -> Share premium
D121: Beginning Balance | M121: =L123 -> 32262 | N121: =M123 -> 32262 | O121: =N123 -> 32262 | P121: =O123 -> 32262 | Q121: =P123 -> 32262
...

Sheet IS
B2: =company -> Nestle Nigeria
C3: Income Statement
D4: =Live_Scenario -> Live Scenario: Base Case | H4: Start Date | J4: =I5+1 -> 43831 | K4: =J5+1 -> 44197 | L4: =K5+1 -> 44562 | M4: =L5+1 -> 44927 | N4: =M5+1 -> 45292 | O4: =N5+1 -> 45658 | P4: =O5+1 -> 46023 | Q4: =P5+1 -> 46388
D5: ="Audit Check: "& Audit_check -> Audit Check: OK | H5: End Date | I5: =EOMONTH(J5,-months_in_period) -> 43830 | J5: =EOMONTH(K5,-months_in_period) -> 44196 | K5: =EOMONTH(L5,-months_in_period) -> 44561 | L5: =Date_last_historical -> 44926 | M5: =EOMONTH(L5,months_in_period) -> 45291 | N5: =EOMONTH(M5,months_in_period) -> 45657 | O5: =EOMONTH(N5,months_in_period) -> 46022 | P5: =EOMONTH(O5,months_in_period) -> 46387 | Q5: =EOMONTH(P5,months_in_period) -> 46752
D6: Actual | J6: =(J5<=Date_last_historical)*1 -> 1 | K6: =(K5<=Date_last_historical)*1 -> 1 | L6: =(L5<=Date_last_historical)*1 -> 1 | M6: =(M5<=Date_last_historical)*1 -> 0 | N6: =(N5<=Date_last_historical)*1 -> 0 | O6: =(O5<=Date_last_historical)*1 -> 0 | P6: =(P5<=Date_last_historical)*1 -> 0 | Q6: =(Q5<=Date_last_historical)*1 -> 0
D7: Forecast | J7: =(J5>=Date_last_historical)*1 -> 0 | K7: =(K5>=Date_last_historical)*1 -> 0 | L7: =(L5>Date_last_historical)*1 -> 0 | M7: =(M5>=Date_last_historical)*1 -> 1 | N7: =(N5>=Date_last_historical)*1 -> 1 | O7: =(O5>=Date_last_historical)*1 -> 1 | P7: =(P5>=Date_last_historical)*1 -> 1 | Q7: =(Q5>=Date_last_historical)*1 -> 1
D8: Description | E8: Units | F8: Inputs | I8: Row Totals | J8: Hist | K8: Hist | L8: Hist | M8: Proj | N8: Proj | O8: Proj | P8: Proj | Q8: Proj
D10: =Hist!D99 -> Revenue | J10: =Hist!J99 -> 287084087 | K10: =Hist!K99 -> 351822329 | L10: =Hist!L99 -> 446819260 | M10: =Calc!M14 -> 5.451195e+08 | N10: =Calc!N14 -> 6.6504579e+08 | O10: =Calc!O14 -> 8.1135586e+08 | P10: =Calc!P14 -> 9.8985415e+08 | Q10: =Calc!Q14 -> 1.2076221e+09
D11: =Hist!D100 -> Cost of Sales | J11: =Hist!J100 -> 162807627 | K11: =Hist!K100 -> 214296403 | L11: =Hist!L100 -> 284557646 | M11: =Calc!M23 -> 3.5819802e+08 | N11: =Calc!N23 -> 4.3700159e+08 | O11: =Calc!O23 -> 5.3314194e+08 | P11: =Calc!P23 -> 6.5043316e+08 | Q11: =Calc!Q23 -> 7.9352846e+08
D12: =Hist!D101 -> Gross Profit | J12: =J10-J11 -> 124276460 | K12: =K10-K11 -> 137525926 | L12: =L10-L11 -> 162261614 | M12: =M10-M11 -> 1.8692148e+08 | N12: =N10-N11 -> 2.280442e+08 | O12: =O10-O11 -> 2.7821392e+08 | P12: =P10-P11 -> 3.3942099e+08 | Q12: =Q10-Q11 -> 4.140936e+08
D13: =Hist!D102 -> SG&A Expenses | J13: =Hist!J102 -> 52543061 | K13: =Hist!K102 -> 57316411 | L13: =Hist!L102 -> 66347382 | M13: =Calc!M24 -> 80943806 | N13: =Calc!N24 -> 98751443 | O13: =Calc!O24 -> 1.2047676e+08 | P13: =Calc!P24 -> 1.4698165e+08 | Q13: =Calc!Q24 -> 1.7931761e+08
D14: =Hist!D103 -> EBITDA | J14: =J12-J13 -> 71733399 | K14: =K12-K13 -> 80209515 | L14: =L12-L13 -> 95914232 | M14: =M12-M13 -> 1.0597767e+08 | N14: =N12-N13 -> 1.2929276e+08 | O14: =O12-O13 -> 1.5773716e+08 | P14: =P12-P13 -> 1.9243934e+08 | Q14: =Q12-Q13 -> 2.3477599e+08
D15: =Hist!D104 -> Depreciation | J15: =Hist!J104 -> 7314816 | K15: =Hist!K104 -> 7965131 | L15: =Hist!L104 -> 9018706 | M15: =Calc!M110 -> 11648201 | N15: =Calc!N110 -> 11868368 | O15: =Calc!O110 -> 12092749 | P15: =Calc!P110 -> 12321425 | Q15: =Calc!Q110 -> 12554478
D16: =Hist!D105 -> Impairement | J16: =Hist!J105 -> 0 | K16: =Hist!K105 -> 278438 | L16: =Hist!L105 -> 29043 | M16: =Calc!M33 -> 29043 | N16: =Calc!N33 -> 29043 | O16: =Calc!O33 -> 29043 | P16: =Calc!P33 -> 29043 | Q16: =Calc!Q33 -> 29043
D17: =Hist!D106 -> EBIT | J17: =J14-J15-J16 -> 64418583 | K17: =K14-K15-K16 -> 71965946 | L17: =L14-L15-L16 -> 86866483 | M17: =M14-M15-M16 -> 94300426 | N17: =N14-N15-N16 -> 1.1739535e+08 | O17: =O14-O15-O16 -> 1.4561537e+08 | P17: =P14-P15-P16 -> 1.8008887e+08 | Q17: =Q14-Q15-Q16 -> 2.2219247e+08
D18: =Hist!D107 -> Interest income | J18: =Hist!J107 -> 646546 | K18: =Hist!K107 -> 1987042 | L18: =Hist!L107 -> 4777113 | M18: =Calc!M391 -> 4717297.2 | N18: =Calc!N391 -> 3287130.7 | O18: =Calc!O391 -> 3927819.8 | P18: =Calc!P391 -> 4758814.3 | Q18: =Calc!Q391 -> 5944666.1
D19: =Hist!D108 -> Interest Expense | J19: =Hist!J108 -> 2698404 | K19: =Hist!K108 -> 7342611 | L19: =Hist!L108 -> 12682244 | M19: =Calc!M397 -> 25327743 | N19: =Calc!N397 -> 23564196 | O19: =Calc!O397 -> 23844196 | P19: =Calc!P397 -> 21049065 | Q19: =Calc!Q397 -> 12495151
D20: =Hist!D109 -> Net Foreign Exchange Loss | J20: =Hist!J109 -> 1728282 | K20: =Hist!K109 -> 4735034 | L20: =Hist!L109 -> 7851981 | M20: =Calc!M34 -> 7851981 | N20: =Calc!N34 -> 7851981 | O20: =Calc!O34 -> 7851981 | P20: =Calc!P34 -> 7851981 | Q20: =Calc!Q34 -> 7851981
D21: =Hist!D110 -> EBT | J21: =J17+J18-J19-J20 -> 60638443 | K21: =K17+K18-K19-K20 -> 61875343 | L21: =L17+L18-L19-L20 -> 71109371 | M21: =M17+M18-M19-M20 -> 65837999 | N21: =N17+N18-N19-N20 -> 89266299 | O21: =O17+O18-O19-O20 -> 1.1784701e+08 | P21: =P17+P18-P19-P20 -> 1.5594664e+08 | Q21: =Q17+Q18-Q19-Q20 -> 2.0779001e+08
D22: =Hist!D111 -> Current Tax Expense | J22: =Hist!J111 -> 21899010 | K22: =Hist!K111 -> 21234703 | L22: =Hist!L111 -> 19877447 | M22: =Calc!M47 -> 20012160 | N22: =Calc!N47 -> 27509216 | O22: =Calc!O47 -> 36655044 | P22: =Calc!P47 -> 48846925 | Q22: =Calc!Q47 -> 65436802
D23: =Hist!D112 -> Deferred Taxes | J23: =Hist!J112 -> -472592 | K23: =Hist!K112 -> 603362 | L23: =Hist!L112 -> 2266436 | M23: =Calc!M48 -> 1056000 | N23: =Calc!N48 -> 1056000 | O23: =Calc!O48 -> 1056000 | P23: =Calc!P48 -> 1056000 | Q23: =Calc!Q48 -> 1056000
D24: =Hist!D113 -> Net Profit | J24: =J21-J22-J23 -> 39212025 | K24: =K21-K22-K23 -> 40037278 | L24: =L21-L22-L23 -> 48965488 | M24: =M21-M22-M23 -> 44769839 | N24: =N21-N22-N23 -> 60701083 | O24: =O21-O22-O23 -> 80135969 | P24: =P21-P22-P23 -> 1.0604371e+08 | Q24: =Q21-Q22-Q23 -> 1.412972e+08

Sheet BS
B2: =company -> Nestle Nigeria
C3: Balance Sheet
D4: =Live_Scenario -> Live Scenario: Base Case | H4: Start Date | J4: =I5+1 -> 43831 | K4: =J5+1 -> 44197 | L4: =K5+1 -> 44562 | M4: =L5+1 -> 44927 | N4: =M5+1 -> 45292 | O4: =N5+1 -> 45658 | P4: =O5+1 -> 46023 | Q4: =P5+1 -> 46388
D5: ="Audit Check: "& Audit_check -> Audit Check: OK | H5: End Date | I5: =EOMONTH(J5,-months_in_period) -> 43830 | J5: =EOMONTH(K5,-months_in_period) -> 44196 | K5: =EOMONTH(L5,-months_in_period) -> 44561 | L5: =Date_last_historical -> 44926 | M5: =EOMONTH(L5,months_in_period) -> 45291 | N5: =EOMONTH(M5,months_in_period) -> 45657 | O5: =EOMONTH(N5,months_in_period) -> 46022 | P5: =EOMONTH(O5,months_in_period) -> 46387 | Q5: =EOMONTH(P5,months_in_period) -> 46752
D6: Actual | J6: =(J5<=Date_last_historical)*1 -> 1 | K6: =(K5<=Date_last_historical)*1 -> 1 | L6: =(L5<=Date_last_historical)*1 -> 1 | M6: =(M5<=Date_last_historical)*1 -> 0 | N6: =(N5<=Date_last_historical)*1 -> 0 | O6: =(O5<=Date_last_historical)*1 -> 0 | P6: =(P5<=Date_last_historical)*1 -> 0 | Q6: =(Q5<=Date_last_historical)*1 -> 0
D7: Forecast | J7: =(J5>=Date_last_historical)*1 -> 0 | K7: =(K5>=Date_last_historical)*1 -> 0 | L7: =(L5>Date_last_historical)*1 -> 0 | M7: =(M5>Date_last_historical)*1 -> 1 | N7: =(N5>Date_last_historical)*1 -> 1 | O7: =(O5>Date_last_historical)*1 -> 1 | P7: =(P5>Date_last_historical)*1 -> 1 | Q7: =(Q5>Date_last_historical)*1 -> 1
D8: Description | E8: Units | F8: Inputs | I8: Row Totals | J8: Hist | K8: Hist | L8: Hist | M8: Proj | N8: Proj | O8: Proj | P8: Proj | Q8: Proj
B10: =Hist!B118 -> Assets
C11: =Hist!C119 -> Non - Current Assets
D12: =Hist!D120 -> PP&E | J12: =Hist!J120 -> 92320364 | K12: =Hist!K120 -> 103812889 | L12: =Hist!L120 -> 121715789 | M12: =Calc!M112 -> 1.2401639e+08 | N12: =Calc!N112 -> 1.2636102e+08 | O12: =Calc!O112 -> 1.2875052e+08 | P12: =Calc!P112 -> 1.3118577e+08 | Q12: =Calc!Q112 -> 1.3366762e+08
D13: =Hist!D121 -> Total Non-Current Assets | J13: =SUM(J12) -> 92320364 | K13: =SUM(K12) -> 103812889 | L13: =SUM(L12) -> 121715789 | M13: =SUM(M12) -> 1.2401639e+08 | N13: =SUM(N12) -> 1.2636102e+08 | O13: =SUM(O12) -> 1.2875052e+08 | P13: =SUM(P12) -> 1.3118577e+08 | Q13: =SUM(Q12) -> 1.3366762e+08
C15: =Hist!C123 -> Current Assets
D16: =Hist!D124 -> Trade Receivables | J16: =Hist!J124 -> 10904423 | K16: =Hist!K124 -> 4206216 | L16: =Hist!L124 -> 5493686 | M16: =Calc!M85 -> 37831293 | N16: =Calc!N85 -> 46154178 | O16: =Calc!O85 -> 56308097 | P16: =Calc!P85 -> 68695878 | Q16: =Calc!Q85 -> 83808971
D17: =Hist!D125 -> Staff Loans | J17: =Hist!J125 -> 2734089 | K17: =Hist!K125 -> 2870047 | L17: =Hist!L125 -> 2988632 | M17: =Calc!M86 -> 2866469 | N17: =Calc!N86 -> 2866469 | O17: =Calc!O86 -> 2866469 | P17: =Calc!P86 -> 2866469 | Q17: =Calc!Q86 -> 2866469
D18: =Hist!D126 -> Deposit with Company registrars for dividend | J18: =Hist!J126 -> 2724553 | K18: =Hist!K126 -> 2801222 | L18: =Hist!L126 -> 2537334 | M18: =Calc!M87 -> 2439956.2 | N18: =Calc!N87 -> 3308209 | O18: =Calc!O87 -> 4367410.3 | P18: =Calc!P87 -> 5779382.5 | Q18: =Calc!Q87 -> 7700697.7
D19: =Hist!D127 -> Advance payment to suppliers | J19: =Hist!J127 -> 23625648 | K19: =Hist!K127 -> 34263887 | L19: =Hist!L127 -> 68444339 | M19: =Calc!M88 -> 75221585 | N19: =Calc!N88 -> 91770333 | O19: =Calc!O88 -> 1.1195981e+08 | P19: =Calc!P88 -> 1.3659096e+08 | Q19: =Calc!Q88 -> 1.6664098e+08
D20: =Hist!D128 -> Other receivables | J20: =Hist!J128 -> 1982017 | K20: =Hist!K128 -> 1708116 | L20: =Hist!L128 -> 5662251 | M20: =Calc!M89 -> 1170424 | N20: =Calc!N89 -> 1170424 | O20: =Calc!O89 -> 1170424 | P20: =Calc!P89 -> 1170424 | Q20: =Calc!Q89 -> 1170424
D21: =Hist!D129 -> Total Prepayments | J21: =Hist!J129 -> 968426 | K21: =Hist!K129 -> 1093841 | L21: =Hist!L129 -> 1929038 | M21: =Calc!M90 -> 1358804 | N21: =Calc!N90 -> 1657740.9 | O21: =Calc!O90 -> 2022443.9 | P21: =Calc!P90 -> 2467381.6 | Q21: =Calc!Q90 -> 3010205.5
D22: =Hist!D130 -> Inventories | J22: =Hist!J130 -> 52222267 | K22: =Hist!K130 -> 58964125 | L22: =Hist!L130 -> 88340532 | M22: =Calc!M91 -> 68380002 | N22: =Calc!N91 -> 83423603 | O22: =Calc!O91 -> 1.017768e+08 | P22: =Calc!P91 -> 1.2416769e+08 | Q22: =Calc!Q91 -> 1.5148458e+08
D23: =Hist!D131 -> Cash and short term-deposit | J23: =Hist!J131 -> 58703209 | K23: =Hist!K131 -> 100518159 | L23: =Hist!L131 -> 117932430 | M23: =CF!M50 -> 82178268 | N23: =CF!N50 -> 98195495 | O23: =CF!O50 -> 1.1897036e+08 | P23: =CF!P50 -> 1.4861665e+08 | Q23: =CF!Q50 -> 80081560
D24: =Hist!D132 -> Total Current Assets | J24: =SUM(J16:J23) -> 153864632 | K24: =SUM(K16:K23) -> 206425613 | L24: =SUM(L16:L23) -> 293328242 | M24: =SUM(M16:M23) -> 2.714468e+08 | N24: =SUM(N16:N23) -> 3.2854645e+08 | O24: =SUM(O16:O23) -> 3.994418e+08 | P24: =SUM(P16:P23) -> 4.9035484e+08 | Q24: =SUM(Q16:Q23) -> 4.9676389e+08
D25: =Hist!D133 -> Total Assets | J25: =J13+J24 -> 246184996 | K25: =K13+K24 -> 310238502 | L25: =L13+L24 -> 415044031 | M25: =M13+M24 -> 3.9546319e+08 | N25: =N13+N24 -> 4.5490747e+08 | O25: =O13+O24 -> 5.2819233e+08 | P25: =P13+P24 -> 6.2154061e+08 | Q25: =Q13+Q24 -> 6.304315e+08
B26: =Hist!B134 -> Liability & Equity
C27: =Hist!C135 -> Equity
D28: =Hist!D136 -> Share capital | J28: =Hist!J136 -> 396328 | K28: =Hist!K136 -> 396328 | L28: =Hist!L136 -> 396328 | M28: =Calc!M118 -> 396328 | N28: =Calc!N118 -> 396328 | O28: =Calc!O118 -> 396328 | P28: =Calc!P118 -> 396328 | Q28: =Calc!Q118 -> 396328
D29: =Hist!D137 -> Share premium | J29: =Hist!J137 -> 32262 | K29: =Hist!K137 -> 32262 | L29: =Hist!L137 -> 32262 | M29: =Calc!M123 -> 32262 | N29: =Calc!N123 -> 32262 | O29: =Calc!O123 -> 32262 | P29: =Calc!P123 -> 32262 | Q29: =Calc!Q123 -> 32262
D30: =Hist!D138 -> Share based payment reserve | J30: =Hist!J138 -> 113811 | K30: =Hist!K138 -> 113456 | L30: =Hist!L138 -> 90127 | M30: =Calc!M128 -> 90127 | N30: =Calc!N128 -> 90127 | O30: =Calc!O128 -> 90127 | P30: =Calc!P128 -> 90127 | Q30: =Calc!Q128 -> 90127
D31: =Hist!D139 -> Retained earnings | J31: =Hist!J139 -> 28754583 | K31: =Hist!K139 -> 20836160 | L31: =Hist!L139 -> 29772507 | M31: =Calc!M135 -> 38726475 | N31: =Calc!N135 -> 50866692 | O31: =Calc!O135 -> 66893885 | P31: =Calc!P135 -> 88102628 | Q31: =Calc!Q135 -> 1.1636207e+08
D32: =Hist!D140 -> Total Equity | J32: =SUM(J28:J31) -> 29296984 | K32: =SUM(K28:K31) -> 21378206 | L32: =SUM(L28:L31) -> 30291224 | M32: =SUM(M28:M31) -> 39245192 | N32: =SUM(N28:N31) -> 51385409 | O32: =SUM(O28:O31) -> 67412602 | P32: =SUM(P28:P31) -> 88621345 | Q32: =SUM(Q28:Q31) -> 1.1688079e+08
C33: =Hist!C141 -> Non - Current Liabilities
D34: =Hist!D142 -> Total Loans and Borrowings | J34: =Hist!J142 -> 40211686 | K34: =Hist!K142 -> 76864802 | L34: =Hist!L142 -> 155300068 | M34: =Calc!M175 -> 152006556 | N34: =Calc!N175 -> 153006556 | O34: =Calc!O175 -> 154006556 | P34: =Calc!P175 -> 156006556 | Q34: =Calc!Q175 -> 48416847
D35: =Hist!D143 -> Employee benefits | J35: =Hist!J143 -> 4471021 | K35: =Hist!K143 -> 4038600 | L35: =Hist!L143 -> 4359648 | M35: =Calc!M93 -> 4307927 | N35: =Calc!N93 -> 4307927 | O35: =Calc!O93 -> 4307927 | P35: =Calc!P93 -> 4307927 | Q35: =Calc!Q93 -> 4307927
D36: =Hist!D144 -> Lease liabilities | J36: =Hist!J144 -> 799354 | K36: =Hist!K144 -> 467956 | L36: =Hist!L144 -> 181606 | M36: =Calc!M141 -> 181606 | N36: =Calc!N141 -> 181606 | O36: =Calc!O141 -> 181606 | P36: =Calc!P141 -> 181606 | Q36: =Calc!Q141 -> 181606
D37: =Hist!D145 -> Deferred tax liabilities | J37: =Hist!J145 -> 11984354 | K37: =Hist!K145 -> 12587716 | L37: =Hist!L145 -> 14854152 | M37: =Calc!M95 -> 15910152 | N37: =Calc!N95 -> 16966152 | O37: =Calc!O95 -> 18022152 | P37: =Calc!P95 -> 19078152 | Q37: =Calc!Q95 -> 20134152
D38: =Hist!D146 -> Total Non - Current Liabilities | J38: =SUM(J34:J37) -> 57466415 | K38: =SUM(K34:K37) -> 93959074 | L38: =SUM(L34:L37) -> 174695474 | M38: =SUM(M34:M37) -> 172406241 | N38: =SUM(N34:N37) -> 174462241 | O38: =SUM(O34:O37) -> 176518241 | P38: =SUM(P34:P37) -> 179574241 | Q38: =SUM(Q34:Q37) -> 73040532
C39: =Hist!C147 -> Current Liabilities
D40: =Hist!D148 -> Contract liabilities | J40: =Hist!J148 -> 8647246 | K40: =Hist!K148 -> 15452355 | L40: =Hist!L148 -> 16548425 | M40: =Calc!M96 -> 9703127.1 | N40: =Calc!N96 -> 11837815 | O40: =Calc!O96 -> 14442134 | P40: =Calc!P96 -> 17619404 | Q40: =Calc!Q96 -> 21495673
D41: =Hist!D149 -> Refund liabilities | J41: =Hist!J149 -> 90805 | K41: =Hist!K149 -> 78963 | L41: =Hist!L149 -> 112333 | M41: =Calc!M97 -> 708655.35 | N41: =Calc!N97 -> 864559.52 | O41: =Calc!O97 -> 1054762.6 | P41: =Calc!P97 -> 1286810.4 | Q41: =Calc!Q97 -> 1569908.7
D42: =Hist!D150 -> Current tax liabilities | J42: =Hist!J150 -> 30476315 | K42: =Hist!K150 -> 28281629 | L42: =Hist!L150 -> 26208706 | M42: =Calc!M98 -> 27737549 | N42: =Calc!N98 -> 37607892 | O42: =Calc!O98 -> 49648947 | P42: =Calc!P98 -> 65700319 | Q42: =Calc!Q98 -> 87541930
D43: =Hist!D151 -> Provisions | J43: =Hist!J151 -> 3691991 | K43: =Hist!K151 -> 2701498 | L43: =Hist!L151 -> 1026008 | M43: =Calc!M99 -> 1389181.8 | N43: =Calc!N99 -> 1883518.9 | O43: =Calc!O99 -> 2486572 | P43: =Calc!P99 -> 3290474.1 | Q43: =Calc!Q99 -> 4384369.2
D44: =Hist!D152 -> Trade Payables | J44: =Hist!J152 -> 93299251 | K44: =Hist!K152 -> 117612889 | L44: =Hist!L152 -> 136267227 | M44: =Calc!M100 -> 1.1147122e+08 | N44: =Calc!N100 -> 1.3599489e+08 | O44: =Calc!O100 -> 1.6591377e+08 | P44: =Calc!P100 -> 2.024148e+08 | Q44: =Calc!Q100 -> 2.4694606e+08
D45: =Hist!D153 -> Other payables and accruals | J45: =Hist!J153 -> 14921545 | K45: =Hist!K153 -> 21369862 | L45: =Hist!L153 -> 19775025 | M45: =Calc!M101 -> 26525285 | N45: =Calc!N101 -> 32360848 | O45: =Calc!O101 -> 39480235 | P45: =Calc!P101 -> 48165886 | Q45: =Calc!Q101 -> 58762381
D46: =Hist!D154 -> Dividend payable | J46: =Hist!J154 -> 8291893 | K46: =Hist!K154 -> 9401674 | L46: =Hist!L154 -> 10119609 | M46: =Calc!M163 -> 6276731.5 | N46: =Calc!N163 -> 8510291.9 | O46: =Calc!O163 -> 11235063 | P46: =Calc!P163 -> 14867329 | Q46: =Calc!Q163 -> 19809868
D47: =Hist!D155 -> Bank Overdraft | J47: =Hist!J155 -> 2551 | K47: =Hist!K155 -> 2352 | L47: =Hist!L155 -> 0 | M47: =Calc!M425 -> 0 | N47: =Calc!N425 -> 0 | O47: =Calc!O425 -> 0 | P47: =Calc!P425 -> 0 | Q47: =Calc!Q425 -> 0
D48: =Hist!D156 -> Total Current Liabilities | J48: =SUM(J40:J47) -> 159421597 | K48: =SUM(K40:K47) -> 194901222 | L48: =SUM(L40:L47) -> 210057333 | M48: =SUM(M40:M47) -> 1.8381175e+08 | N48: =SUM(N40:N47) -> 2.2905982e+08 | O48: =SUM(O40:O47) -> 2.8426148e+08 | P48: =SUM(P40:P47) -> 3.5334502e+08 | Q48: =SUM(Q40:Q47) -> 4.4051019e+08
D49: =Hist!D157 -> Total Liabilities | J49: =J48+J38 -> 216888012 | K49: =K48+K38 -> 288860296 | L49: =L48+L38 -> 384752807 | M49: =M48+M38 -> 3.56218e+08 | N49: =N48+N38 -> 4.0352206e+08 | O49: =O48+O38 -> 4.6077972e+08 | P49: =P48+P38 -> 5.3291926e+08 | Q49: =Q48+Q38 -> 5.1355072e+08
D50: =Hist!D158 -> Total Equity & Liabilities | J50: =J49+J32 -> 246184996 | K50: =K49+K32 -> 310238502 | L50: =L49+L32 -> 415044031 | M50: =M49+M32 -> 3.9546319e+08 | N50: =N49+N32 -> 4.5490747e+08 | O50: =O49+O32 -> 5.2819233e+08 | P50: =P49+P32 -> 6.2154061e+08 | Q50: =Q49+Q32 -> 6.304315e+08
B52: Reconciliation Check | I52: =COUNTIF(J52:Q52, "<>0") -> 0 | J52: =J25-J50 -> 0 | K52: =K25-K50 -> 0 | L52: =L25-L50 -> 0 | M52: =M25-M50 -> 0 | N52: =N25-N50 -> 0 | O52: =O25-O50 -> 0 | P52: =P25-P50 -> 0 | Q52: =Q25-Q50 -> 0

Sheet CF
B2: =company -> Nestle Nigeria
C3: Cash Flow Statement
D4: =Live_Scenario -> Live Scenario: Base Case | H4: Start Date | J4: =I5+1 -> 43831 | K4: =J5+1 -> 44197 | L4: =K5+1 -> 44562 | M4: =L5+1 -> 44927 | N4: =M5+1 -> 45292 | O4: =N5+1 -> 45658 | P4: =O5+1 -> 46023 | Q4: =P5+1 -> 46388
D5: ="Audit Check: "& Audit_check -> Audit Check: OK | H5: End Date | I5: =EOMONTH(J5,-months_in_period) -> 43830 | J5: =EOMONTH(K5,-months_in_period) -> 44196 | K5: =EOMONTH(L5,-months_in_period) -> 44561 | L5: =Date_last_historical -> 44926 | M5: =EOMONTH(L5,months_in_period) -> 45291 | N5: =EOMONTH(M5,months_in_period) -> 45657 | O5: =EOMONTH(N5,months_in_period) -> 46022 | P5: =EOMONTH(O5,months_in_period) -> 46387 | Q5: =EOMONTH(P5,months_in_period) -> 46752
D6: Actual | J6: =(J5<=Date_last_historical)*1 -> 1 | K6: =(K5<=Date_last_historical)*1 -> 1 | L6: =(L5<=Date_last_historical)*1 -> 1 | M6: =(M5<=Date_last_historical)*1 -> 0 | N6: =(N5<=Date_last_historical)*1 -> 0 | O6: =(O5<=Date_last_historical)*1 -> 0 | P6: =(P5<=Date_last_historical)*1 -> 0 | Q6: =(Q5<=Date_last_historical)*1 -> 0
D7: Forecast | J7: =(J5>=Date_last_historical)*1 -> 0 | K7: =(K5>=Date_last_historical)*1 -> 0 | L7: =(L5>Date_last_historical)*1 -> 0 | M7: =(M5>=Date_last_historical)*1 -> 1 | N7: =(N5>=Date_last_historical)*1 -> 1 | O7: =(O5>=Date_last_historical)*1 -> 1 | P7: =(P5>=Date_last_historical)*1 -> 1 | Q7: =(Q5>=Date_last_historical)*1 -> 1
D8: Description | E8: Units | F8: Inputs | I8: Row Totals | J8: Hist | K8: Hist | L8: Hist | M8: Proj | N8: Proj | O8: Proj | P8: Proj | Q8: Proj
C10: Cash Flow from Operations
D11: =IS!D17 -> EBIT | M11: =IS!M17 -> 94300426 | N11: =IS!N17 -> 1.1739535e+08 | O11: =IS!O17 -> 1.4561537e+08 | P11: =IS!P17 -> 1.8008887e+08 | Q11: =IS!Q17 -> 2.2219247e+08
D12: Adjusting for non-cash expense
D13: =IS!D15 -> Depreciation | M13: =IS!M15 -> 11648201 | N13: =IS!N15 -> 11868368 | O13: =IS!O15 -> 12092749 | P13: =IS!P15 -> 12321425 | Q13: =IS!Q15 -> 12554478
D14: =IS!D16 -> Impairement | M14: =IS!M16 -> 29043 | N14: =IS!N16 -> 29043 | O14: =IS!O16 -> 29043 | P14: =IS!P16 -> 29043 | Q14: =IS!Q16 -> 29043
D15: EBITDA | M15: =M11+M13+M14 -> 1.0597767e+08 | N15: =N11+N13+N14 -> 1.2929276e+08 | O15: =O11+O13+O14 -> 1.5773716e+08 | P15: =P11+P13+P14 -> 1.9243934e+08 | Q15: =Q11+Q13+Q14 -> 2.3477599e+08
D16: =Calc!D104 -> Change in OWC | M16: =Calc!M104 -> -35271144 | N16: =Calc!N104 -> 2988080.9 | O16: =Calc!O104 -> 3412404.4 | P16: =Calc!P104 -> 5240529.3 | Q16: =Calc!Q104 -> 8334487.8
D17: Adjusting for non-cash tax expense
D18: =IS!D23 -> Deferred Taxes | M18: =-IS!M23 -> -1056000 | N18: =-IS!N23 -> -1056000 | O18: =-IS!O23 -> -1056000 | P18: =-IS!P23 -> -1056000 | Q18: =-IS!Q23 -> -1056000
D19: Financing Operations
D20: =IS!D18 -> Interest income | M20: =IS!M18 -> 4717297.2 | N20: =IS!N18 -> 3287130.7 | O20: =IS!O18 -> 3927819.8 | P20: =IS!P18 -> 4758814.3 | Q20: =IS!Q18 -> 5944666.1
D21: =IS!D19 -> Interest Expense | M21: =-IS!M19 -> -25327743 | N21: =-IS!N19 -> -23564196 | O21: =-IS!O19 -> -23844196 | P21: =-IS!P19 -> -21049065 | Q21: =-IS!Q19 -> -12495151
D22: =IS!D20 -> Net Foreign Exchange Loss | M22: =-IS!M20 -> -7851981 | N22: =-IS!N20 -> -7851981 | O22: =-IS!O20 -> -7851981 | P22: =-IS!P20 -> -7851981 | Q22: =-IS!Q20 -> -7851981
D24: =IS!D22 -> Current Tax Expense | M24: =-IS!M22 -> -20012160 | N24: =-IS!N22 -> -27509216 | O24: =-IS!O22 -> -36655044 | P24: =-IS!P22 -> -48846925 | Q24: =-IS!Q22 -> -65436802
D26: Total Cash Flow from Operations | M26: =SUM(M15:M24) -> 21175940 | N26: =SUM(N15:N24) -> 75586576 | O26: =SUM(O15:O24) -> 95670166 | P26: =SUM(P15:P24) -> 1.2363471e+08 | Q26: =SUM(Q15:Q24) -> 1.6221521e+08
C28: Cash Flow from Investing
D29: =Calc!D109 -> Capex | M29: =-Calc!M109 -> -13977841 | N29: =-Calc!N109 -> -14242042 | O29: =-Calc!O109 -> -14511299 | P29: =-Calc!P109 -> -14785710 | Q29: =-Calc!Q109 -> -15065373
D31: Total Cash Flow from Investing | M31: =M29 -> -13977841 | N31: =N29 -> -14242042 | O31: =O29 -> -14511299 | P31: =P29 -> -14785710 | Q31: =Q29 -> -15065373
C33: Cash Flow from Financing
D35: ="Change in "& Calc!C115 -> Change in Share capital | M35: =Calc!M117 -> 0 | N35: =Calc!N117 -> 0 | O35: =Calc!O117 -> 0 | P35: =Calc!P117 -> 0 | Q35: =Calc!Q117 -> 0
D36: ="Change in "&Calc!C120 -> Change in Share premium | M36: =Calc!M122 -> 0 | N36: =Calc!N122 -> 0 | O36: =Calc!O122 -> 0 | P36: =Calc!P122 -> 0 | Q36: =Calc!Q122 -> 0
D37: ="Change in "& Calc!C125 -> Change in Share based payment reserve | M37: =Calc!M127 -> 0 | N37: =Calc!N127 -> 0 | O37: =Calc!O127 -> 0 | P37: =Calc!P127 -> 0 | Q37: =Calc!Q127 -> 0
D38: =Calc!D173 -> Total New Debt Issued | M38: =Calc!M173 -> 5000000 | N38: =Calc!N173 -> 1000000 | O38: =Calc!O173 -> 6000000 | P38: =Calc!P173 -> 3000000 | Q38: =Calc!Q173 -> 2000000
D39: =Calc!D174 -> Total Repayments | M39: =-Calc!M174 -> -8293512 | N39: =-Calc!N174 -> 0 | O39: =-Calc!O174 -> -5000000 | P39: =-Calc!P174 -> -1000000 | Q39: =-Calc!Q174 -> -109589709
D40: =Calc!D162 -> Dividend Paid | M40: =-Calc!M162 -> -39658749 | N40: =-Calc!N162 -> -46327306 | O40: =-Calc!O162 -> -61384004 | P40: =-Calc!P162 -> -81202706 | Q40: =-Calc!Q162 -> -1.0809522e+08
D41: Overdraft - New Issue (or Repayment) | M41: =Calc!M424 -> 0 | N41: =Calc!N424 -> 0 | O41: =Calc!O424 -> 0 | P41: =Calc!P424 -> 0 | Q41: =Calc!Q424 -> 0
D43: Total Cash Flow from Financing | M43: =SUM(M35:M41) -> -42952261 | N43: =SUM(N35:N41) -> -45327306 | O43: =SUM(O35:O41) -> -60384004 | P43: =SUM(P35:P41) -> -79202706 | Q43: =SUM(Q35:Q41) -> -2.1568493e+08
D45: Total Cash Generated in the Year | M45: =M26+M31+M43 -> -35754162 | N45: =N26+N31+N43 -> 16017227 | O45: =O26+O31+O43 -> 20774862 | P45: =P26+P31+P43 -> 29646296 | Q45: =Q26+Q31+Q43 -> -68535093
C47: Cash Schedule
D48: Beginning Balance | M48: =L50 -> 117932430 | N48: =M50 -> 82178268 | O48: =N50 -> 98195495 | P48: =O50 -> 1.1897036e+08 | Q48: =P50 -> 1.4861665e+08
D49: =D45 -> Total Cash Generated in the Year | M49: =M45 -> -35754162 | N49: =N45 -> 16017227 | O49: =O45 -> 20774862 | P49: =P45 -> 29646296 | Q49: =Q45 -> -68535093
D50: Ending Balance | L50: =BS!L23 -> 117932430 | M50: =SUM(M48:M49) -> 82178268 | N50: =SUM(N48:N49) -> 98195495 | O50: =SUM(O48:O49) -> 1.1897036e+08 | P50: =SUM(P48:P49) -> 1.4861665e+08 | Q50: =SUM(Q48:Q49) -> 80081560
E58: Note: Cash balances can not be less than 0 because the overdraft schedule will take care of it by borrowing more cash

Sheet Ratios
B2: =company -> Nestle Nigeria
C3: Ratio Analysis
D4: =Live_Scenario -> Live Scenario: Base Case | H4: Start Date | J4: =I5+1 -> 43831 | K4: =J5+1 -> 44197 | L4: =K5+1 -> 44562 | M4: =L5+1 -> 44927 | N4: =M5+1 -> 45292 | O4: =N5+1 -> 45658 | P4: =O5+1 -> 46023 | Q4: =P5+1 -> 46388
D5: ="Audit Check: "& Audit_check -> Audit Check: OK | H5: End Date | I5: =EOMONTH(J5,-months_in_period) -> 43830 | J5: =EOMONTH(K5,-months_in_period) -> 44196 | K5: =EOMONTH(L5,-months_in_period) -> 44561 | L5: =Date_last_historical -> 44926 | M5: =EOMONTH(L5,months_in_period) -> 45291 | N5: =EOMONTH(M5,months_in_period) -> 45657 | O5: =EOMONTH(N5,months_in_period) -> 46022 | P5: =EOMONTH(O5,months_in_period) -> 46387 | Q5: =EOMONTH(P5,months_in_period) -> 46752
D6: Actual | J6: =(J5<=Date_last_historical)*1 -> 1 | K6: =(K5<=Date_last_historical)*1 -> 1 | L6: =(L5<=Date_last_historical)*1 -> 1 | M6: =(M5<=Date_last_historical)*1 -> 0 | N6: =(N5<=Date_last_historical)*1 -> 0 | O6: =(O5<=Date_last_historical)*1 -> 0 | P6: =(P5<=Date_last_historical)*1 -> 0 | Q6: =(Q5<=Date_last_historical)*1 -> 0
D7: Forecast | J7: =(J5>=Date_last_historical)*1 -> 0 | K7: =(K5>=Date_last_historical)*1 -> 0 | L7: =(L5>Date_last_historical)*1 -> 0 | M7: =(M5>=Date_last_historical)*1 -> 1 | N7: =(N5>=Date_last_historical)*1 -> 1 | O7: =(O5>=Date_last_historical)*1 -> 1 | P7: =(P5>=Date_last_historical)*1 -> 1 | Q7: =(Q5>=Date_last_historical)*1 -> 1
D8: Description | E8: Units | F8: Inputs | I8: Row Totals | J8: Hist | K8: Hist | L8: Hist | M8: Proj | N8: Proj | O8: Proj | P8: Proj | Q8: Proj
B9: Profitability Ratios
D10: Gross Profit Margin | J10: =IS!J12/IS!J10 -> 0.43289219 | K10: =IS!K12/IS!K10 -> 0.39089596 | L10: =IS!L12/IS!L10 -> 0.36314821 | M10: =IS!M12/IS!M10 -> 0.3429 | N10: =IS!N12/IS!N10 -> 0.3429 | O10: =IS!O12/IS!O10 -> 0.3429 | P10: =IS!P12/IS!P10 -> 0.3429 | Q10: =IS!Q12/IS!Q10 -> 0.3429
D11: Operating Profit Margin | J11: =IS!J14/IS!J10 -> 0.24986895 | K11: =IS!K14/IS!K10 -> 0.22798301 | L11: =IS!L14/IS!L10 -> 0.21466002 | M11: =IS!M14/IS!M10 -> 0.19441181 | N11: =IS!N14/IS!N10 -> 0.19441181 | O11: =IS!O14/IS!O10 -> 0.19441181 | P11: =IS!P14/IS!P10 -> 0.19441181 | Q11: =IS!Q14/IS!Q10 -> 0.19441181
D12: Net Profit Margin | J12: =IS!J24/IS!J10 -> 0.13658725 | K12: =IS!K24/IS!K10 -> 0.11379971 | L12: =IS!L24/IS!L10 -> 0.10958679 | M12: =IS!M24/IS!M10 -> 0.082128487 | N12: =IS!N24/IS!N10 -> 0.09127354 | O12: =IS!O24/IS!O10 -> 0.098767968 | P12: =IS!P24/IS!P10 -> 0.10713065 | Q12: =IS!Q24/IS!Q10 -> 0.11700449
D13: Return on Assets
D14: Return on Equity
D15: Return on Capital Employed | J15: =IS!J21/(BS!J25-BS!J48) -> 0.69889428 | K15: =IS!K21/(BS!K25-BS!K48) -> 0.53647306 | L15: =IS!L21/(BS!L25-BS!L48) -> 0.34689749 | M15: =IS!M21/(BS!M25-BS!M48) -> 0.31106805 | N15: =IS!N21/(BS!N25-BS!N48) -> 0.39525007 | O15: =IS!O21/(BS!O25-BS!O48) -> 0.48311649 | P15: =IS!P21/(BS!P25-BS!P48) -> 0.58146609 | Q15: =IS!Q21/(BS!Q25-BS!Q48) -> 1.0940847
B17: Liquidity Ratios
D18: Current Ratio | J18: =BS!J24/BS!J48 -> 0.96514296 | K18: =BS!K24/BS!K48 -> 1.0591294 | L18: =BS!L24/BS!L48 -> 1.3964199 | M18: =BS!M24/BS!M48 -> 1.4767652 | N18: =BS!N24/BS!N48 -> 1.434326 | O18: =BS!O24/BS!O48 -> 1.4051914 | P18: =BS!P24/BS!P48 -> 1.3877508 | Q18: =BS!Q24/BS!Q48 -> 1.1277012
D19: Quick Ratio | J19: =(BS!J24-BS!J22)/BS!J48 -> 0.63756961 | K19: =(BS!K24-BS!K22)/BS!K48 -> 0.75659602 | L19: =(BS!L24-BS!L22)/BS!L48 -> 0.97586553 | M19: =(BS!M24-BS!M22)/BS!M48 -> 1.1047542 | N19: =(BS!N24-BS!N22)/BS!N48 -> 1.0701259 | O19: =(BS!O24-BS!O22)/BS!O48 -> 1.0471521 | P19: =(BS!P24-BS!P22)/BS!P48 -> 1.0363444 | Q19: =(BS!Q24-BS!Q22)/BS!Q48 -> 0.78381684
D20: Cash Ratio | J20: =BS!J23/BS!J48 -> 0.3682262 | K20: =BS!K23/BS!K48 -> 0.51573899 | L20: =BS!L23/BS!L48 -> 0.56142972 | M20: =BS!M23/BS!M48 -> 0.44707841 | N20: =BS!N23/BS!N48 -> 0.42868931 | O20: =BS!O23/BS!O48 -> 0.41852437 | P20: =BS!P23/BS!P48 -> 0.42059926 | Q20: =BS!Q23/BS!Q48 -> 0.18179275
B22: Leverage Ratios
D23: Debt-to-Equity Ratio | L23: =Calc!L175/BS!L32 -> 5.1268997 | M23: =Calc!M175/BS!M32 -> 3.873253 | N23: =Calc!N175/BS!N32 -> 2.9776265 | O23: =Calc!O175/BS!O32 -> 2.2845366 | P23: =Calc!P175/BS!P32 -> 1.7603722 | Q23: =Calc!Q175/BS!Q32 -> 0.41424128
D24: Debt Ratio | L24: =Calc!L175/BS!L25 -> 0.37417733 | M24: =Calc!M175/BS!M25 -> 0.384376 | N24: =Calc!N175/BS!N25 -> 0.33634655 | O24: =Calc!O175/BS!O25 -> 0.29157288 | P24: =Calc!P175/BS!P25 -> 0.25099978 | Q24: =Calc!Q175/BS!Q25 -> 0.076799536
D25: Interest Coverage Ratio | J25: =IS!J11/IS!J13 -> 3.0985562 | K25: =IS!K11/IS!K13 -> 3.7388315 | L25: =IS!L11/IS!L13 -> 4.2889054 | M25: =IS!M11/IS!M13 -> 4.4252678 | N25: =IS!N11/IS!N13 -> 4.4252678 | O25: =IS!O11/IS!O13 -> 4.4252678 | P25: =IS!P11/IS!P13 -> 4.4252678 | Q25: =IS!Q11/IS!Q13 -> 4.4252678
D26: Equity Ratio | J26: =BS!J32/BS!J25 -> 0.11900394 | K26: =BS!K32/BS!K25 -> 0.068908939 | L26: =BS!L32/BS!L25 -> 0.072983158 | M26: =BS!M32/BS!M25 -> 0.099238546 | N26: =BS!N32/BS!N25 -> 0.11295794 | O26: =BS!O32/BS!O25 -> 0.12762889 | P26: =BS!P32/BS!P25 -> 0.14258336 | Q26: =BS!Q32/BS!Q25 -> 0.18539807
B28: Efficiency Ratios
B32: Market Ratios

Sheet Vals
B2: =company -> Nestle Nigeria
C3: Valuation Analysis
D4: =Live_Scenario -> Live Scenario: Base Case | H4: Start Date | J4: =I5+1 -> 43831 | K4: =J5+1 -> 44197 | L4: =K5+1 -> 44562 | M4: =L5+1 -> 44927 | N4: =M5+1 -> 45292 | O4: =N5+1 -> 45658 | P4: =O5+1 -> 46023 | Q4: =P5+1 -> 46388
D5: ="Audit Check: "& Audit_check -> Audit Check: OK | H5: End Date | I5: =EOMONTH(J5,-months_in_period) -> 43830 | J5: =EOMONTH(K5,-months_in_period) -> 44196 | K5: =EOMONTH(L5,-months_in_period) -> 44561 | L5: =Date_last_historical -> 44926 | M5: =EOMONTH(L5,months_in_period) -> 45291 | N5: =EOMONTH(M5,months_in_period) -> 45657 | O5: =EOMONTH(N5,months_in_period) -> 46022 | P5: =EOMONTH(O5,months_in_period) -> 46387 | Q5: =EOMONTH(P5,months_in_period) -> 46752
D6: Actual | J6: =(J5<=Date_last_historical)*1 -> 1 | K6: =(K5<=Date_last_historical)*1 -> 1 | L6: =(L5<=Date_last_historical)*1 -> 1 | M6: =(M5<=Date_last_historical)*1 -> 0 | N6: =(N5<=Date_last_historical)*1 -> 0 | O6: =(O5<=Date_last_historical)*1 -> 0 | P6: =(P5<=Date_last_historical)*1 -> 0 | Q6: =(Q5<=Date_last_historical)*1 -> 0
D7: Forecast | J7: =(J5>=Date_last_historical)*1 -> 0 | K7: =(K5>=Date_last_historical)*1 -> 0 | L7: =(L5>Date_last_historical)*1 -> 0 | M7: =(M5>=Date_last_historical)*1 -> 1 | N7: =(N5>=Date_last_historical)*1 -> 1 | O7: =(O5>=Date_last_historical)*1 -> 1 | P7: =(P5>=Date_last_historical)*1 -> 1 | Q7: =(Q5>=Date_last_historical)*1 -> 1
D8: Description | E8: Units | F8: Inputs | I8: Row Totals | J8: Hist | K8: Hist | L8: Hist | M8: Proj | N8: Proj | O8: Proj | P8: Proj | Q8: Proj
